Workbook

Sheet REGLAS
A1: ASPECTO | B1: REGLA | C1: ORIGEN | H1: ¿EN QUE RANGO DE EDAD TE ENCUENTRAS?
A2: TOTAL DE REGISTROS | B2: 479 PERSONAS FICTICIAS | C2: SG-04
A3: EDAD PERMITIDA | B3: DE 18 A 28 AÑOS | C3: SG-04 | Y3: =IF(I3="Tengo un emprendimiento o quiero iniciar uno",X3,"")
A4: URBANA CONSOLIDADA | B4: 256 REGISTROS | C4: SG-04 | Y4: =IF(I4="Tengo un emprendimiento o quiero iniciar uno",X4,"")
A5: URBANA PERIFERICA | B5: 113 REGISTROS | C5: SG-04 | Y5: =IF(I5="Tengo un emprendimiento o quiero iniciar uno",X5,"")
A6: CENTROS POBLADOS Y RURAL | B6: 110 REGISTROS | C6: SG-04 | Y6: =IF(I6="Tengo un emprendimiento o quiero iniciar uno",X6,"")
A7: PRUEBA DEL PROFESOR | B7: EXCLUIR LA FILA 3 DE LAHOJA DE RESPUESTAS INICIALES | C7: CONFIRMADO POR EL ESTUDIANTE | Y7: =IF(I7="Tengo un emprendimiento o quiero iniciar uno",X7,"")
A8: RESPUESTAS INICIALES | B8: REFERENCI: NO INCLUIR ENTRE 479 FICTICIAS | C8: HD-01 | Y8: =IF(I8="Tengo un emprendimiento o quiero iniciar uno",X8,"")
A9: UBICACIÓN DE LA EDAD | B9: COLUMNA H DE LA HOJA DE RESPUESTAS INICIALES | C9: ECXEL DE LA ENCUESTA | Y9: =IF(I9="Tengo un emprendimiento o quiero iniciar uno",X9,"")
A10: EDAD FUERA DEL RANGO | B10: FILA 5; 29 AÑOS; NO USAR COMO REFERENCIA DE LA POBLACION DE 18 A 28 AÑOS | C10: REVISION DEL EXCEL | Y10: =IF(I10="Tengo un emprendimiento o quiero iniciar uno",X10,"")
A11: PARTICIPACION NO ACEPTADA | B11: FILA 4; NO ACEPTA PARTICIPAR; EXCLUIR DE LOS DATOS DE REFERENCIA | C11: REVISION DE LA COLUMNA F | Y11: =IF(I11="Tengo un emprendimiento o quiero iniciar uno",X11,"")
A12: UBICACIÓN DE RESIDENCIA | B12: COLUMNA J DE LA HOJA DE RESPUESTAS INICIALES | C12: EXCEL DE LA ENCUESTA | Y12: =IF(I12="Tengo un emprendimiento o quiero iniciar uno",X12,"")
A13: RESPUESTAS DE RESIDENCIA OBSERVADAS | B13: RURAL; URBANO PERIFERICO | C13: REVISION DE LAS RESPUESTAS INICIALES | Y13: =IF(I13="Tengo un emprendimiento o quiero iniciar uno",X13,"")
A14: OPCIONES PERMITIDAS DE RESIDENCIA | B14: URBANO; URBANO PERIFERICO;CENTRO POBLADO; RURAL | C14: FORMULARIO APROBADO | Y14: =IF(I14="Tengo un emprendimiento o quiero iniciar uno",X14,"")
... A135: Dificultades de acceso | B135: Variar opciones individuales y combinadas para los 479 registros. “Ninguna” aparece sola; “Otros” no se utiliza. Se completa aunque sea opcional | C135: Supuesto académico; sin diferencias territoriales impuestas | Y135: =IF(I135="Tengo un emprendimiento o quiero iniciar uno",X135,"")
A136: Servicios conocidos | B136: Una sola respuesta por registro: oficina de orientación laboral; ferias de empleo; programas de emprendimiento; no conozco ninguno. Reparto aproximadamente uniforme; se completa aunque sea opcional | Y136: =IF(I136="Tengo un emprendimiento o quiero iniciar uno",X136,"")
A137: Modalidad preferida | B137: Reparto aproximadamente uniforme entre Presencial, Virtual, Presencial y virtual, y Me es indiferente. Se completa para los 479 registros | C137: Supuesto académico; no representa preferencias reales | Y137: =IF(I137="Tengo un emprendimiento o quiero iniciar uno",X137,"")
A138: Horario preferido | B138: Reparto aproximadamente uniforme entre Diurno, Nocturno, Mañana entre semana y Fines de semana. Se completa para los 479 registros | C138: Supuesto académico; no representa preferencias reales | Y138: =IF(I138="Tengo un emprendimiento o quiero iniciar uno",X138,"")
A139: Medio preferido para recibir información | B139: Reparto aproximadamente uniforme entre WhatsApp, Correo electrónico, Redes sociales y Celular. “Otro” no se utiliza. Se completa para los 479 registros | C139: Supuesto académico; no representa preferencias reales | Y139: =IF(I139="Tengo un emprendimiento o quiero iniciar uno",X139,"")
A140: Alcance del perfil de emprendimiento | B140: Los 39 registros responden preguntas iniciales, emprendimiento y perfilamiento común. J a U quedan vacías por el recorrido simulado; no se interpreta como ausencia de trabajo o búsqueda | C140: Simplificación académica y limitación de la simulación | Y140: =IF(I140="Tengo un emprendimiento o quiero iniciar uno",X140,"")
Y141: =IF(I141="Tengo un emprendimiento o quiero iniciar uno",X141,"")
Y142: =IF(I142="Tengo un emprendimiento o quiero iniciar uno",X142,"")
Y143: =IF(I143="Tengo un emprendimiento o quiero iniciar uno",X143,"")
Y144: =IF(I144="Tengo un emprendimiento o quiero iniciar uno",X144,"")
Y145: =IF(I145="Tengo un emprendimiento o quiero iniciar uno",X145,"")
Y146: =IF(I146="Tengo un emprendimiento o quiero iniciar uno",X146,"")
Y147: =IF(I147="Tengo un emprendimiento o quiero iniciar uno",X147,"")
Y148: =IF(I148="Tengo un emprendimiento o quiero iniciar uno",X148,"")
Y149: =IF(I149="Tengo un emprendimiento o quiero iniciar uno",X149,"")
Y150: =IF(I150="Tengo un emprendimiento o quiero iniciar uno",X150,"")
Y151: =IF(I151="Tengo un emprendimiento o quiero iniciar uno",X151,"")
Y152: =IF(I152="Tengo un emprendimiento o quiero iniciar uno",X152,"")
... Y480: =IF(I480="Tengo un emprendimiento o quiero iniciar uno",X480,"")

Sheet RECORRIDOS
A1: Situación laboral | B1: Preguntas que responde | C1: Preguntas que quedan vacías
A2: Actualmente no trabajo y estoy buscando empleo | B2: Preguntas iniciales 1 a 6; búsqueda de empleo 13 a 18; perfilamiento común desde la 24 | C2: Trabajo actual 7 a 12. Emprendimiento 19 a 23 pendiente de definir según interés
A3: Busco mi primer empleo | B3: Preguntas iniciales 1 a 6; búsqueda de empleo 13 a 18; perfilamiento común desde la 24 | C3: Trabajo actual 7 a 12. Emprendimiento 19 a 23 pendiente de definir según interés
A4: Trabajo actualmente como empleado | B4: Preguntas 1 a 12; búsqueda de empleo 13 a 18 según su situación; perfilamiento común desde la 24 | C4: Emprendimiento 19 a 23: pendiente de definir según interés
A5: Trabajo de manera independiente | B5: Preguntas 1 a 12; búsqueda de empleo 13 a 18 según su situación; perfilamiento común desde la 24 | C5: Emprendimiento 19 a 23: pendiente de definir según interés
A6: Estudio y quiero comenzar a trabajar | B6: Preguntas 1 a 6; búsqueda de empleo 13 a 18; perfilamiento común desde la 24 | C6: Trabajo actual 7 a 12 vacías; emprendimiento 19 a 23 según interés
A7: Tengo un emprendimiento o quiero iniciar uno | B7: Preguntas 1 a 6; emprendimiento 19 a 23; perfilamiento común desde la 24 | C7: Preguntas 7 a 18 sin recoger en este recorrido; situación de empleo adicional desconocida

Sheet RESUMEN TERRITORIAL
A3: DOMINIO TERRITORIAL | B3: PORCENTAJE DE REGISTROS | C3: NUMERO D REGISTROS
A4: CENTROS POBLADOS Y RURAL | B4: 0.22964509 | C4: 110
A5: Urbana Consolidada | B5: 0.53444676 | C5: 256
A6: URBANA PERIFÉRICA | B6: 0.23590814 | C6: 113
A7: Total general | B7: 1 | C7: 479
E20: Dominio territorial | F20: Numero de Registros
E21: Centros Poblados y rural | F21: =C4 -> 110
E22: =A5 -> Urbana Consolidada | F22: =C5 -> 256
E23: Urbana Periferica | F23: =C6 -> 113

Sheet BASE SIMULADA
A1: ID artificial. | B1: Dominio territorial. | C1: ¿Aceptas participar voluntariamente en este formulario y autorizas el uso de la información proporcionada para los fines académicos anteriormente descritos? | D1: ¿Con que género te identificas? | E1: ¿En que rango de edad te encuentras? | F1: ¿Cuál es tu edad? | G1: ¿En qué zona vives actualmente? | H1: ¿Cuál es tu nivel educativo? | I1: ¿Cuál de las siguientes opciones describe mejor tu situación actual? | J1: ¿Cuál describe mejor tu tipo de contrato o trabajo actual? | K1: ¿Cuánto tiempo llevas trabajando? | L1: ¿Tú trabajo está relacionado con tu formación o habilidades? | M1: ¿Qué tan satisfecho/a estás con tus condiciones laborales actuales? | N1: ¿Qué aspecto te gustaría mejorar principalmente de tu situación laboral? | O1: ¿Actualmente estás interesado/a en encontrar un empleo diferente? | P1: ¿Cuánto tiempo llevas buscando empleo? | Q1: ¿Tienes actualmente una hoja de vida actualizada? | R1: ¿Has tenido anteriormente un empleo o trabajo remunerado? | S1: ¿Dónde buscas o buscarias principalmente oportunidades laborales? | T1: ¿Cuál consideras que es tu principal dificultad para conseguir empleo? | U1: ¿Has participado en una entrevista laboral durante los últimos 6 meses? | V1: ¿Cuál describe mejor tu situación? | W1: Si tienes o estás iniciando un emprendimiento, ¿en qué etapa se encuentra? | X1: ¿Cuál es la principal dificultad para iniciar o fortalecer tu emprendimiento? | Y1: ¿Qué tipo de apoyo consideras más importante? | Z1: ¿Has participado anteriormente en algún programa de apoyo al emprendimiento? | AA1: Indica qué tan preparado/a te sientes para realizar las siguientes actividades relacionadas con el empleo..Elaborar o actualizar mi hoja de vida. | AB1: Indica qué tan preparado/a te sientes para realizar las siguientes actividades relacionadas con el empleo..Buscar vacantes por internet. | AC1: Indica qué tan preparado/a te sientes para realizar las siguientes actividades relacionadas con el empleo..Presentarme a una entrevista laboral. | AD1: Indica qué tan preparado/a te sientes para realizar las siguientes actividades relacionadas con el empleo..Explicar mis habilidades y experiencia. | AE1: Indica qué tan preparado/a te sientes para realizar las siguientes actividades relacionadas con el empleo..Utilizar herramientas digitales para trabajar. | AF1: ¿Qué competencias te gustaría fortalecer? | AG1: ¿Qué situaciones dificultan actualmente tu acceso a oportunidades laborales o de formación? | AH1: ¿Cuáles de los siguientes servicios conoces? | AI1: ¿Cómo prefieres participar en actividades de empleabilidad? | AJ1: ¿Qué horario te resulta más conveniente? | AK1: ¿Por qué medio preferirías recibir información sobre oportunidades laborales?
A2: ="SG"&TEXT(ROW()-1,"000") -> SG001 | B2: Urbana Consolidada | C2: SI, ACEPTO PARTICIPAR | D2: =IF(MOD((ROW()-2)*137,479)<230,"Masculino",IF(MOD((ROW()-2)*137,479)<460,"Femenino",IF(MOD((ROW()-2)*137,479)<470,"Otro","No quiero responder"))) -> Masculino | E2: =CHOOSE(MOD(ROW()-2,5)+1,"De 18 a 20 años","De 20 a 22 años","De 22 a 24 años","De 24 a 26 años","De 26 a 28 años") -> De 18 a 20 años | F2: =CHOOSE(MOD(ROW()-2,5)+1,18,20,22,24,26)+MOD(INT((ROW()-2)/5),IF(MOD(ROW()-2,5)=4,3,2)) -> 18 | G2: URBANA | H2: =_xlfn.LET(_xlpm.grupo,MOD(ROW()-2,5),_xlpm.turno,INT((ROW()-2)/5),_xlpm.orden,MOD(_xlpm.turno*37,IF(_xlpm.grupo=4,95,96)),CHOOSE(_xlpm.grupo+1,IF(_xlpm.orden<60,"Bachiller",IF(_xlpm.orden<84,"Técnico","Tecnólogo")),IF(_xlpm.orden<36,"Bachiller",IF(_xlpm.orden<66,"Técnico","Tecnólogo")),IF(_xlpm.orden<24,"Bachiller",IF(_xlpm.orden<48,"Técnico",IF(_xlpm.orden<72,"Tecnólogo","Profesional"))),IF(_xlpm.orden<12,"Bachiller",IF(_xlpm.orden<30,"Técnico",IF(_xlpm.orden<54,"Tecnólogo",IF(_xlpm.orden<90,"Profesional","Posgrado")))),IF(_xlpm.orden<10,"Bachiller",IF(_xlpm.orden<25,"Técnico",IF(_xlpm.orden<45,"Tecnólogo",IF(_xlpm.orden<85,"Profesional","Posgrado")))))) -> Bachiller | I2: =_xlfn.LET(_xlpm.orden,MOD((ROW()-2)*173,479),IF(_xlpm.orden<150,"Trabajo actualmente como empleado",IF(_xlpm.orden<230,"Trabajo de manera independiente",IF(_xlpm.orden<320,"Actualmente no trabajo y estoy buscando empleo",IF(_xlpm.orden<380,"Busco mi primer empleo",IF(_xlpm.orden<440,"Estudio y quiero comenzar a trabajar","Tengo un emprendimiento o quiero iniciar uno")))))) -> Trabajo actualmente como empleado | J2: =IF(I2="Trabajo actualmente como empleado",IF(MOD((COUNTIF($I$2:I2,"Trabajo actualmente como empleado")-1)*37,150)<100,"Empleado con contrato","Empleado sin contrato formal"),IF(I2="Trabajo de manera independiente","Trabajo independiente","")) -> Empleado con contrato | K2: =IF(OR(I2="Trabajo actualmente como empleado",I2="Trabajo de manera independiente"),CHOOSE(MOD(COUNTIF($I$2:I2,I2)-1,4)+1,"Menos de 3 meses","De 3 a 6 meses","De 7 a 12 meses","Más de un año"),"") -> Menos de 3 meses | L2: =IF(OR(I2="Trabajo actualmente como empleado",I2="Trabajo de manera independiente"),CHOOSE(MOD(COUNTIF($I$2:I2,I2)-1,3)+1,"Sí, completamente","Parcialmente","No"),"") -> Sí, completamente | M2: =IF(OR(I2="Trabajo actualmente como empleado",I2="Trabajo de manera independiente"),CHOOSE(MOD(INT((COUNTIF($I$2:I2,I2)-1)/3),4)+1,"1- Muy satisfecho/a","2- Satisfecho/a","3- Insatisfecho/a","4- Muy insatisfecho/a"),"") -> 1- Muy satisfecho/a | N2: =IF(OR(I2="Trabajo actualmente como empleado",I2="Trabajo de manera independiente"),_xlfn.LET(_xlpm.opcion,MOD(INT((COUNTIF($I$2:I2,I2)-1)/5),6)+1,CHOOSE(IF(AND(_xlpm.opcion=6,L2="Sí, completamente"),5,_xlpm.opcion),"Salario","Estabilidad laboral","Horario","Acceso a prestaciones","Oportunidades de crecimiento","Trabajar en un área relacionada con mi formación")),"") -> Salario | O2: =IF(OR(I2="Trabajo actualmente como empleado",I2="Trabajo de manera independiente"),_xlfn.LET(_xlpm.turno,MOD(COUNTIF($I$2:I2,I2)-1,5),_xlpm.nivel,VALUE(LEFT(M2,1)),IF(_xlpm.turno=4,"No estoy seguro/a",IF(_xlpm.turno<IF(_xlpm.nivel<=2,1,3),"Sí","No"))),"") -> Sí | P2: =_xlfn.LET(_xlpm.perfil,I2,_xlpm.turno,COUNTIF($I$2:I2,_xlpm.perfil)-1,_xlpm.busca,OR(_xlpm.perfil="Actualmente no trabajo y estoy buscando empleo",_xlpm.perfil="Busco mi primer empleo"),_xlpm.trabaja,OR(_xlpm.perfil="Trabajo actualmente como empleado",_xlpm.perfil="Trabajo de manera independiente"),IF(_xlpm.busca,CHOOSE(MOD(_xlpm.turno*3,4)+1,"Menos de 1 mes","Entre 1 y 3 meses","Entre 4 y 6 meses","Más de 6 meses"),IF(OR(_xlpm.trabaja,_xlpm.perfil="Estudio y quiero comenzar a trabajar"),IF(AND(_xlpm.trabaja,O2="No"),"Todavía no he iniciado una búsqueda activa",CHOOSE(MOD(_xlpm.turno*3,5)+1,"Menos de 1 mes","Entre 1 y 3 meses","Entre 4 y 6 meses","Más de 6 meses","Todavía no he iniciado una búsqueda activa")),""))) -> Menos de 1 mes | Q2: =IF(I2="Tengo un emprendimiento o quiero iniciar uno","",CHOOSE(MOD(INT((COUNTIF($I$2:I2,I2)-1)/7),3)+1,"Sí","No","Tengo una pero necesito actualizarla")) -> Sí | R2: =IF(I2="Tengo un emprendimiento o quiero iniciar uno","",IF(I2="Busco mi primer empleo","No",IF(MOD(COUNTIF($I$2:I2,I2)-1,2)=0,"Sí","No"))) -> Sí | S2: =IF(I2="Tengo un emprendimiento o quiero iniciar uno","",CHOOSE(MOD(INT((COUNTIF($I$2:I2,I2)-1)/3),10)+1,"Portales de empleo","Redes sociales","Familiares o conocidos","Empresas directamente","Ferias de empleo","Instituciones públicas","Institución educativa","No sé dónde buscar","Portales de empleo;Redes sociales","Familiares o conocidos;Empresas directamente")) -> Portales de empleo | T2: =IF(I2="Tengo un emprendimiento o quiero iniciar uno","",_xlfn.LET(_xlpm.opcion,MOD(INT((COUNTIF($I$2:I2,I2)-1)/4),6)+1,CHOOSE(IF(AND(_xlpm.opcion=3,Q2="Sí"),1,_xlpm.opcion),"Falta de experiencia","Falta de formación","Dificultades con la hoja de vida","Horarios disponibles","Transporte","Internet"))) -> Falta de experiencia | U2: =IF(I2="Tengo un emprendimiento o quiero iniciar uno","",IF(MOD(INT((COUNTIF($I$2:I2,I2)-1)/3),2)=0,"Sí","No")) -> Sí | V2: =IF(I2="Tengo un emprendimiento o quiero iniciar uno",CHOOSE(MOD(COUNTIF($I$2:I2,I2)-1,3)+1,"Tengo un emprendimiento","Estoy iniciando un emprendimiento","Me interesa emprender"),"") | W2: =IF(V2="Tengo un emprendimiento","Funcionamiento estable",IF(V2="Estoy iniciando un emprendimiento","Inicio","")) | X2: =IF(I2="Tengo un emprendimiento o quiero iniciar uno",CHOOSE(MOD(COUNTIF($I$2:I2,I2)-1,5)+1,"Falta de financiación","Falta de conocimientos administrativos","Falta de conocimientos financieros","Falta de tiempo","Falta de herramientas"),"") | Y2: =IF(I2="Tengo un emprendimiento o quiero iniciar uno",X2,"") | Z2: =IF(I2="Tengo un emprendimiento o quiero iniciar uno",CHOOSE(INT(MOD((COUNTIF($I$2:I2,I2)-1)*7,39)/13)+1,"Sí","No","No conozco programas de ese tipo"),"") | AA2: =CHOOSE(INT(MOD((ROW()-2)*191,479)/120)+1,"No puedo hacerlo","Puedo hacerlo con ayuda","Puedo hacerlo con dificultad","Puedo hacerlo sin ayuda") -> No puedo hacerlo | AB2: =CHOOSE(INT(MOD((ROW()-2)*191,479)/120)+1,"No puedo hacerlo","Puedo hacerlo con ayuda","Puedo hacerlo con dificultad","Puedo hacerlo sin ayuda") -> No puedo hacerlo | AC2: =CHOOSE(INT(MOD((ROW()-2)*157+83,479)/120)+1,"No puedo hacerlo","Puedo hacerlo con ayuda","Puedo hacerlo con dificultad","Puedo hacerlo sin ayuda") -> No puedo hacerlo | AD2: =CHOOSE(INT(MOD((ROW()-2)*89+131,479)/120)+1,"No puedo hacerlo","Puedo hacerlo con ayuda","Puedo hacerlo con dificultad","Puedo hacerlo sin ayuda") -> Puedo hacerlo con ayuda | AE2: =CHOOSE(INT(MOD((ROW()-2)*73+179,479)/120)+1,"No puedo hacerlo","Puedo hacerlo con ayuda","Puedo hacerlo con dificultad","Puedo hacerlo sin ayuda") -> Puedo hacerlo con ayuda | AF2: =CHOOSE(MOD((ROW()-2)*61+23,10)+1,"Crear una hoja de vida","Preparación para entrevista","Comunicación","Liderazgo","Emprendimiento","Herramientas digitales","Educación financiera","Crear una hoja de vida;Preparación para entrevista","Comunicación;Liderazgo","Herramientas digitales;Educación financiera") -> Liderazgo | AG2: AH1 | AH2: =CHOOSE(INT(MOD((ROW()-2)*199+59,479)/120)+1,"Oficina de orientación laboral","Ferias de empleo","Programas de emprendimiento","No conozco ninguno") -> Oficina de orientación laboral | AI2: =CHOOSE(INT(MOD((ROW()-2)*127+71,479)/120)+1,"Presencial","Virtual","Presencial y virtual","Me es indiferente") -> Presencial | AJ2: =CHOOSE(INT(MOD((ROW()-2)*163+97,479)/120)+1,"Diurno","Nocturno","Mañana entre semana","Fines de semana") -> Diurno | AK2: =CHOOSE(INT(MOD((ROW()-2)*181+109,479)/120)+1,"WhatsApp","Correo electrónico","Redes sociales","Celular") -> WhatsApp
A3: ="SG"&TEXT(ROW()-1,"000") -> SG002 | B3: Urbana Consolidada | C3: SI, ACEPTO PARTICIPAR | D3: =IF(MOD((ROW()-2)*137,479)<230,"Masculino",IF(MOD((ROW()-2)*137,479)<460,"Femenino",IF(MOD((ROW()-2)*137,479)<470,"Otro","No quiero responder"))) -> Masculino | E3: =CHOOSE(MOD(ROW()-2,5)+1,"De 18 a 20 años","De 20 a 22 años","De 22 a 24 años","De 24 a 26 años","De 26 a 28 años") -> De 20 a 22 años | F3: =CHOOSE(MOD(ROW()-2,5)+1,18,20,22,24,26)+MOD(INT((ROW()-2)/5),IF(MOD(ROW()-2,5)=4,3,2)) -> 20 | G3: URBANA | H3: =_xlfn.LET(_xlpm.grupo,MOD(ROW()-2,5),_xlpm.turno,INT((ROW()-2)/5),_xlpm.orden,MOD(_xlpm.turno*37,IF(_xlpm.grupo=4,95,96)),CHOOSE(_xlpm.grupo+1,IF(_xlpm.orden<60,"Bachiller",IF(_xlpm.orden<84,"Técnico","Tecnólogo")),IF(_xlpm.orden<36,"Bachiller",IF(_xlpm.orden<66,"Técnico","Tecnólogo")),IF(_xlpm.orden<24,"Bachiller",IF(_xlpm.orden<48,"Técnico",IF(_xlpm.orden<72,"Tecnólogo","Profesional"))),IF(_xlpm.orden<12,"Bachiller",IF(_xlpm.orden<30,"Técnico",IF(_xlpm.orden<54,"Tecnólogo",IF(_xlpm.orden<90,"Profesional","Posgrado")))),IF(_xlpm.orden<10,"Bachiller",IF(_xlpm.orden<25,"Técnico",IF(_xlpm.orden<45,"Tecnólogo",IF(_xlpm.orden<85,"Profesional","Posgrado")))))) -> Bachiller | I3: =_xlfn.LET(_xlpm.orden,MOD((ROW()-2)*173,479),IF(_xlpm.orden<150,"Trabajo actualmente como empleado",IF(_xlpm.orden<230,"Trabajo de manera independiente",IF(_xlpm.orden<320,"Actualmente no trabajo y estoy buscando empleo",IF(_xlpm.orden<380,"Busco mi primer empleo",IF(_xlpm.orden<440,"Estudio y quiero comenzar a trabajar","Tengo un emprendimiento o quiero iniciar uno")))))) -> Trabajo de manera independiente | J3: =IF(I3="Trabajo actualmente como empleado",IF(MOD((COUNTIF($I$2:I3,"Trabajo actualmente como empleado")-1)*37,150)<100,"Empleado con contrato","Empleado sin contrato formal"),IF(I3="Trabajo de manera independiente","Trabajo independiente","")) -> Trabajo independiente | K3: =IF(OR(I3="Trabajo actualmente como empleado",I3="Trabajo de manera independiente"),CHOOSE(MOD(COUNTIF($I$2:I3,I3)-1,4)+1,"Menos de 3 meses","De 3 a 6 meses","De 7 a 12 meses","Más de un año"),"") -> Menos de 3 meses | L3: =IF(OR(I3="Trabajo actualmente como empleado",I3="Trabajo de manera independiente"),CHOOSE(MOD(COUNTIF($I$2:I3,I3)-1,3)+1,"Sí, completamente","Parcialmente","No"),"") -> Sí, completamente | M3: =IF(OR(I3="Trabajo actualmente como empleado",I3="Trabajo de manera independiente"),CHOOSE(MOD(INT((COUNTIF($I$2:I3,I3)-1)/3),4)+1,"1- Muy satisfecho/a","2- Satisfecho/a","3- Insatisfecho/a","4- Muy insatisfecho/a"),"") -> 1- Muy satisfecho/a | N3: =IF(OR(I3="Trabajo actualmente como empleado",I3="Trabajo de manera independiente"),_xlfn.LET(_xlpm.opcion,MOD(INT((COUNTIF($I$2:I3,I3)-1)/5),6)+1,CHOOSE(IF(AND(_xlpm.opcion=6,L3="Sí, completamente"),5,_xlpm.opcion),"Salario","Estabilidad laboral","Horario","Acceso a prestaciones","Oportunidades de crecimiento","Trabajar en un área relacionada con mi formación")),"") -> Salario | O3: =IF(OR(I3="Trabajo actualmente como empleado",I3="Trabajo de manera independiente"),_xlfn.LET(_xlpm.turno,MOD(COUNTIF($I$2:I3,I3)-1,5),_xlpm.nivel,VALUE(LEFT(M3,1)),IF(_xlpm.turno=4,"No estoy seguro/a",IF(_xlpm.turno<IF(_xlpm.nivel<=2,1,3),"Sí","No"))),"") -> Sí | P3: =_xlfn.LET(_xlpm.perfil,I3,_xlpm.turno,COUNTIF($I$2:I3,_xlpm.perfil)-1,_xlpm.busca,OR(_xlpm.perfil="Actualmente no trabajo y estoy buscando empleo",_xlpm.perfil="Busco mi primer empleo"),_xlpm.trabaja,OR(_xlpm.perfil="Trabajo actualmente como empleado",_xlpm.perfil="Trabajo de manera independiente"),IF(_xlpm.busca,CHOOSE(MOD(_xlpm.turno*3,4)+1,"Menos de 1 mes","Entre 1 y 3 meses","Entre 4 y 6 meses","Más de 6 meses"),IF(OR(_xlpm.trabaja,_xlpm.perfil="Estudio y quiero comenzar a trabajar"),IF(AND(_xlpm.trabaja,O3="No"),"Todavía no he iniciado una búsqueda activa",CHOOSE(MOD(_xlpm.turno*3,5)+1,"Menos de 1 mes","Entre 1 y 3 meses","Entre 4 y 6 meses","Más de 6 meses","Todavía no he iniciado una búsqueda activa")),""))) -> Menos de 1 mes | Q3: =IF(I3="Tengo un emprendimiento o quiero iniciar uno","",CHOOSE(MOD(INT((COUNTIF($I$2:I3,I3)-1)/7),3)+1,"Sí","No","Tengo una pero necesito actualizarla")) -> Sí | R3: =IF(I3="Tengo un emprendimiento o quiero iniciar uno","",IF(I3="Busco mi primer empleo","No",IF(MOD(COUNTIF($I$2:I3,I3)-1,2)=0,"Sí","No"))) -> Sí | S3: =IF(I3="Tengo un emprendimiento o quiero iniciar uno","",CHOOSE(MOD(INT((COUNTIF($I$2:I3,I3)-1)/3),10)+1,"Portales de empleo","Redes sociales","Familiares o conocidos","Empresas directamente","Ferias de empleo","Instituciones públicas","Institución educativa","No sé dónde buscar","Portales de empleo;Redes sociales","Familiares o conocidos;Empresas directamente")) -> Portales de empleo | T3: =IF(I3="Tengo un emprendimiento o quiero iniciar uno","",_xlfn.LET(_xlpm.opcion,MOD(INT((COUNTIF($I$2:I3,I3)-1)/4),6)+1,CHOOSE(IF(AND(_xlpm.opcion=3,Q3="Sí"),1,_xlpm.opcion),"Falta de experiencia","Falta de formación","Dificultades con la hoja de vida","Horarios disponibles","Transporte","Internet"))) -> Falta de experiencia | U3: =IF(I3="Tengo un emprendimiento o quiero iniciar uno","",IF(MOD(INT((COUNTIF($I$2:I3,I3)-1)/3),2)=0,"Sí","No")) -> Sí | V3: =IF(I3="Tengo un emprendimiento o quiero iniciar uno",CHOOSE(MOD(COUNTIF($I$2:I3,I3)-1,3)+1,"Tengo un emprendimiento","Estoy iniciando un emprendimiento","Me interesa emprender"),"") | W3: =IF(V3="Tengo un emprendimiento","Funcionamiento estable",IF(V3="Estoy iniciando un emprendimiento","Inicio","")) | X3: =IF(I3="Tengo un emprendimiento o quiero iniciar uno",CHOOSE(MOD(COUNTIF($I$2:I3,I3)-1,5)+1,"Falta de financiación","Falta de conocimientos administrativos","Falta de conocimientos financieros","Falta de tiempo","Falta de herramientas"),"") | Y3: =IF(I3="Tengo un emprendimiento o quiero iniciar uno",X3,"") | Z3: =IF(I3="Tengo un emprendimiento o quiero iniciar uno",CHOOSE(INT(MOD((COUNTIF($I$2:I3,I3)-1)*7,39)/13)+1,"Sí","No","No conozco programas de ese tipo"),"") | AA3: =CHOOSE(INT(MOD((ROW()-2)*191,479)/120)+1,"No puedo hacerlo","Puedo hacerlo con ayuda","Puedo hacerlo con dificultad","Puedo hacerlo sin ayuda") -> Puedo hacerlo con ayuda | AB3: =CHOOSE(INT(MOD((ROW()-2)*191,479)/120)+1,"No puedo hacerlo","Puedo hacerlo con ayuda","Puedo hacerlo con dificultad","Puedo hacerlo sin ayuda") -> Puedo hacerlo con ayuda | AC3: =CHOOSE(INT(MOD((ROW()-2)*157+83,479)/120)+1,"No puedo hacerlo","Puedo hacerlo con ayuda","Puedo hacerlo con dificultad","Puedo hacerlo sin ayuda") -> Puedo hacerlo con dificultad | AD3: =CHOOSE(INT(MOD((ROW()-2)*89+131,479)/120)+1,"No puedo hacerlo","Puedo hacerlo con ayuda","Puedo hacerlo con dificultad","Puedo hacerlo sin ayuda") -> Puedo hacerlo con ayuda | AE3: =CHOOSE(INT(MOD((ROW()-2)*73+179,479)/120)+1,"No puedo hacerlo","Puedo hacerlo con ayuda","Puedo hacerlo con dificultad","Puedo hacerlo sin ayuda") -> Puedo hacerlo con dificultad | AF3: =CHOOSE(MOD((ROW()-2)*61+23,10)+1,"Crear una hoja de vida","Preparación para entrevista","Comunicación","Liderazgo","Emprendimiento","Herramientas digitales","Educación financiera","Crear una hoja de vida;Preparación para entrevista","Comunicación;Liderazgo","Herramientas digitales;Educación financiera") -> Emprendimiento | AG3: =CHOOSE(MOD(INT((ROW()-2)/3)*7,9)+1,"Costos de transporte","Distancia","Horarios","Falta de experiencia","Falta de información","Ninguna","Costos de transporte;Distancia","Horarios;Falta de información","Falta de experiencia;Falta de información") -> Costos de transporte | AH3: =CHOOSE(INT(MOD((ROW()-2)*199+59,479)/120)+1,"Oficina de orientación laboral","Ferias de empleo","Programas de emprendimiento","No conozco ninguno") -> Programas de emprendimiento | AI3: =CHOOSE(INT(MOD((ROW()-2)*127+71,479)/120)+1,"Presencial","Virtual","Presencial y virtual","Me es indiferente") -> Virtual | AJ3: =CHOOSE(INT(MOD((ROW()-2)*163+97,479)/120)+1,"Diurno","Nocturno","Mañana entre semana","Fines de semana") -> Mañana entre semana | AK3: =CHOOSE(INT(MOD((ROW()-2)*181+109,479)/120)+1,"WhatsApp","Correo electrónico","Redes sociales","Celular") -> Redes sociales
A4: ="SG"&TEXT(ROW()-1,"000") -> SG003 | B4: Urbana Consolidada | C4: SI, ACEPTO PARTICIPAR | D4: =IF(MOD((ROW()-2)*137,479)<230,"Masculino",IF(MOD((ROW()-2)*137,479)<460,"Femenino",IF(MOD((ROW()-2)*137,479)<470,"Otro","No quiero responder"))) -> Femenino | E4: =CHOOSE(MOD(ROW()-2,5)+1,"De 18 a 20 años","De 20 a 22 años","De 22 a 24 años","De 24 a 26 años","De 26 a 28 años") -> De 22 a 24 años | F4: =CHOOSE(MOD(ROW()-2,5)+1,18,20,22,24,26)+MOD(INT((ROW()-2)/5),IF(MOD(ROW()-2,5)=4,3,2)) -> 22 | G4: URBANA | H4: =_xlfn.LET(_xlpm.grupo,MOD(ROW()-2,5),_xlpm.turno,INT((ROW()-2)/5),_xlpm.orden,MOD(_xlpm.turno*37,IF(_xlpm.grupo=4,95,96)),CHOOSE(_xlpm.grupo+1,IF(_xlpm.orden<60,"Bachiller",IF(_xlpm.orden<84,"Técnico","Tecnólogo")),IF(_xlpm.orden<36,"Bachiller",IF(_xlpm.orden<66,"Técnico","Tecnólogo")),IF(_xlpm.orden<24,"Bachiller",IF(_xlpm.orden<48,"Técnico",IF(_xlpm.orden<72,"Tecnólogo","Profesional"))),IF(_xlpm.orden<12,"Bachiller",IF(_xlpm.orden<30,"Técnico",IF(_xlpm.orden<54,"Tecnólogo",IF(_xlpm.orden<90,"Profesional","Posgrado")))),IF(_xlpm.orden<10,"Bachiller",IF(_xlpm.orden<25,"Técnico",IF(_xlpm.orden<45,"Tecnólogo",IF(_xlpm.orden<85,"Profesional","Posgrado")))))) -> Bachiller | I4: =_xlfn.LET(_xlpm.orden,MOD((ROW()-2)*173,479),IF(_xlpm.orden<150,"Trabajo actualmente como empleado",IF(_xlpm.orden<230,"Trabajo de manera independiente",IF(_xlpm.orden<320,"Actualmente no trabajo y estoy buscando empleo",IF(_xlpm.orden<380,"Busco mi primer empleo",IF(_xlpm.orden<440,"Estudio y quiero comenzar a trabajar","Tengo un emprendimiento o quiero iniciar uno")))))) -> Busco mi primer empleo | J4: =IF(I4="Trabajo actualmente como empleado",IF(MOD((COUNTIF($I$2:I4,"Trabajo actualmente como empleado")-1)*37,150)<100,"Empleado con contrato","Empleado sin contrato formal"),IF(I4="Trabajo de manera independiente","Trabajo independiente","")) | K4: =IF(OR(I4="Trabajo actualmente como empleado",I4="Trabajo de manera independiente"),CHOOSE(MOD(COUNTIF($I$2:I4,I4)-1,4)+1,"Menos de 3 meses","De 3 a 6 meses","De 7 a 12 meses","Más de un año"),"") | L4: =IF(OR(I4="Trabajo actualmente como empleado",I4="Trabajo de manera independiente"),CHOOSE(MOD(COUNTIF($I$2:I4,I4)-1,3)+1,"Sí, completamente","Parcialmente","No"),"") | M4: =IF(OR(I4="Trabajo actualmente como empleado",I4="Trabajo de manera independiente"),CHOOSE(MOD(INT((COUNTIF($I$2:I4,I4)-1)/3),4)+1,"1- Muy satisfecho/a","2- Satisfecho/a","3- Insatisfecho/a","4- Muy insatisfecho/a"),"") | N4: =IF(OR(I4="Trabajo actualmente como empleado",I4="Trabajo de manera independiente"),_xlfn.LET(_xlpm.opcion,MOD(INT((COUNTIF($I$2:I4,I4)-1)/5),6)+1,CHOOSE(IF(AND(_xlpm.opcion=6,L4="Sí, completamente"),5,_xlpm.opcion),"Salario","Estabilidad laboral","Horario","Acceso a prestaciones","Oportunidades de crecimiento","Trabajar en un área relacionada con mi formación")),"") | O4: =IF(OR(I4="Trabajo actualmente como empleado",I4="Trabajo de manera independiente"),_xlfn.LET(_xlpm.turno,MOD(COUNTIF($I$2:I4,I4)-1,5),_xlpm.nivel,VALUE(LEFT(M4,1)),IF(_xlpm.turno=4,"No estoy seguro/a",IF(_xlpm.turno<IF(_xlpm.nivel<=2,1,3),"Sí","No"))),"") | P4: =_xlfn.LET(_xlpm.perfil,I4,_xlpm.turno,COUNTIF($I$2:I4,_xlpm.perfil)-1,_xlpm.busca,OR(_xlpm.perfil="Actualmente no trabajo y estoy buscando empleo",_xlpm.perfil="Busco mi primer empleo"),_xlpm.trabaja,OR(_xlpm.perfil="Trabajo actualmente como empleado",_xlpm.perfil="Trabajo de manera independiente"),IF(_xlpm.busca,CHOOSE(MOD(_xlpm.turno*3,4)+1,"Menos de 1 mes","Entre 1 y 3 meses","Entre 4 y 6 meses","Más de 6 meses"),IF(OR(_xlpm.trabaja,_xlpm.perfil="Estudio y quiero comenzar a trabajar"),IF(AND(_xlpm.trabaja,O4="No"),"Todavía no he iniciado una búsqueda activa",CHOOSE(MOD(_xlpm.turno*3,5)+1,"Menos de 1 mes","Entre 1 y 3 meses","Entre 4 y 6 meses","Más de 6 meses","Todavía no he iniciado una búsqueda activa")),""))) -> Menos de 1 mes | Q4: =IF(I4="Tengo un emprendimiento o quiero iniciar uno","",CHOOSE(MOD(INT((COUNTIF($I$2:I4,I4)-1)/7),3)+1,"Sí","No","Tengo una pero necesito actualizarla")) -> Sí | R4: =IF(I4="Tengo un emprendimiento o quiero iniciar uno","",IF(I4="Busco mi primer empleo","No",IF(MOD(COUNTIF($I$2:I4,I4)-1,2)=0,"Sí","No"))) -> No | S4: =IF(I4="Tengo un emprendimiento o quiero iniciar uno","",CHOOSE(MOD(INT((COUNTIF($I$2:I4,I4)-1)/3),10)+1,"Portales de empleo","Redes sociales","Familiares o conocidos","Empresas directamente","Ferias de empleo","Instituciones públicas","Institución educativa","No sé dónde buscar","Portales de empleo;Redes sociales","Familiares o conocidos;Empresas directamente")) -> Portales de empleo | T4: =IF(I4="Tengo un emprendimiento o quiero iniciar uno","",_xlfn.LET(_xlpm.opcion,MOD(INT((COUNTIF($I$2:I4,I4)-1)/4),6)+1,CHOOSE(IF(AND(_xlpm.opcion=3,Q4="Sí"),1,_xlpm.opcion),"Falta de experiencia","Falta de formación","Dificultades con la hoja de vida","Horarios disponibles","Transporte","Internet"))) -> Falta de experiencia | U4: =IF(I4="Tengo un emprendimiento o quiero iniciar uno","",IF(MOD(INT((COUNTIF($I$2:I4,I4)-1)/3),2)=0,"Sí","No")) -> Sí | V4: =IF(I4="Tengo un emprendimiento o quiero iniciar uno",CHOOSE(MOD(COUNTIF($I$2:I4,I4)-1,3)+1,"Tengo un emprendimiento","Estoy iniciando un emprendimiento","Me interesa emprender"),"") | W4: =IF(V4="Tengo un emprendimiento","Funcionamiento estable",IF(V4="Estoy iniciando un emprendimiento","Inicio","")) | X4: =IF(I4="Tengo un emprendimiento o quiero iniciar uno",CHOOSE(MOD(COUNTIF($I$2:I4,I4)-1,5)+1,"Falta de financiación","Falta de conocimientos administrativos","Falta de conocimientos financieros","Falta de tiempo","Falta de herramientas"),"") | Y4: =IF(I4="Tengo un emprendimiento o quiero iniciar uno",X4,"") | Z4: =IF(I4="Tengo un emprendimiento o quiero iniciar uno",CHOOSE(INT(MOD((COUNTIF($I$2:I4,I4)-1)*7,39)/13)+1,"Sí","No","No conozco programas de ese tipo"),"") | AA4: =CHOOSE(INT(MOD((ROW()-2)*191,479)/120)+1,"No puedo hacerlo","Puedo hacerlo con ayuda","Puedo hacerlo con dificultad","Puedo hacerlo sin ayuda") -> Puedo hacerlo sin ayuda | AB4: =CHOOSE(INT(MOD((ROW()-2)*191,479)/120)+1,"No puedo hacerlo","Puedo hacerlo con ayuda","Puedo hacerlo con dificultad","Puedo hacerlo sin ayuda") -> Puedo hacerlo sin ayuda | AC4: =CHOOSE(INT(MOD((ROW()-2)*157+83,479)/120)+1,"No puedo hacerlo","Puedo hacerlo con ayuda","Puedo hacerlo con dificultad","Puedo hacerlo sin ayuda") -> Puedo hacerlo sin ayuda | AD4: =CHOOSE(INT(MOD((ROW()-2)*89+131,479)/120)+1,"No puedo hacerlo","Puedo hacerlo con ayuda","Puedo hacerlo con dificultad","Puedo hacerlo sin ayuda") -> Puedo hacerlo con dificultad | AE4: =CHOOSE(INT(MOD((ROW()-2)*73+179,479)/120)+1,"No puedo hacerlo","Puedo hacerlo con ayuda","Puedo hacerlo con dificultad","Puedo hacerlo sin ayuda") -> Puedo hacerlo con dificultad | AF4: =CHOOSE(MOD((ROW()-2)*61+23,10)+1,"Crear una hoja de vida","Preparación para entrevista","Comunicación","Liderazgo","Emprendimiento","Herramientas digitales","Educación financiera","Crear una hoja de vida;Preparación para entrevista","Comunicación;Liderazgo","Herramientas digitales;Educación financiera") -> Herramientas digitales | AG4: =CHOOSE(MOD(INT((ROW()-2)/3)*7,9)+1,"Costos de transporte","Distancia","Horarios","Falta de experiencia","Falta de información","Ninguna","Costos de transporte;Distancia","Horarios;Falta de información","Falta de experiencia;Falta de información") -> Costos de transporte | AH4: =CHOOSE(INT(MOD((ROW()-2)*199+59,479)/120)+1,"Oficina de orientación laboral","Ferias de empleo","Programas de emprendimiento","No conozco ninguno") -> No conozco ninguno | AI4: =CHOOSE(INT(MOD((ROW()-2)*127+71,479)/120)+1,"Presencial","Virtual","Presencial y virtual","Me es indiferente") -> Presencial y virtual | AJ4: =CHOOSE(INT(MOD((ROW()-2)*163+97,479)/120)+1,"Diurno","Nocturno","Mañana entre semana","Fines de semana") -> Fines de semana | AK4: =CHOOSE(INT(MOD((ROW()-2)*181+109,479)/120)+1,"WhatsApp","Correo electrónico","Redes sociales","Celular") -> Celular
A5: ="SG"&TEXT(ROW()-1,"000") -> SG004 | B5: Urbana Consolidada | C5: SI, ACEPTO PARTICIPAR | D5: =IF(MOD((ROW()-2)*137,479)<230,"Masculino",IF(MOD((ROW()-2)*137,479)<460,"Femenino",IF(MOD((ROW()-2)*137,479)<470,"Otro","No quiero responder"))) -> Femenino | E5: =CHOOSE(MOD(ROW()-2,5)+1,"De 18 a 20 años","De 20 a 22 años","De 22 a 24 años","De 24 a 26 años","De 26 a 28 años") -> De 24 a 26 años | F5: =CHOOSE(MOD(ROW()-2,5)+1,18,20,22,24,26)+MOD(INT((ROW()-2)/5),IF(MOD(ROW()-2,5)=4,3,2)) -> 24 | G5: URBANA | H5: =_xlfn.LET(_xlpm.grupo,MOD(ROW()-2,5),_xlpm.turno,INT((ROW()-2)/5),_xlpm.orden,MOD(_xlpm.turno*37,IF(_xlpm.grupo=4,95,96)),CHOOSE(_xlpm.grupo+1,IF(_xlpm.orden<60,"Bachiller",IF(_xlpm.orden<84,"Técnico","Tecnólogo")),IF(_xlpm.orden<36,"Bachiller",IF(_xlpm.orden<66,"Técnico","Tecnólogo")),IF(_xlpm.orden<24,"Bachiller",IF(_xlpm.orden<48,"Técnico",IF(_xlpm.orden<72,"Tecnólogo","Profesional"))),IF(_xlpm.orden<12,"Bachiller",IF(_xlpm.orden<30,"Técnico",IF(_xlpm.orden<54,"Tecnólogo",IF(_xlpm.orden<90,"Profesional","Posgrado")))),IF(_xlpm.orden<10,"Bachiller",IF(_xlpm.orden<25,"Técnico",IF(_xlpm.orden<45,"Tecnólogo",IF(_xlpm.orden<85,"Profesional","Posgrado")))))) -> Bachiller | I5: =_xlfn.LET(_xlpm.orden,MOD((ROW()-2)*173,479),IF(_xlpm.orden<150,"Trabajo actualmente como empleado",IF(_xlpm.orden<230,"Trabajo de manera independiente",IF(_xlpm.orden<320,"Actualmente no trabajo y estoy buscando empleo",IF(_xlpm.orden<380,"Busco mi primer empleo",IF(_xlpm.orden<440,"Estudio y quiero comenzar a trabajar","Tengo un emprendimiento o quiero iniciar uno")))))) -> Trabajo actualmente como empleado | J5: =IF(I5="Trabajo actualmente como empleado",IF(MOD((COUNTIF($I$2:I5,"Trabajo actualmente como empleado")-1)*37,150)<100,"Empleado con contrato","Empleado sin contrato formal"),IF(I5="Trabajo de manera independiente","Trabajo independiente","")) -> Empleado con contrato | K5: =IF(OR(I5="Trabajo actualmente como empleado",I5="Trabajo de manera independiente"),CHOOSE(MOD(COUNTIF($I$2:I5,I5)-1,4)+1,"Menos de 3 meses","De 3 a 6 meses","De 7 a 12 meses","Más de un año"),"") -> De 3 a 6 meses | L5: =IF(OR(I5="Trabajo actualmente como empleado",I5="Trabajo de manera independiente"),CHOOSE(MOD(COUNTIF($I$2:I5,I5)-1,3)+1,"Sí, completamente","Parcialmente","No"),"") -> Parcialmente | M5: =IF(OR(I5="Trabajo actualmente como empleado",I5="Trabajo de manera independiente"),CHOOSE(MOD(INT((COUNTIF($I$2:I5,I5)-1)/3),4)+1,"1- Muy satisfecho/a","2- Satisfecho/a","3- Insatisfecho/a","4- Muy insatisfecho/a"),"") -> 1- Muy satisfecho/a | N5: =IF(OR(I5="Trabajo actualmente como empleado",I5="Trabajo de manera independiente"),_xlfn.LET(_xlpm.opcion,MOD(INT((COUNTIF($I$2:I5,I5)-1)/5),6)+1,CHOOSE(IF(AND(_xlpm.opcion=6,L5="Sí, completamente"),5,_xlpm.opcion),"Salario","Estabilidad laboral","Horario","Acceso a prestaciones","Oportunidades de crecimiento","Trabajar en un área relacionada con mi formación")),"") -> Salario | O5: =IF(OR(I5="Trabajo actualmente como empleado",I5="Trabajo de manera independiente"),_xlfn.LET(_xlpm.turno,MOD(COUNTIF($I$2:I5,I5)-1,5),_xlpm.nivel,VALUE(LEFT(M5,1)),IF(_xlpm.turno=4,"No estoy seguro/a",IF(_xlpm.turno<IF(_xlpm.nivel<=2,1,3),"Sí","No"))),"") -> No | P5: =_xlfn.LET(_xlpm.perfil,I5,_xlpm.turno,COUNTIF($I$2:I5,_xlpm.perfil)-1,_xlpm.busca,OR(_xlpm.perfil="Actualmente no trabajo y estoy buscando empleo",_xlpm.perfil="Busco mi primer empleo"),_xlpm.trabaja,OR(_xlpm.perfil="Trabajo actualmente como empleado",_xlpm.perfil="Trabajo de manera independiente"),IF(_xlpm.busca,CHOOSE(MOD(_xlpm.turno*3,4)+1,"Menos de 1 mes","Entre 1 y 3 meses","Entre 4 y 6 meses","Más de 6 meses"),IF(OR(_xlpm.trabaja,_xlpm.perfil="Estudio y quiero comenzar a trabajar"),IF(AND(_xlpm.trabaja,O5="No"),"Todavía no he iniciado una búsqueda activa",CHOOSE(MOD(_xlpm.turno*3,5)+1,"Menos de 1 mes","Entre 1 y 3 meses","Entre 4 y 6 meses","Más de 6 meses","Todavía no he iniciado una búsqueda activa")),""))) -> Todavía no he iniciado una búsqueda activa | Q5: =IF(I5="Tengo un emprendimiento o quiero iniciar uno","",CHOOSE(MOD(INT((COUNTIF($I$2:I5,I5)-1)/7),3)+1,"Sí","No","Tengo una pero necesito actualizarla")) -> Sí | R5: =IF(I5="Tengo un emprendimiento o quiero iniciar uno","",IF(I5="Busco mi primer empleo","No",IF(MOD(COUNTIF($I$2:I5,I5)-1,2)=0,"Sí","No"))) -> No | S5: =IF(I5="Tengo un emprendimiento o quiero iniciar uno","",CHOOSE(MOD(INT((COUNTIF($I$2:I5,I5)-1)/3),10)+1,"Portales de empleo","Redes sociales","Familiares o conocidos","Empresas directamente","Ferias de empleo","Instituciones públicas","Institución educativa","No sé dónde buscar","Portales de empleo;Redes sociales","Familiares o conocidos;Empresas directamente")) -> Portales de empleo | T5: =IF(I5="Tengo un emprendimiento o quiero iniciar uno","",_xlfn.LET(_xlpm.opcion,MOD(INT((COUNTIF($I$2:I5,I5)-1)/4),6)+1,CHOOSE(IF(AND(_xlpm.opcion=3,Q5="Sí"),1,_xlpm.opcion),"Falta de experiencia","Falta de formación","Dificultades con la hoja de vida","Horarios disponibles","Transporte","Internet"))) -> Falta de experiencia | U5: =IF(I5="Tengo un emprendimiento o quiero iniciar uno","",IF(MOD(INT((COUNTIF($I$2:I5,I5)-1)/3),2)=0,"Sí","No")) -> Sí | V5: =IF(I5="Tengo un emprendimiento o quiero iniciar uno",CHOOSE(MOD(COUNTIF($I$2:I5,I5)-1,3)+1,"Tengo un emprendimiento","Estoy iniciando un emprendimiento","Me interesa emprender"),"") | W5: =IF(V5="Tengo un emprendimiento","Funcionamiento estable",IF(V5="Estoy iniciando un emprendimiento","Inicio","")) | X5: =IF(I5="Tengo un emprendimiento o quiero iniciar uno",CHOOSE(MOD(COUNTIF($I$2:I5,I5)-1,5)+1,"Falta de financiación","Falta de conocimientos administrativos","Falta de conocimientos financieros","Falta de tiempo","Falta de herramientas"),"") | Y5: =IF(I5="Tengo un emprendimiento o quiero iniciar uno",X5,"") | Z5: =IF(I5="Tengo un emprendimiento o quiero iniciar uno",CHOOSE(INT(MOD((COUNTIF($I$2:I5,I5)-1)*7,39)/13)+1,"Sí","No","No conozco programas de ese tipo"),"") | AA5: =CHOOSE(INT(MOD((ROW()-2)*191,479)/120)+1,"No puedo hacerlo","Puedo hacerlo con ayuda","Puedo hacerlo con dificultad","Puedo hacerlo sin ayuda") -> No puedo hacerlo | AB5: =CHOOSE(INT(MOD((ROW()-2)*191,479)/120)+1,"No puedo hacerlo","Puedo hacerlo con ayuda","Puedo hacerlo con dificultad","Puedo hacerlo sin ayuda") -> No puedo hacerlo | AC5: =CHOOSE(INT(MOD((ROW()-2)*157+83,479)/120)+1,"No puedo hacerlo","Puedo hacerlo con ayuda","Puedo hacerlo con dificultad","Puedo hacerlo sin ayuda") -> No puedo hacerlo | AD5: =CHOOSE(INT(MOD((ROW()-2)*89+131,479)/120)+1,"No puedo hacerlo","Puedo hacerlo con ayuda","Puedo hacerlo con dificultad","Puedo hacerlo sin ayuda") -> Puedo hacerlo sin ayuda | AE5: =CHOOSE(INT(MOD((ROW()-2)*73+179,479)/120)+1,"No puedo hacerlo","Puedo hacerlo con ayuda","Puedo hacerlo con dificultad","Puedo hacerlo sin ayuda") -> Puedo hacerlo sin ayuda | AF5: =CHOOSE(MOD((ROW()-2)*61+23,10)+1,"Crear una hoja de vida","Preparación para entrevista","Comunicación","Liderazgo","Emprendimiento","Herramientas digitales","Educación financiera","Crear una hoja de vida;Preparación para entrevista","Comunicación;Liderazgo","Herramientas digitales;Educación financiera") -> Educación financiera | AG5: =CHOOSE(MOD(INT((ROW()-2)/3)*7,9)+1,"Costos de transporte","Distancia","Horarios","Falta de experiencia","Falta de información","Ninguna","Costos de transporte;Distancia","Horarios;Falta de información","Falta de experiencia;Falta de información") -> Horarios;Falta de información | AH5: =CHOOSE(INT(MOD((ROW()-2)*199+59,479)/120)+1,"Oficina de orientación laboral","Ferias de empleo","Programas de emprendimiento","No conozco ninguno") -> Ferias de empleo | AI5: =CHOOSE(INT(MOD((ROW()-2)*127+71,479)/120)+1,"Presencial","Virtual","Presencial y virtual","Me es indiferente") -> Me es indiferente | AJ5: =CHOOSE(INT(MOD((ROW()-2)*163+97,479)/120)+1,"Diurno","Nocturno","Mañana entre semana","Fines de semana") -> Diurno | AK5: =CHOOSE(INT(MOD((ROW()-2)*181+109,479)/120)+1,"WhatsApp","Correo electrónico","Redes sociales","Celular") -> Correo electrónico
A6: ="SG"&TEXT(ROW()-1,"000") -> SG005 | B6: Urbana Consolidada | C6: SI, ACEPTO PARTICIPAR | D6: =IF(MOD((ROW()-2)*137,479)<230,"Masculino",IF(MOD((ROW()-2)*137,479)<460,"Femenino",IF(MOD((ROW()-2)*137,479)<470,"Otro","No quiero responder"))) -> Masculino | E6: =CHOOSE(MOD(ROW()-2,5)+1,"De 18 a 20 años","De 20 a 22 años","De 22 a 24 años","De 24 a 26 años","De 26 a 28 años") -> De 26 a 28 años | F6: =CHOOSE(MOD(ROW()-2,5)+1,18,20,22,24,26)+MOD(INT((ROW()-2)/5),IF(MOD(ROW()-2,5)=4,3,2)) -> 26 | G6: URBANA | H6: =_xlfn.LET(_xlpm.grupo,MOD(ROW()-2,5),_xlpm.turno,INT((ROW()-2)/5),_xlpm.orden,MOD(_xlpm.turno*37,IF(_xlpm.grupo=4,95,96)),CHOOSE(_xlpm.grupo+1,IF(_xlpm.orden<60,"Bachiller",IF(_xlpm.orden<84,"Técnico","Tecnólogo")),IF(_xlpm.orden<36,"Bachiller",IF(_xlpm.orden<66,"Técnico","Tecnólogo")),IF(_xlpm.orden<24,"Bachiller",IF(_xlpm.orden<48,"Técnico",IF(_xlpm.orden<72,"Tecnólogo","Profesional"))),IF(_xlpm.orden<12,"Bachiller",IF(_xlpm.orden<30,"Técnico",IF(_xlpm.orden<54,"Tecnólogo",IF(_xlpm.orden<90,"Profesional","Posgrado")))),IF(_xlpm.orden<10,"Bachiller",IF(_xlpm.orden<25,"Técnico",IF(_xlpm.orden<45,"Tecnólogo",IF(_xlpm.orden<85,"Profesional","Posgrado")))))) -> Bachiller | I6: =_xlfn.LET(_xlpm.orden,MOD((ROW()-2)*173,479),IF(_xlpm.orden<150,"Trabajo actualmente como empleado",IF(_xlpm.orden<230,"Trabajo de manera independiente",IF(_xlpm.orden<320,"Actualmente no trabajo y estoy buscando empleo",IF(_xlpm.orden<380,"Busco mi primer empleo",IF(_xlpm.orden<440,"Estudio y quiero comenzar a trabajar","Tengo un emprendimiento o quiero iniciar uno")))))) -> Trabajo de manera independiente | J6: =IF(I6="Trabajo actualmente como empleado",IF(MOD((COUNTIF($I$2:I6,"Trabajo actualmente como empleado")-1)*37,150)<100,"Empleado con contrato","Empleado sin contrato formal"),IF(I6="Trabajo de manera independiente","Trabajo independiente","")) -> Trabajo independiente | K6: =IF(OR(I6="Trabajo actualmente como empleado",I6="Trabajo de manera independiente"),CHOOSE(MOD(COUNTIF($I$2:I6,I6)-1,4)+1,"Menos de 3 meses","De 3 a 6 meses","De 7 a 12 meses","Más de un año"),"") -> De 3 a 6 meses | L6: =IF(OR(I6="Trabajo actualmente como empleado",I6="Trabajo de manera independiente"),CHOOSE(MOD(COUNTIF($I$2:I6,I6)-1,3)+1,"Sí, completamente","Parcialmente","No"),"") -> Parcialmente | M6: =IF(OR(I6="Trabajo actualmente como empleado",I6="Trabajo de manera independiente"),CHOOSE(MOD(INT((COUNTIF($I$2:I6,I6)-1)/3),4)+1,"1- Muy satisfecho/a","2- Satisfecho/a","3- Insatisfecho/a","4- Muy insatisfecho/a"),"") -> 1- Muy satisfecho/a | N6: =IF(OR(I6="Trabajo actualmente como empleado",I6="Trabajo de manera independiente"),_xlfn.LET(_xlpm.opcion,MOD(INT((COUNTIF($I$2:I6,I6)-1)/5),6)+1,CHOOSE(IF(AND(_xlpm.opcion=6,L6="Sí, completamente"),5,_xlpm.opcion),"Salario","Estabilidad laboral","Horario","Acceso a prestaciones","Oportunidades de crecimiento","Trabajar en un área relacionada con mi formación")),"") -> Salario | O6: =IF(OR(I6="Trabajo actualmente como empleado",I6="Trabajo de manera independiente"),_xlfn.LET(_xlpm.turno,MOD(COUNTIF($I$2:I6,I6)-1,5),_xlpm.nivel,VALUE(LEFT(M6,1)),IF(_xlpm.turno=4,"No estoy seguro/a",IF(_xlpm.turno<IF(_xlpm.nivel<=2,1,3),"Sí","No"))),"") -> No | P6: =_xlfn.LET(_xlpm.perfil,I6,_xlpm.turno,COUNTIF($I$2:I6,_xlpm.perfil)-1,_xlpm.busca,OR(_xlpm.perfil="Actualmente no trabajo y estoy buscando empleo",_xlpm.perfil="Busco mi primer empleo"),_xlpm.trabaja,OR(_xlpm.perfil="Trabajo actualmente como empleado",_xlpm.perfil="Trabajo de manera independiente"),IF(_xlpm.busca,CHOOSE(MOD(_xlpm.turno*3,4)+1,"Menos de 1 mes","Entre 1 y 3 meses","Entre 4 y 6 meses","Más de 6 meses"),IF(OR(_xlpm.trabaja,_xlpm.perfil="Estudio y quiero comenzar a trabajar"),IF(AND(_xlpm.trabaja,O6="No"),"Todavía no he iniciado una búsqueda activa",CHOOSE(MOD(_xlpm.turno*3,5)+1,"Menos de 1 mes","Entre 1 y 3 meses","Entre 4 y 6 meses","Más de 6 meses","Todavía no he iniciado una búsqueda activa")),""))) -> Todavía no he iniciado una búsqueda activa | Q6: =IF(I6="Tengo un emprendimiento o quiero iniciar uno","",CHOOSE(MOD(INT((COUNTIF($I$2:I6,I6)-1)/7),3)+1,"Sí","No","Tengo una pero necesito actualizarla")) -> Sí | R6: =IF(I6="Tengo un emprendimiento o quiero iniciar uno","",IF(I6="Busco mi primer empleo","No",IF(MOD(COUNTIF($I$2:I6,I6)-1,2)=0,"Sí","No"))) -> No | S6: =IF(I6="Tengo un emprendimiento o quiero iniciar uno","",CHOOSE(MOD(INT((COUNTIF($I$2:I6,I6)-1)/3),10)+1,"Portales de empleo","Redes sociales","Familiares o conocidos","Empresas directamente","Ferias de empleo","Instituciones públicas","Institución educativa","No sé dónde buscar","Portales de empleo;Redes sociales","Familiares o conocidos;Empresas directamente")) -> Portales de empleo | T6: =IF(I6="Tengo un emprendimiento o quiero iniciar uno","",_xlfn.LET(_xlpm.opcion,MOD(INT((COUNTIF($I$2:I6,I6)-1)/4),6)+1,CHOOSE(IF(AND(_xlpm.opcion=3,Q6="Sí"),1,_xlpm.opcion),"Falta de experiencia","Falta de formación","Dificultades con la hoja de vida","Horarios disponibles","Transporte","Internet"))) -> Falta de experiencia | U6: =IF(I6="Tengo un emprendimiento o quiero iniciar uno","",IF(MOD(INT((COUNTIF($I$2:I6,I6)-1)/3),2)=0,"Sí","No")) -> Sí | V6: =IF(I6="Tengo un emprendimiento o quiero iniciar uno",CHOOSE(MOD(COUNTIF($I$2:I6,I6)-1,3)+1,"Tengo un emprendimiento","Estoy iniciando un emprendimiento","Me interesa emprender"),"") | W6: =IF(V6="Tengo un emprendimiento","Funcionamiento estable",IF(V6="Estoy iniciando un emprendimiento","Inicio","")) | X6: =IF(I6="Tengo un emprendimiento o quiero iniciar uno",CHOOSE(MOD(COUNTIF($I$2:I6,I6)-1,5)+1,"Falta de financiación","Falta de conocimientos administrativos","Falta de conocimientos financieros","Falta de tiempo","Falta de herramientas"),"") | Y6: =IF(I6="Tengo un emprendimiento o quiero iniciar uno",X6,"") | Z6: =IF(I6="Tengo un emprendimiento o quiero iniciar uno",CHOOSE(INT(MOD((COUNTIF($I$2:I6,I6)-1)*7,39)/13)+1,"Sí","No","No conozco programas de ese tipo"),"") | AA6: =CHOOSE(INT(MOD((ROW()-2)*191,479)/120)+1,"No puedo hacerlo","Puedo hacerlo con ayuda","Puedo hacerlo con dificultad","Puedo hacerlo sin ayuda") -> Puedo hacerlo con dificultad | AB6: =CHOOSE(INT(MOD((ROW()-2)*191,479)/120)+1,"No puedo hacerlo","Puedo hacerlo con ayuda","Puedo hacerlo con dificultad","Puedo hacerlo sin ayuda") -> Puedo hacerlo con dificultad | AC6: =CHOOSE(INT(MOD((ROW()-2)*157+83,479)/120)+1,"No puedo hacerlo","Puedo hacerlo con ayuda","Puedo hacerlo con dificultad","Puedo hacerlo sin ayuda") -> Puedo hacerlo con ayuda | AD6: =CHOOSE(INT(MOD((ROW()-2)*89+131,479)/120)+1,"No puedo hacerlo","Puedo hacerlo con ayuda","Puedo hacerlo con dificultad","Puedo hacerlo sin ayuda") -> No puedo hacerlo | AE6: =CHOOSE(INT(MOD((ROW()-2)*73+179,479)/120)+1,"No puedo hacerlo","Puedo hacerlo con ayuda","Puedo hacerlo con dificultad","Puedo hacerlo sin ayuda") -> Puedo hacerlo sin ayuda | AF6: =CHOOSE(MOD((ROW()-2)*61+23,10)+1,"Crear una hoja de vida","Preparación para entrevista","Comunicación","Liderazgo","Emprendimiento","Herramientas digitales","Educación financiera","Crear una hoja de vida;Preparación para entrevista","Comunicación;Liderazgo","Herramientas digitales;Educación financiera") -> Crear una hoja de vida;Preparación para entrevista | AG6: =CHOOSE(MOD(INT((ROW()-2)/3)*7,9)+1,"Costos de transporte","Distancia","Horarios","Falta de experiencia","Falta de información","Ninguna","Costos de transporte;Distancia","Horarios;Falta de información","Falta de experiencia;Falta de información") -> Horarios;Falta de información | AH6: =CHOOSE(INT(MOD((ROW()-2)*199+59,479)/120)+1,"Oficina de orientación laboral","Ferias de empleo","Programas de emprendimiento","No conozco ninguno") -> No conozco ninguno | AI6: =CHOOSE(INT(MOD((ROW()-2)*127+71,479)/120)+1,"Presencial","Virtual","Presencial y virtual","Me es indiferente") -> Presencial | AJ6: =CHOOSE(INT(MOD((ROW()-2)*163+97,479)/120)+1,"Diurno","Nocturno","Mañana entre semana","Fines de semana") -> Mañana entre semana | AK6: =CHOOSE(INT(MOD((ROW()-2)*181+109,479)/120)+1,"WhatsApp","Correo electrónico","Redes sociales","Celular") -> Redes sociales
A7: ="SG"&TEXT(ROW()-1,"000") -> SG006 | B7: Urbana Consolidada | C7: SI, ACEPTO PARTICIPAR | D7: =IF(MOD((ROW()-2)*137,479)<230,"Masculino",IF(MOD((ROW()-2)*137,479)<460,"Femenino",IF(MOD((ROW()-2)*137,479)<470,"Otro","No quiero responder"))) -> Masculino | E7: =CHOOSE(MOD(ROW()-2,5)+1,"De 18 a 20 años","De 20 a 22 años","De 22 a 24 años","De 24 a 26 años","De 26 a 28 años") -> De 18 a 20 años | F7: =CHOOSE(MOD(ROW()-2,5)+1,18,20,22,24,26)+MOD(INT((ROW()-2)/5),IF(MOD(ROW()-2,5)=4,3,2)) -> 19 | G7: URBANA | H7: =_xlfn.LET(_xlpm.grupo,MOD(ROW()-2,5),_xlpm.turno,INT((ROW()-2)/5),_xlpm.orden,MOD(_xlpm.turno*37,IF(_xlpm.grupo=4,95,96)),CHOOSE(_xlpm.grupo+1,IF(_xlpm.orden<60,"Bachiller",IF(_xlpm.orden<84,"Técnico","Tecnólogo")),IF(_xlpm.orden<36,"Bachiller",IF(_xlpm.orden<66,"Técnico","Tecnólogo")),IF(_xlpm.orden<24,"Bachiller",IF(_xlpm.orden<48,"Técnico",IF(_xlpm.orden<72,"Tecnólogo","Profesional"))),IF(_xlpm.orden<12,"Bachiller",IF(_xlpm.orden<30,"Técnico",IF(_xlpm.orden<54,"Tecnólogo",IF(_xlpm.orden<90,"Profesional","Posgrado")))),IF(_xlpm.orden<10,"Bachiller",IF(_xlpm.orden<25,"Técnico",IF(_xlpm.orden<45,"Tecnólogo",IF(_xlpm.orden<85,"Profesional","Posgrado")))))) -> Bachiller | I7: =_xlfn.LET(_xlpm.orden,MOD((ROW()-2)*173,479),IF(_xlpm.orden<150,"Trabajo actualmente como empleado",IF(_xlpm.orden<230,"Trabajo de manera independiente",IF(_xlpm.orden<320,"Actualmente no trabajo y estoy buscando empleo",IF(_xlpm.orden<380,"Busco mi primer empleo",IF(_xlpm.orden<440,"Estudio y quiero comenzar a trabajar","Tengo un emprendimiento o quiero iniciar uno")))))) -> Estudio y quiero comenzar a trabajar | J7: =IF(I7="Trabajo actualmente como empleado",IF(MOD((COUNTIF($I$2:I7,"Trabajo actualmente como empleado")-1)*37,150)<100,"Empleado con contrato","Empleado sin contrato formal"),IF(I7="Trabajo de manera independiente","Trabajo independiente","")) | K7: =IF(OR(I7="Trabajo actualmente como empleado",I7="Trabajo de manera independiente"),CHOOSE(MOD(COUNTIF($I$2:I7,I7)-1,4)+1,"Menos de 3 meses","De 3 a 6 meses","De 7 a 12 meses","Más de un año"),"") | L7: =IF(OR(I7="Trabajo actualmente como empleado",I7="Trabajo de manera independiente"),CHOOSE(MOD(COUNTIF($I$2:I7,I7)-1,3)+1,"Sí, completamente","Parcialmente","No"),"") | M7: =IF(OR(I7="Trabajo actualmente como empleado",I7="Trabajo de manera independiente"),CHOOSE(MOD(INT((COUNTIF($I$2:I7,I7)-1)/3),4)+1,"1- Muy satisfecho/a","2- Satisfecho/a","3- Insatisfecho/a","4- Muy insatisfecho/a"),"") | N7: =IF(OR(I7="Trabajo actualmente como empleado",I7="Trabajo de manera independiente"),_xlfn.LET(_xlpm.opcion,MOD(INT((COUNTIF($I$2:I7,I7)-1)/5),6)+1,CHOOSE(IF(AND(_xlpm.opcion=6,L7="Sí, completamente"),5,_xlpm.opcion),"Salario","Estabilidad laboral","Horario","Acceso a prestaciones","Oportunidades de crecimiento","Trabajar en un área relacionada con mi formación")),"") | O7: =IF(OR(I7="Trabajo actualmente como empleado",I7="Trabajo de manera independiente"),_xlfn.LET(_xlpm.turno,MOD(COUNTIF($I$2:I7,I7)-1,5),_xlpm.nivel,VALUE(LEFT(M7,1)),IF(_xlpm.turno=4,"No estoy seguro/a",IF(_xlpm.turno<IF(_xlpm.nivel<=2,1,3),"Sí","No"))),"") | P7: =_xlfn.LET(_xlpm.perfil,I7,_xlpm.turno,COUNTIF($I$2:I7,_xlpm.perfil)-1,_xlpm.busca,OR(_xlpm.perfil="Actualmente no trabajo y estoy buscando empleo",_xlpm.perfil="Busco mi primer empleo"),_xlpm.trabaja,OR(_xlpm.perfil="Trabajo actualmente como empleado",_xlpm.perfil="Trabajo de manera independiente"),IF(_xlpm.busca,CHOOSE(MOD(_xlpm.turno*3,4)+1,"Menos de 1 mes","Entre 1 y 3 meses","Entre 4 y 6 meses","Más de 6 meses"),IF(OR(_xlpm.trabaja,_xlpm.perfil="Estudio y quiero comenzar a trabajar"),IF(AND(_xlpm.trabaja,O7="No"),"Todavía no he iniciado una búsqueda activa",CHOOSE(MOD(_xlpm.turno*3,5)+1,"Menos de 1 mes","Entre 1 y 3 meses","Entre 4 y 6 meses","Más de 6 meses","Todavía no he iniciado una búsqueda activa")),""))) -> Menos de 1 mes | Q7: =IF(I7="Tengo un emprendimiento o quiero iniciar uno","",CHOOSE(MOD(INT((COUNTIF($I$2:I7,I7)-1)/7),3)+1,"Sí","No","Tengo una pero necesito actualizarla")) -> Sí | R7: =IF(I7="Tengo un emprendimiento o quiero iniciar uno","",IF(I7="Busco mi primer empleo","No",IF(MOD(COUNTIF($I$2:I7,I7)-1,2)=0,"Sí","No"))) -> Sí | S7: =IF(I7="Tengo un emprendimiento o quiero iniciar uno","",CHOOSE(MOD(INT((COUNTIF($I$2:I7,I7)-1)/3),10)+1,"Portales de empleo","Redes sociales","Familiares o conocidos","Empresas directamente","Ferias de empleo","Instituciones públicas","Institución educativa","No sé dónde buscar","Portales de empleo;Redes sociales","Familiares o conocidos;Empresas directamente")) -> Portales de empleo | T7: =IF(I7="Tengo un emprendimiento o quiero iniciar uno","",_xlfn.LET(_xlpm.opcion,MOD(INT((COUNTIF($I$2:I7,I7)-1)/4),6)+1,CHOOSE(IF(AND(_xlpm.opcion=3,Q7="Sí"),1,_xlpm.opcion),"Falta de experiencia","Falta de formación","Dificultades con la hoja de vida","Horarios disponibles","Transporte","Internet"))) -> Falta de experiencia | U7: =IF(I7="Tengo un emprendimiento o quiero iniciar uno","",IF(MOD(INT((COUNTIF($I$2:I7,I7)-1)/3),2)=0,"Sí","No")) -> Sí | V7: =IF(I7="Tengo un emprendimiento o quiero iniciar uno",CHOOSE(MOD(COUNTIF($I$2:I7,I7)-1,3)+1,"Tengo un emprendimiento","Estoy iniciando un emprendimiento","Me interesa emprender"),"") | W7: =IF(V7="Tengo un emprendimiento","Funcionamiento estable",IF(V7="Estoy iniciando un emprendimiento","Inicio","")) | X7: =IF(I7="Tengo un emprendimiento o quiero iniciar uno",CHOOSE(MOD(COUNTIF($I$2:I7,I7)-1,5)+1,"Falta de financiación","Falta de conocimientos administrativos","Falta de conocimientos financieros","Falta de tiempo","Falta de herramientas"),"") | Y7: =IF(I7="Tengo un emprendimiento o quiero iniciar uno",X7,"") | Z7: =IF(I7="Tengo un emprendimiento o quiero iniciar uno",CHOOSE(INT(MOD((COUNTIF($I$2:I7,I7)-1)*7,39)/13)+1,"Sí","No","No conozco programas de ese tipo"),"") | AA7: =CHOOSE(INT(MOD((ROW()-2)*191,479)/120)+1,"No puedo hacerlo","Puedo hacerlo con ayuda","Puedo hacerlo con dificultad","Puedo hacerlo sin ayuda") -> Puedo hacerlo sin ayuda | AB7: =CHOOSE(INT(MOD((ROW()-2)*191,479)/120)+1,"No puedo hacerlo","Puedo hacerlo con ayuda","Puedo hacerlo con dificultad","Puedo hacerlo sin ayuda") -> Puedo hacerlo sin ayuda | AC7: =CHOOSE(INT(MOD((ROW()-2)*157+83,479)/120)+1,"No puedo hacerlo","Puedo hacerlo con ayuda","Puedo hacerlo con dificultad","Puedo hacerlo sin ayuda") -> Puedo hacerlo sin ayuda | AD7: =CHOOSE(INT(MOD((ROW()-2)*89+131,479)/120)+1,"No puedo hacerlo","Puedo hacerlo con ayuda","Puedo hacerlo con dificultad","Puedo hacerlo sin ayuda") -> No puedo hacerlo | AE7: =CHOOSE(INT(MOD((ROW()-2)*73+179,479)/120)+1,"No puedo hacerlo","Puedo hacerlo con ayuda","Puedo hacerlo con dificultad","Puedo hacerlo sin ayuda") -> No puedo hacerlo | AF7: =CHOOSE(MOD((ROW()-2)*61+23,10)+1,"Crear una hoja de vida","Preparación para entrevista","Comunicación","Liderazgo","Emprendimiento","Herramientas digitales","Educación financiera","Crear una hoja de vida;Preparación para entrevista","Comunicación;Liderazgo","Herramientas digitales;Educación financiera") -> Comunicación;Liderazgo | AG7: =CHOOSE(MOD(INT((ROW()-2)/3)*7,9)+1,"Costos de transporte","Distancia","Horarios","Falta de experiencia","Falta de información","Ninguna","Costos de transporte;Distancia","Horarios;Falta de información","Falta de experiencia;Falta de información") -> Horarios;Falta de información | AH7: =CHOOSE(INT(MOD((ROW()-2)*199+59,479)/120)+1,"Oficina de orientación laboral","Ferias de empleo","Programas de emprendimiento","No conozco ninguno") -> Oficina de orientación laboral | AI7: =CHOOSE(INT(MOD((ROW()-2)*127+71,479)/120)+1,"Presencial","Virtual","Presencial y virtual","Me es indiferente") -> Virtual | AJ7: =CHOOSE(INT(MOD((ROW()-2)*163+97,479)/120)+1,"Diurno","Nocturno","Mañana entre semana","Fines de semana") -> Fines de semana | AK7: =CHOOSE(INT(MOD((ROW()-2)*181+109,479)/120)+1,"WhatsApp","Correo electrónico","Redes sociales","Celular") -> WhatsApp
A8: ="SG"&TEXT(ROW()-1,"000") -> SG007 | B8: Urbana Consolidada | C8: SI, ACEPTO PARTICIPAR | D8: =IF(MOD((ROW()-2)*137,479)<230,"Masculino",IF(MOD((ROW()-2)*137,479)<460,"Femenino",IF(MOD((ROW()-2)*137,479)<470,"Otro","No quiero responder"))) -> Femenino | E8: =CHOOSE(MOD(ROW()-2,5)+1,"De 18 a 20 años","De 20 a 22 años","De 22 a 24 años","De 24 a 26 años","De 26 a 28 años") -> De 20 a 22 años | F8: =CHOOSE(MOD(ROW()-2,5)+1,18,20,22,24,26)+MOD(INT((ROW()-2)/5),IF(MOD(ROW()-2,5)=4,3,2)) -> 21 | G8: URBANA | H8: =_xlfn.LET(_xlpm.grupo,MOD(ROW()-2,5),_xlpm.turno,INT((ROW()-2)/5),_xlpm.orden,MOD(_xlpm.turno*37,IF(_xlpm.grupo=4,95,96)),CHOOSE(_xlpm.grupo+1,IF(_xlpm.orden<60,"Bachiller",IF(_xlpm.orden<84,"Técnico","Tecnólogo")),IF(_xlpm.orden<36,"Bachiller",IF(_xlpm.orden<66,"Técnico","Tecnólogo")),IF(_xlpm.orden<24,"Bachiller",IF(_xlpm.orden<48,"Técnico",IF(_xlpm.orden<72,"Tecnólogo","Profesional"))),IF(_xlpm.orden<12,"Bachiller",IF(_xlpm.orden<30,"Técnico",IF(_xlpm.orden<54,"Tecnólogo",IF(_xlpm.orden<90,"Profesional","Posgrado")))),IF(_xlpm.orden<10,"Bachiller",IF(_xlpm.orden<25,"Técnico",IF(_xlpm.orden<45,"Tecnólogo",IF(_xlpm.orden<85,"Profesional","Posgrado")))))) -> Técnico | I8: =_xlfn.LET(_xlpm.orden,MOD((ROW()-2)*173,479),IF(_xlpm.orden<150,"Trabajo actualmente como empleado",IF(_xlpm.orden<230,"Trabajo de manera independiente",IF(_xlpm.orden<320,"Actualmente no trabajo y estoy buscando empleo",IF(_xlpm.orden<380,"Busco mi primer empleo",IF(_xlpm.orden<440,"Estudio y quiero comenzar a trabajar","Tengo un emprendimiento o quiero iniciar uno")))))) -> Trabajo actualmente como empleado | J8: =IF(I8="Trabajo actualmente como empleado",IF(MOD((COUNTIF($I$2:I8,"Trabajo actualmente como empleado")-1)*37,150)<100,"Empleado con contrato","Empleado sin contrato formal"),IF(I8="Trabajo de manera independiente","Trabajo independiente","")) -> Empleado con contrato | K8: =IF(OR(I8="Trabajo actualmente como empleado",I8="Trabajo de manera independiente"),CHOOSE(MOD(COUNTIF($I$2:I8,I8)-1,4)+1,"Menos de 3 meses","De 3 a 6 meses","De 7 a 12 meses","Más de un año"),"") -> De 7 a 12 meses | L8: =IF(OR(I8="Trabajo actualmente como empleado",I8="Trabajo de manera independiente"),CHOOSE(MOD(COUNTIF($I$2:I8,I8)-1,3)+1,"Sí, completamente","Parcialmente","No"),"") -> No | M8: =IF(OR(I8="Trabajo actualmente como empleado",I8="Trabajo de manera independiente"),CHOOSE(MOD(INT((COUNTIF($I$2:I8,I8)-1)/3),4)+1,"1- Muy satisfecho/a","2- Satisfecho/a","3- Insatisfecho/a","4- Muy insatisfecho/a"),"") -> 1- Muy satisfecho/a | N8: =IF(OR(I8="Trabajo actualmente como empleado",I8="Trabajo de manera independiente"),_xlfn.LET(_xlpm.opcion,MOD(INT((COUNTIF($I$2:I8,I8)-1)/5),6)+1,CHOOSE(IF(AND(_xlpm.opcion=6,L8="Sí, completamente"),5,_xlpm.opcion),"Salario","Estabilidad laboral","Horario","Acceso a prestaciones","Oportunidades de crecimiento","Trabajar en un área relacionada con mi formación")),"") -> Salario | O8: =IF(OR(I8="Trabajo actualmente como empleado",I8="Trabajo de manera independiente"),_xlfn.LET(_xlpm.turno,MOD(COUNTIF($I$2:I8,I8)-1,5),_xlpm.nivel,VALUE(LEFT(M8,1)),IF(_xlpm.turno=4,"No estoy seguro/a",IF(_xlpm.turno<IF(_xlpm.nivel<=2,1,3),"Sí","No"))),"") -> No | P8: =_xlfn.LET(_xlpm.perfil,I8,_xlpm.turno,COUNTIF($I$2:I8,_xlpm.perfil)-1,_xlpm.busca,OR(_xlpm.perfil="Actualmente no trabajo y estoy buscando empleo",_xlpm.perfil="Busco mi primer empleo"),_xlpm.trabaja,OR(_xlpm.perfil="Trabajo actualmente como empleado",_xlpm.perfil="Trabajo de manera independiente"),IF(_xlpm.busca,CHOOSE(MOD(_xlpm.turno*3,4)+1,"Menos de 1 mes","Entre 1 y 3 meses","Entre 4 y 6 meses","Más de 6 meses"),IF(OR(_xlpm.trabaja,_xlpm.perfil="Estudio y quiero comenzar a trabajar"),IF(AND(_xlpm.trabaja,O8="No"),"Todavía no he iniciado una búsqueda activa",CHOOSE(MOD(_xlpm.turno*3,5)+1,"Menos de 1 mes","Entre 1 y 3 meses","Entre 4 y 6 meses","Más de 6 meses","Todavía no he iniciado una búsqueda activa")),""))) -> Todavía no he iniciado una búsqueda activa | Q8: =IF(I8="Tengo un emprendimiento o quiero iniciar uno","",CHOOSE(MOD(INT((COUNTIF($I$2:I8,I8)-1)/7),3)+1,"Sí","No","Tengo una pero necesito actualizarla")) -> Sí | R8: =IF(I8="Tengo un emprendimiento o quiero iniciar uno","",IF(I8="Busco mi primer empleo","No",IF(MOD(COUNTIF($I$2:I8,I8)-1,2)=0,"Sí","No"))) -> Sí | S8: =IF(I8="Tengo un emprendimiento o quiero iniciar uno","",CHOOSE(MOD(INT((COUNTIF($I$2:I8,I8)-1)/3),10)+1,"Portales de empleo","Redes sociales","Familiares o conocidos","Empresas directamente","Ferias de empleo","Instituciones públicas","Institución educativa","No sé dónde buscar","Portales de empleo;Redes sociales","Familiares o conocidos;Empresas directamente")) -> Portales de empleo | T8: =IF(I8="Tengo un emprendimiento o quiero iniciar uno","",_xlfn.LET(_xlpm.opcion,MOD(INT((COUNTIF($I$2:I8,I8)-1)/4),6)+1,CHOOSE(IF(AND(_xlpm.opcion=3,Q8="Sí"),1,_xlpm.opcion),"Falta de experiencia","Falta de formación","Dificultades con la hoja de vida","Horarios disponibles","Transporte","Internet"))) -> Falta de experiencia | U8: =IF(I8="Tengo un emprendimiento o quiero iniciar uno","",IF(MOD(INT((COUNTIF($I$2:I8,I8)-1)/3),2)=0,"Sí","No")) -> Sí | V8: =IF(I8="Tengo un emprendimiento o quiero iniciar uno",CHOOSE(MOD(COUNTIF($I$2:I8,I8)-1,3)+1,"Tengo un emprendimiento","Estoy iniciando un emprendimiento","Me interesa emprender"),"") | W8: =IF(V8="Tengo un emprendimiento","Funcionamiento estable",IF(V8="Estoy iniciando un emprendimiento","Inicio","")) | X8: =IF(I8="Tengo un emprendimiento o quiero iniciar uno",CHOOSE(MOD(COUNTIF($I$2:I8,I8)-1,5)+1,"Falta de financiación","Falta de conocimientos administrativos","Falta de conocimientos financieros","Falta de tiempo","Falta de herramientas"),"") | Y8: =IF(I8="Tengo un emprendimiento o quiero iniciar uno",X8,"") | Z8: =IF(I8="Tengo un emprendimiento o quiero iniciar uno",CHOOSE(INT(MOD((COUNTIF($I$2:I8,I8)-1)*7,39)/13)+1,"Sí","No","No conozco programas de ese tipo"),"") | AA8: =CHOOSE(INT(MOD((ROW()-2)*191,479)/120)+1,"No puedo hacerlo","Puedo hacerlo con ayuda","Puedo hacerlo con dificultad","Puedo hacerlo sin ayuda") -> Puedo hacerlo con ayuda | AB8: =CHOOSE(INT(MOD((ROW()-2)*191,479)/120)+1,"No puedo hacerlo","Puedo hacerlo con ayuda","Puedo hacerlo con dificultad","Puedo hacerlo sin ayuda") -> Puedo hacerlo con ayuda | AC8: =CHOOSE(INT(MOD((ROW()-2)*157+83,479)/120)+1,"No puedo hacerlo","Puedo hacerlo con ayuda","Puedo hacerlo con dificultad","Puedo hacerlo sin ayuda") -> No puedo hacerlo | AD8: =CHOOSE(INT(MOD((ROW()-2)*89+131,479)/120)+1,"No puedo hacerlo","Puedo hacerlo con ayuda","Puedo hacerlo con dificultad","Puedo hacerlo sin ayuda") -> Puedo hacerlo con ayuda | AE8: =CHOOSE(INT(MOD((ROW()-2)*73+179,479)/120)+1,"No puedo hacerlo","Puedo hacerlo con ayuda","Puedo hacerlo con dificultad","Puedo hacerlo sin ayuda") -> Puedo hacerlo con ayuda | AF8: =CHOOSE(MOD((ROW()-2)*61+23,10)+1,"Crear una hoja de vida","Preparación para entrevista","Comunicación","Liderazgo","Emprendimiento","Herramientas digitales","Educación financiera","Crear una hoja de vida;Preparación para entrevista","Comunicación;Liderazgo","Herramientas digitales;Educación financiera") -> Herramientas digitales;Educación financiera | AG8: =CHOOSE(MOD(INT((ROW()-2)/3)*7,9)+1,"Costos de transporte","Distancia","Horarios","Falta de experiencia","Falta de información","Ninguna","Costos de transporte;Distancia","Horarios;Falta de información","Falta de experiencia;Falta de información") -> Ninguna | AH8: =CHOOSE(INT(MOD((ROW()-2)*199+59,479)/120)+1,"Oficina de orientación laboral","Ferias de empleo","Programas de emprendimiento","No conozco ninguno") -> Programas de emprendimiento | AI8: =CHOOSE(INT(MOD((ROW()-2)*127+71,479)/120)+1,"Presencial","Virtual","Presencial y virtual","Me es indiferente") -> Presencial y virtual | AJ8: =CHOOSE(INT(MOD((ROW()-2)*163+97,479)/120)+1,"Diurno","Nocturno","Mañana entre semana","Fines de semana") -> Diurno | AK8: =CHOOSE(INT(MOD((ROW()-2)*181+109,479)/120)+1,"WhatsApp","Correo electrónico","Redes sociales","Celular") -> Correo electrónico
A9: ="SG"&TEXT(ROW()-1,"000") -> SG008 | B9: Urbana Consolidada | C9: SI, ACEPTO PARTICIPAR | D9: =IF(MOD((ROW()-2)*137,479)<230,"Masculino",IF(MOD((ROW()-2)*137,479)<460,"Femenino",IF(MOD((ROW()-2)*137,479)<470,"Otro","No quiero responder"))) -> Masculino | E9: =CHOOSE(MOD(ROW()-2,5)+1,"De 18 a 20 años","De 20 a 22 años","De 22 a 24 años","De 24 a 26 años","De 26 a 28 años") -> De 22 a 24 años | F9: =CHOOSE(MOD(ROW()-2,5)+1,18,20,22,24,26)+MOD(INT((ROW()-2)/5),IF(MOD(ROW()-2,5)=4,3,2)) -> 23 | G9: URBANA | H9: =_xlfn.LET(_xlpm.grupo,MOD(ROW()-2,5),_xlpm.turno,INT((ROW()-2)/5),_xlpm.orden,MOD(_xlpm.turno*37,IF(_xlpm.grupo=4,95,96)),CHOOSE(_xlpm.grupo+1,IF(_xlpm.orden<60,"Bachiller",IF(_xlpm.orden<84,"Técnico","Tecnólogo")),IF(_xlpm.orden<36,"Bachiller",IF(_xlpm.orden<66,"Técnico","Tecnólogo")),IF(_xlpm.orden<24,"Bachiller",IF(_xlpm.orden<48,"Técnico",IF(_xlpm.orden<72,"Tecnólogo","Profesional"))),IF(_xlpm.orden<12,"Bachiller",IF(_xlpm.orden<30,"Técnico",IF(_xlpm.orden<54,"Tecnólogo",IF(_xlpm.orden<90,"Profesional","Posgrado")))),IF(_xlpm.orden<10,"Bachiller",IF(_xlpm.orden<25,"Técnico",IF(_xlpm.orden<45,"Tecnólogo",IF(_xlpm.orden<85,"Profesional","Posgrado")))))) -> Técnico | I9: =_xlfn.LET(_xlpm.orden,MOD((ROW()-2)*173,479),IF(_xlpm.orden<150,"Trabajo actualmente como empleado",IF(_xlpm.orden<230,"Trabajo de manera independiente",IF(_xlpm.orden<320,"Actualmente no trabajo y estoy buscando empleo",IF(_xlpm.orden<380,"Busco mi primer empleo",IF(_xlpm.orden<440,"Estudio y quiero comenzar a trabajar","Tengo un emprendimiento o quiero iniciar uno")))))) -> Actualmente no trabajo y estoy buscando empleo | J9: =IF(I9="Trabajo actualmente como empleado",IF(MOD((COUNTIF($I$2:I9,"Trabajo actualmente como empleado")-1)*37,150)<100,"Empleado con contrato","Empleado sin contrato formal"),IF(I9="Trabajo de manera independiente","Trabajo independiente","")) | K9: =IF(OR(I9="Trabajo actualmente como empleado",I9="Trabajo de manera independiente"),CHOOSE(MOD(COUNTIF($I$2:I9,I9)-1,4)+1,"Menos de 3 meses","De 3 a 6 meses","De 7 a 12 meses","Más de un año"),"") | L9: =IF(OR(I9="Trabajo actualmente como empleado",I9="Trabajo de manera independiente"),CHOOSE(MOD(COUNTIF($I$2:I9,I9)-1,3)+1,"Sí, completamente","Parcialmente","No"),"") | M9: =IF(OR(I9="Trabajo actualmente como empleado",I9="Trabajo de manera independiente"),CHOOSE(MOD(INT((COUNTIF($I$2:I9,I9)-1)/3),4)+1,"1- Muy satisfecho/a","2- Satisfecho/a","3- Insatisfecho/a","4- Muy insatisfecho/a"),"") | N9: =IF(OR(I9="Trabajo actualmente como empleado",I9="Trabajo de manera independiente"),_xlfn.LET(_xlpm.opcion,MOD(INT((COUNTIF($I$2:I9,I9)-1)/5),6)+1,CHOOSE(IF(AND(_xlpm.opcion=6,L9="Sí, completamente"),5,_xlpm.opcion),"Salario","Estabilidad laboral","Horario","Acceso a prestaciones","Oportunidades de crecimiento","Trabajar en un área relacionada con mi formación")),"") | O9: =IF(OR(I9="Trabajo actualmente como empleado",I9="Trabajo de manera independiente"),_xlfn.LET(_xlpm.turno,MOD(COUNTIF($I$2:I9,I9)-1,5),_xlpm.nivel,VALUE(LEFT(M9,1)),IF(_xlpm.turno=4,"No estoy seguro/a",IF(_xlpm.turno<IF(_xlpm.nivel<=2,1,3),"Sí","No"))),"") | P9: =_xlfn.LET(_xlpm.perfil,I9,_xlpm.turno,COUNTIF($I$2:I9,_xlpm.perfil)-1,_xlpm.busca,OR(_xlpm.perfil="Actualmente no trabajo y estoy buscando empleo",_xlpm.perfil="Busco mi primer empleo"),_xlpm.trabaja,OR(_xlpm.perfil="Trabajo actualmente como empleado",_xlpm.perfil="Trabajo de manera independiente"),IF(_xlpm.busca,CHOOSE(MOD(_xlpm.turno*3,4)+1,"Menos de 1 mes","Entre 1 y 3 meses","Entre 4 y 6 meses","Más de 6 meses"),IF(OR(_xlpm.trabaja,_xlpm.perfil="Estudio y quiero comenzar a trabajar"),IF(AND(_xlpm.trabaja,O9="No"),"Todavía no he iniciado una búsqueda activa",CHOOSE(MOD(_xlpm.turno*3,5)+1,"Menos de 1 mes","Entre 1 y 3 meses","Entre 4 y 6 meses","Más de 6 meses","Todavía no he iniciado una búsqueda activa")),""))) -> Menos de 1 mes | Q9: =IF(I9="Tengo un emprendimiento o quiero iniciar uno","",CHOOSE(MOD(INT((COUNTIF($I$2:I9,I9)-1)/7),3)+1,"Sí","No","Tengo una pero necesito actualizarla")) -> Sí | R9: =IF(I9="Tengo un emprendimiento o quiero iniciar uno","",IF(I9="Busco mi primer empleo","No",IF(MOD(COUNTIF($I$2:I9,I9)-1,2)=0,"Sí","No"))) -> Sí | S9: =IF(I9="Tengo un emprendimiento o quiero iniciar uno","",CHOOSE(MOD(INT((COUNTIF($I$2:I9,I9)-1)/3),10)+1,"Portales de empleo","Redes sociales","Familiares o conocidos","Empresas directamente","Ferias de empleo","Instituciones públicas","Institución educativa","No sé dónde buscar","Portales de empleo;Redes sociales","Familiares o conocidos;Empresas directamente")) -> Portales de empleo | T9: =IF(I9="Tengo un emprendimiento o quiero iniciar uno","",_xlfn.LET(_xlpm.opcion,MOD(INT((COUNTIF($I$2:I9,I9)-1)/4),6)+1,CHOOSE(IF(AND(_xlpm.opcion=3,Q9="Sí"),1,_xlpm.opcion),"Falta de experiencia","Falta de formación","Dificultades con la hoja de vida","Horarios disponibles","Transporte","Internet"))) -> Falta de experiencia | U9: =IF(I9="Tengo un emprendimiento o quiero iniciar uno","",IF(MOD(INT((COUNTIF($I$2:I9,I9)-1)/3),2)=0,"Sí","No")) -> Sí | V9: =IF(I9="Tengo un emprendimiento o quiero iniciar uno",CHOOSE(MOD(COUNTIF($I$2:I9,I9)-1,3)+1,"Tengo un emprendimiento","Estoy iniciando un emprendimiento","Me interesa emprender"),"") | W9: =IF(V9="Tengo un emprendimiento","Funcionamiento estable",IF(V9="Estoy iniciando un emprendimiento","Inicio","")) | X9: =IF(I9="Tengo un emprendimiento o quiero iniciar uno",CHOOSE(MOD(COUNTIF($I$2:I9,I9)-1,5)+1,"Falta de financiación","Falta de conocimientos administrativos","Falta de conocimientos financieros","Falta de tiempo","Falta de herramientas"),"") | Y9: =IF(I9="Tengo un emprendimiento o quiero iniciar uno",X9,"") | Z9: =IF(I9="Tengo un emprendimiento o quiero iniciar uno",CHOOSE(INT(MOD((COUNTIF($I$2:I9,I9)-1)*7,39)/13)+1,"Sí","No","No conozco programas de ese tipo"),"") | AA9: =CHOOSE(INT(MOD((ROW()-2)*191,479)/120)+1,"No puedo hacerlo","Puedo hacerlo con ayuda","Puedo hacerlo con dificultad","Puedo hacerlo sin ayuda") -> Puedo hacerlo sin ayuda | AB9: =CHOOSE(INT(MOD((ROW()-2)*191,479)/120)+1,"No puedo hacerlo","Puedo hacerlo con ayuda","Puedo hacerlo con dificultad","Puedo hacerlo sin ayuda") -> Puedo hacerlo sin ayuda | AC9: =CHOOSE(INT(MOD((ROW()-2)*157+83,479)/120)+1,"No puedo hacerlo","Puedo hacerlo con ayuda","Puedo hacerlo con dificultad","Puedo hacerlo sin ayuda") -> Puedo hacerlo con ayuda | AD9: =CHOOSE(INT(MOD((ROW()-2)*89+131,479)/120)+1,"No puedo hacerlo","Puedo hacerlo con ayuda","Puedo hacerlo con dificultad","Puedo hacerlo sin ayuda") -> Puedo hacerlo con dificultad | AE9: =CHOOSE(INT(MOD((ROW()-2)*73+179,479)/120)+1,"No puedo hacerlo","Puedo hacerlo con ayuda","Puedo hacerlo con dificultad","Puedo hacerlo sin ayuda") -> Puedo hacerlo con ayuda | AF9: =CHOOSE(MOD((ROW()-2)*61+23,10)+1,"Crear una hoja de vida","Preparación para entrevista","Comunicación","Liderazgo","Emprendimiento","Herramientas digitales","Educación financiera","Crear una hoja de vida;Preparación para entrevista","Comunicación;Liderazgo","Herramientas digitales;Educación financiera") -> Crear una hoja de vida | AG9: =CHOOSE(MOD(INT((ROW()-2)/3)*7,9)+1,"Costos de transporte","Distancia","Horarios","Falta de experiencia","Falta de información","Ninguna","Costos de transporte;Distancia","Horarios;Falta de información","Falta de experiencia;Falta de información") -> Ninguna | AH9: =CHOOSE(INT(MOD((ROW()-2)*199+59,479)/120)+1,"Oficina de orientación laboral","Ferias de empleo","Programas de emprendimiento","No conozco ninguno") -> Oficina de orientación laboral | AI9: =CHOOSE(INT(MOD((ROW()-2)*127+71,479)/120)+1,"Presencial","Virtual","Presencial y virtual","Me es indiferente") -> Presencial | AJ9: =CHOOSE(INT(MOD((ROW()-2)*163+97,479)/120)+1,"Diurno","Nocturno","Mañana entre semana","Fines de semana") -> Mañana entre semana | AK9: =CHOOSE(INT(MOD((ROW()-2)*181+109,479)/120)+1,"WhatsApp","Correo electrónico","Redes sociales","Celular") -> Celular
A10: ="SG"&TEXT(ROW()-1,"000") -> SG009 | B10: Urbana Consolidada | C10: SI, ACEPTO PARTICIPAR | D10: =IF(MOD((ROW()-2)*137,479)<230,"Masculino",IF(MOD((ROW()-2)*137,479)<460,"Femenino",IF(MOD((ROW()-2)*137,479)<470,"Otro","No quiero responder"))) -> Masculino | E10: =CHOOSE(MOD(ROW()-2,5)+1,"De 18 a 20 años","De 20 a 22 años","De 22 a 24 años","De 24 a 26 años","De 26 a 28 años") -> De 24 a 26 años | F10: =CHOOSE(MOD(ROW()-2,5)+1,18,20,22,24,26)+MOD(INT((ROW()-2)/5),IF(MOD(ROW()-2,5)=4,3,2)) -> 25 | G10: URBANA | H10: =_xlfn.LET(_xlpm.grupo,MOD(ROW()-2,5),_xlpm.turno,INT((ROW()-2)/5),_xlpm.orden,MOD(_xlpm.turno*37,IF(_xlpm.grupo=4,95,96)),CHOOSE(_xlpm.grupo+1,IF(_xlpm.orden<60,"Bachiller",IF(_xlpm.orden<84,"Técnico","Tecnólogo")),IF(_xlpm.orden<36,"Bachiller",IF(_xlpm.orden<66,"Técnico","Tecnólogo")),IF(_xlpm.orden<24,"Bachiller",IF(_xlpm.orden<48,"Técnico",IF(_xlpm.orden<72,"Tecnólogo","Profesional"))),IF(_xlpm.orden<12,"Bachiller",IF(_xlpm.orden<30,"Técnico",IF(_xlpm.orden<54,"Tecnólogo",IF(_xlpm.orden<90,"Profesional","Posgrado")))),IF(_xlpm.orden<10,"Bachiller",IF(_xlpm.orden<25,"Técnico",IF(_xlpm.orden<45,"Tecnólogo",IF(_xlpm.orden<85,"Profesional","Posgrado")))))) -> Tecnólogo | I10: =_xlfn.LET(_xlpm.orden,MOD((ROW()-2)*173,479),IF(_xlpm.orden<150,"Trabajo actualmente como empleado",IF(_xlpm.orden<230,"Trabajo de manera independiente",IF(_xlpm.orden<320,"Actualmente no trabajo y estoy buscando empleo",IF(_xlpm.orden<380,"Busco mi primer empleo",IF(_xlpm.orden<440,"Estudio y quiero comenzar a trabajar","Tengo un emprendimiento o quiero iniciar uno")))))) -> Estudio y quiero comenzar a trabajar | J10: =IF(I10="Trabajo actualmente como empleado",IF(MOD((COUNTIF($I$2:I10,"Trabajo actualmente como empleado")-1)*37,150)<100,"Empleado con contrato","Empleado sin contrato formal"),IF(I10="Trabajo de manera independiente","Trabajo independiente","")) | K10: =IF(OR(I10="Trabajo actualmente como empleado",I10="Trabajo de manera independiente"),CHOOSE(MOD(COUNTIF($I$2:I10,I10)-1,4)+1,"Menos de 3 meses","De 3 a 6 meses","De 7 a 12 meses","Más de un año"),"") | L10: =IF(OR(I10="Trabajo actualmente como empleado",I10="Trabajo de manera independiente"),CHOOSE(MOD(COUNTIF($I$2:I10,I10)-1,3)+1,"Sí, completamente","Parcialmente","No"),"") | M10: =IF(OR(I10="Trabajo actualmente como empleado",I10="Trabajo de manera independiente"),CHOOSE(MOD(INT((COUNTIF($I$2:I10,I10)-1)/3),4)+1,"1- Muy satisfecho/a","2- Satisfecho/a","3- Insatisfecho/a","4- Muy insatisfecho/a"),"") | N10: =IF(OR(I10="Trabajo actualmente como empleado",I10="Trabajo de manera independiente"),_xlfn.LET(_xlpm.opcion,MOD(INT((COUNTIF($I$2:I10,I10)-1)/5),6)+1,CHOOSE(IF(AND(_xlpm.opcion=6,L10="Sí, completamente"),5,_xlpm.opcion),"Salario","Estabilidad laboral","Horario","Acceso a prestaciones","Oportunidades de crecimiento","Trabajar en un área relacionada con mi formación")),"") | O10: =IF(OR(I10="Trabajo actualmente como empleado",I10="Trabajo de manera independiente"),_xlfn.LET(_xlpm.turno,MOD(COUNTIF($I$2:I10,I10)-1,5),_xlpm.nivel,VALUE(LEFT(M10,1)),IF(_xlpm.turno=4,"No estoy seguro/a",IF(_xlpm.turno<IF(_xlpm.nivel<=2,1,3),"Sí","No"))),"") | P10: =_xlfn.LET(_xlpm.perfil,I10,_xlpm.turno,COUNTIF($I$2:I10,_xlpm.perfil)-1,_xlpm.busca,OR(_xlpm.perfil="Actualmente no trabajo y estoy buscando empleo",_xlpm.perfil="Busco mi primer empleo"),_xlpm.trabaja,OR(_xlpm.perfil="Trabajo actualmente como empleado",_xlpm.perfil="Trabajo de manera independiente"),IF(_xlpm.busca,CHOOSE(MOD(_xlpm.turno*3,4)+1,"Menos de 1 mes","Entre 1 y 3 meses","Entre 4 y 6 meses","Más de 6 meses"),IF(OR(_xlpm.trabaja,_xlpm.perfil="Estudio y quiero comenzar a trabajar"),IF(AND(_xlpm.trabaja,O10="No"),"Todavía no he iniciado una búsqueda activa",CHOOSE(MOD(_xlpm.turno*3,5)+1,"Menos de 1 mes","Entre 1 y 3 meses","Entre 4 y 6 meses","Más de 6 meses","Todavía no he iniciado una búsqueda activa")),""))) -> Más de 6 meses | Q10: =IF(I10="Tengo un emprendimiento o quiero iniciar uno","",CHOOSE(MOD(INT((COUNTIF($I$2:I10,I10)-1)/7),3)+1,"Sí","No","Tengo una pero necesito actualizarla")) -> Sí | R10: =IF(I10="Tengo un emprendimiento o quiero iniciar uno","",IF(I10="Busco mi primer empleo","No",IF(MOD(COUNTIF($I$2:I10,I10)-1,2)=0,"Sí","No"))) -> No | S10: =IF(I10="Tengo un emprendimiento o quiero iniciar uno","",CHOOSE(MOD(INT((COUNTIF($I$2:I10,I10)-1)/3),10)+1,"Portales de empleo","Redes sociales","Familiares o conocidos","Empresas directamente","Ferias de empleo","Instituciones públicas","Institución educativa","No sé dónde buscar","Portales de empleo;Redes sociales","Familiares o conocidos;Empresas directamente")) -> Portales de empleo | T10: =IF(I10="Tengo un emprendimiento o quiero iniciar uno","",_xlfn.LET(_xlpm.opcion,MOD(INT((COUNTIF($I$2:I10,I10)-1)/4),6)+1,CHOOSE(IF(AND(_xlpm.opcion=3,Q10="Sí"),1,_xlpm.opcion),"Falta de experiencia","Falta de formación","Dificultades con la hoja de vida","Horarios disponibles","Transporte","Internet"))) -> Falta de experiencia | U10: =IF(I10="Tengo un emprendimiento o quiero iniciar uno","",IF(MOD(INT((COUNTIF($I$2:I10,I10)-1)/3),2)=0,"Sí","No")) -> Sí | V10: =IF(I10="Tengo un emprendimiento o quiero iniciar uno",CHOOSE(MOD(COUNTIF($I$2:I10,I10)-1,3)+1,"Tengo un emprendimiento","Estoy iniciando un emprendimiento","Me interesa emprender"),"") | W10: =IF(V10="Tengo un emprendimiento","Funcionamiento estable",IF(V10="Estoy iniciando un emprendimiento","Inicio","")) | X10: =IF(I10="Tengo un emprendimiento o quiero iniciar uno",CHOOSE(MOD(COUNTIF($I$2:I10,I10)-1,5)+1,"Falta de financiación","Falta de conocimientos administrativos","Falta de conocimientos financieros","Falta de tiempo","Falta de herramientas"),"") | Y10: =IF(I10="Tengo un emprendimiento o quiero iniciar uno",X10,"") | Z10: =IF(I10="Tengo un emprendimiento o quiero iniciar uno",CHOOSE(INT(MOD((COUNTIF($I$2:I10,I10)-1)*7,39)/13)+1,"Sí","No","No conozco programas de ese tipo"),"") | AA10: =CHOOSE(INT(MOD((ROW()-2)*191,479)/120)+1,"No puedo hacerlo","Puedo hacerlo con ayuda","Puedo hacerlo con dificultad","Puedo hacerlo sin ayuda") -> No puedo hacerlo | AB10: =CHOOSE(INT(MOD((ROW()-2)*191,479)/120)+1,"No puedo hacerlo","Puedo hacerlo con ayuda","Puedo hacerlo con dificultad","Puedo hacerlo sin ayuda") -> No puedo hacerlo | AC10: =CHOOSE(INT(MOD((ROW()-2)*157+83,479)/120)+1,"No puedo hacerlo","Puedo hacerlo con ayuda","Puedo hacerlo con dificultad","Puedo hacerlo sin ayuda") -> Puedo hacerlo sin ayuda | AD10: =CHOOSE(INT(MOD((ROW()-2)*89+131,479)/120)+1,"No puedo hacerlo","Puedo hacerlo con ayuda","Puedo hacerlo con dificultad","Puedo hacerlo sin ayuda") -> Puedo hacerlo sin ayuda | AE10: =CHOOSE(INT(MOD((ROW()-2)*73+179,479)/120)+1,"No puedo hacerlo","Puedo hacerlo con ayuda","Puedo hacerlo con dificultad","Puedo hacerlo sin ayuda") -> Puedo hacerlo con dificultad | AF10: =CHOOSE(MOD((ROW()-2)*61+23,10)+1,"Crear una hoja de vida","Preparación para entrevista","Comunicación","Liderazgo","Emprendimiento","Herramientas digitales","Educación financiera","Crear una hoja de vida;Preparación para entrevista","Comunicación;Liderazgo","Herramientas digitales;Educación financiera") -> Preparación para entrevista | AG10: =CHOOSE(MOD(INT((ROW()-2)/3)*7,9)+1,"Costos de transporte","Distancia","Horarios","Falta de experiencia","Falta de información","Ninguna","Costos de transporte;Distancia","Horarios;Falta de información","Falta de experiencia;Falta de información") -> Ninguna | AH10: =CHOOSE(INT(MOD((ROW()-2)*199+59,479)/120)+1,"Oficina de orientación laboral","Ferias de empleo","Programas de emprendimiento","No conozco ninguno") -> Ferias de empleo | AI10: =CHOOSE(INT(MOD((ROW()-2)*127+71,479)/120)+1,"Presencial","Virtual","Presencial y virtual","Me es indiferente") -> Virtual | AJ10: =CHOOSE(INT(MOD((ROW()-2)*163+97,479)/120)+1,"Diurno","Nocturno","Mañana entre semana","Fines de semana") -> Fines de semana | AK10: =CHOOSE(INT(MOD((ROW()-2)*181+109,479)/120)+1,"WhatsApp","Correo electrónico","Redes sociales","Celular") -> Correo electrónico
A11: ="SG"&TEXT(ROW()-1,"000") -> SG010 | B11: Urbana Consolidada | C11: SI, ACEPTO PARTICIPAR | D11: =IF(MOD((ROW()-2)*137,479)<230,"Masculino",IF(MOD((ROW()-2)*137,479)<460,"Femenino",IF(MOD((ROW()-2)*137,479)<470,"Otro","No quiero responder"))) -> Femenino | E11: =CHOOSE(MOD(ROW()-2,5)+1,"De 18 a 20 años","De 20 a 22 años","De 22 a 24 años","De 24 a 26 años","De 26 a 28 años") -> De 26 a 28 años | F11: =CHOOSE(MOD(ROW()-2,5)+1,18,20,22,24,26)+MOD(INT((ROW()-2)/5),IF(MOD(ROW()-2,5)=4,3,2)) -> 27 | G11: URBANA | H11: =_xlfn.LET(_xlpm.grupo,MOD(ROW()-2,5),_xlpm.turno,INT((ROW()-2)/5),_xlpm.orden,MOD(_xlpm.turno*37,IF(_xlpm.grupo=4,95,96)),CHOOSE(_xlpm.grupo+1,IF(_xlpm.orden<60,"Bachiller",IF(_xlpm.orden<84,"Técnico","Tecnólogo")),IF(_xlpm.orden<36,"Bachiller",IF(_xlpm.orden<66,"Técnico","Tecnólogo")),IF(_xlpm.orden<24,"Bachiller",IF(_xlpm.orden<48,"Técnico",IF(_xlpm.orden<72,"Tecnólogo","Profesional"))),IF(_xlpm.orden<12,"Bachiller",IF(_xlpm.orden<30,"Técnico",IF(_xlpm.orden<54,"Tecnólogo",IF(_xlpm.orden<90,"Profesional","Posgrado")))),IF(_xlpm.orden<10,"Bachiller",IF(_xlpm.orden<25,"Técnico",IF(_xlpm.orden<45,"Tecnólogo",IF(_xlpm.orden<85,"Profesional","Posgrado")))))) -> Tecnólogo | I11: =_xlfn.LET(_xlpm.orden,MOD((ROW()-2)*173,479),IF(_xlpm.orden<150,"Trabajo actualmente como empleado",IF(_xlpm.orden<230,"Trabajo de manera independiente",IF(_xlpm.orden<320,"Actualmente no trabajo y estoy buscando empleo",IF(_xlpm.orden<380,"Busco mi primer empleo",IF(_xlpm.orden<440,"Estudio y quiero comenzar a trabajar","Tengo un emprendimiento o quiero iniciar uno")))))) -> Trabajo actualmente como empleado | J11: =IF(I11="Trabajo actualmente como empleado",IF(MOD((COUNTIF($I$2:I11,"Trabajo actualmente como empleado")-1)*37,150)<100,"Empleado con contrato","Empleado sin contrato formal"),IF(I11="Trabajo de manera independiente","Trabajo independiente","")) -> Empleado sin contrato formal | K11: =IF(OR(I11="Trabajo actualmente como empleado",I11="Trabajo de manera independiente"),CHOOSE(MOD(COUNTIF($I$2:I11,I11)-1,4)+1,"Menos de 3 meses","De 3 a 6 meses","De 7 a 12 meses","Más de un año"),"") -> Más de un año | L11: =IF(OR(I11="Trabajo actualmente como empleado",I11="Trabajo de manera independiente"),CHOOSE(MOD(COUNTIF($I$2:I11,I11)-1,3)+1,"Sí, completamente","Parcialmente","No"),"") -> Sí, completamente | M11: =IF(OR(I11="Trabajo actualmente como empleado",I11="Trabajo de manera independiente"),CHOOSE(MOD(INT((COUNTIF($I$2:I11,I11)-1)/3),4)+1,"1- Muy satisfecho/a","2- Satisfecho/a","3- Insatisfecho/a","4- Muy insatisfecho/a"),"") -> 2- Satisfecho/a | N11: =IF(OR(I11="Trabajo actualmente como empleado",I11="Trabajo de manera independiente"),_xlfn.LET(_xlpm.opcion,MOD(INT((COUNTIF($I$2:I11,I11)-1)/5),6)+1,CHOOSE(IF(AND(_xlpm.opcion=6,L11="Sí, completamente"),5,_xlpm.opcion),"Salario","Estabilidad laboral","Horario","Acceso a prestaciones","Oportunidades de crecimiento","Trabajar en un área relacionada con mi formación")),"") -> Salario | O11: =IF(OR(I11="Trabajo actualmente como empleado",I11="Trabajo de manera independiente"),_xlfn.LET(_xlpm.turno,MOD(COUNTIF($I$2:I11,I11)-1,5),_xlpm.nivel,VALUE(LEFT(M11,1)),IF(_xlpm.turno=4,"No estoy seguro/a",IF(_xlpm.turno<IF(_xlpm.nivel<=2,1,3),"Sí","No"))),"") -> No | P11: =_xlfn.LET(_xlpm.perfil,I11,_xlpm.turno,COUNTIF($I$2:I11,_xlpm.perfil)-1,_xlpm.busca,OR(_xlpm.perfil="Actualmente no trabajo y estoy buscando empleo",_xlpm.perfil="Busco mi primer empleo"),_xlpm.trabaja,OR(_xlpm.perfil="Trabajo actualmente como empleado",_xlpm.perfil="Trabajo de manera independiente"),IF(_xlpm.busca,CHOOSE(MOD(_xlpm.turno*3,4)+1,"Menos de 1 mes","Entre 1 y 3 meses","Entre 4 y 6 meses","Más de 6 meses"),IF(OR(_xlpm.trabaja,_xlpm.perfil="Estudio y quiero comenzar a trabajar"),IF(AND(_xlpm.trabaja,O11="No"),"Todavía no he iniciado una búsqueda activa",CHOOSE(MOD(_xlpm.turno*3,5)+1,"Menos de 1 mes","Entre 1 y 3 meses","Entre 4 y 6 meses","Más de 6 meses","Todavía no he iniciado una búsqueda activa")),""))) -> Todavía no he iniciado una búsqueda activa | Q11: =IF(I11="Tengo un emprendimiento o quiero iniciar uno","",CHOOSE(MOD(INT((COUNTIF($I$2:I11,I11)-1)/7),3)+1,"Sí","No","Tengo una pero necesito actualizarla")) -> Sí | R11: =IF(I11="Tengo un emprendimiento o quiero iniciar uno","",IF(I11="Busco mi primer empleo","No",IF(MOD(COUNTIF($I$2:I11,I11)-1,2)=0,"Sí","No"))) -> No | S11: =IF(I11="Tengo un emprendimiento o quiero iniciar uno","",CHOOSE(MOD(INT((COUNTIF($I$2:I11,I11)-1)/3),10)+1,"Portales de empleo","Redes sociales","Familiares o conocidos","Empresas directamente","Ferias de empleo","Instituciones públicas","Institución educativa","No sé dónde buscar","Portales de empleo;Redes sociales","Familiares o conocidos;Empresas directamente")) -> Redes sociales | T11: =IF(I11="Tengo un emprendimiento o quiero iniciar uno","",_xlfn.LET(_xlpm.opcion,MOD(INT((COUNTIF($I$2:I11,I11)-1)/4),6)+1,CHOOSE(IF(AND(_xlpm.opcion=3,Q11="Sí"),1,_xlpm.opcion),"Falta de experiencia","Falta de formación","Dificultades con la hoja de vida","Horarios disponibles","Transporte","Internet"))) -> Falta de experiencia | U11: =IF(I11="Tengo un emprendimiento o quiero iniciar uno","",IF(MOD(INT((COUNTIF($I$2:I11,I11)-1)/3),2)=0,"Sí","No")) -> No | V11: =IF(I11="Tengo un emprendimiento o quiero iniciar uno",CHOOSE(MOD(COUNTIF($I$2:I11,I11)-1,3)+1,"Tengo un emprendimiento","Estoy iniciando un emprendimiento","Me interesa emprender"),"") | W11: =IF(V11="Tengo un emprendimiento","Funcionamiento estable",IF(V11="Estoy iniciando un emprendimiento","Inicio","")) | X11: =IF(I11="Tengo un emprendimiento o quiero iniciar uno",CHOOSE(MOD(COUNTIF($I$2:I11,I11)-1,5)+1,"Falta de financiación","Falta de conocimientos administrativos","Falta de conocimientos financieros","Falta de tiempo","Falta de herramientas"),"") | Y11: =IF(I11="Tengo un emprendimiento o quiero iniciar uno",X11,"") | Z11: =IF(I11="Tengo un emprendimiento o quiero iniciar uno",CHOOSE(INT(MOD((COUNTIF($I$2:I11,I11)-1)*7,39)/13)+1,"Sí","No","No conozco programas de ese tipo"),"") | AA11: =CHOOSE(INT(MOD((ROW()-2)*191,479)/120)+1,"No puedo hacerlo","Puedo hacerlo con ayuda","Puedo hacerlo con dificultad","Puedo hacerlo sin ayuda") -> Puedo hacerlo con dificultad | AB11: =CHOOSE(INT(MOD((ROW()-2)*191,479)/120)+1,"No puedo hacerlo","Puedo hacerlo con ayuda","Puedo hacerlo con dificultad","Puedo hacerlo sin ayuda") -> Puedo hacerlo con dificultad | AC11: =CHOOSE(INT(MOD((ROW()-2)*157+83,479)/120)+1,"No puedo hacerlo","Puedo hacerlo con ayuda","Puedo hacerlo con dificultad","Puedo hacerlo sin ayuda") -> No puedo hacerlo | AD11: =CHOOSE(INT(MOD((ROW()-2)*89+131,479)/120)+1,"No puedo hacerlo","Puedo hacerlo con ayuda","Puedo hacerlo con dificultad","Puedo hacerlo sin ayuda") -> Puedo hacerlo sin ayuda | AE11: =CHOOSE(INT(MOD((ROW()-2)*73+179,479)/120)+1,"No puedo hacerlo","Puedo hacerlo con ayuda","Puedo hacerlo con dificultad","Puedo hacerlo sin ayuda") -> Puedo hacerlo con dificultad | AF11: =CHOOSE(MOD((ROW()-2)*61+23,10)+1,"Crear una hoja de vida","Preparación para entrevista","Comunicación","Liderazgo","Emprendimiento","Herramientas digitales","Educación financiera","Crear una hoja de vida;Preparación para entrevista","Comunicación;Liderazgo","Herramientas digitales;Educación financiera") -> Comunicación | AG11: =CHOOSE(MOD(INT((ROW()-2)/3)*7,9)+1,"Costos de transporte","Distancia","Horarios","Falta de experiencia","Falta de información","Ninguna","Costos de transporte;Distancia","Horarios;Falta de información","Falta de experiencia;Falta de información") -> Falta de experiencia | AH11: =CHOOSE(INT(MOD((ROW()-2)*199+59,479)/120)+1,"Oficina de orientación laboral","Ferias de empleo","Programas de emprendimiento","No conozco ninguno") -> No conozco ninguno | AI11: =CHOOSE(INT(MOD((ROW()-2)*127+71,479)/120)+1,"Presencial","Virtual","Presencial y virtual","Me es indiferente") -> Presencial y virtual | AJ11: =CHOOSE(INT(MOD((ROW()-2)*163+97,479)/120)+1,"Diurno","Nocturno","Mañana entre semana","Fines de semana") -> Nocturno | AK11: =CHOOSE(INT(MOD((ROW()-2)*181+109,479)/120)+1,"WhatsApp","Correo electrónico","Redes sociales","Celular") -> Redes sociales
A12: ="SG"&TEXT(ROW()-1,"000") -> SG011 | B12: Urbana Consolidada | C12: SI, ACEPTO PARTICIPAR | D12: =IF(MOD((ROW()-2)*137,479)<230,"Masculino",IF(MOD((ROW()-2)*137,479)<460,"Femenino",IF(MOD((ROW()-2)*137,479)<470,"Otro","No quiero responder"))) -> Femenino | E12: =CHOOSE(MOD(ROW()-2,5)+1,"De 18 a 20 años","De 20 a 22 años","De 22 a 24 años","De 24 a 26 años","De 26 a 28 años") -> De 18 a 20 años | F12: =CHOOSE(MOD(ROW()-2,5)+1,18,20,22,24,26)+MOD(INT((ROW()-2)/5),IF(MOD(ROW()-2,5)=4,3,2)) -> 18 | G12: URBANA | H12: =_xlfn.LET(_xlpm.grupo,MOD(ROW()-2,5),_xlpm.turno,INT((ROW()-2)/5),_xlpm.orden,MOD(_xlpm.turno*37,IF(_xlpm.grupo=4,95,96)),CHOOSE(_xlpm.grupo+1,IF(_xlpm.orden<60,"Bachiller",IF(_xlpm.orden<84,"Técnico","Tecnólogo")),IF(_xlpm.orden<36,"Bachiller",IF(_xlpm.orden<66,"Técnico","Tecnólogo")),IF(_xlpm.orden<24,"Bachiller",IF(_xlpm.orden<48,"Técnico",IF(_xlpm.orden<72,"Tecnólogo","Profesional"))),IF(_xlpm.orden<12,"Bachiller",IF(_xlpm.orden<30,"Técnico",IF(_xlpm.orden<54,"Tecnólogo",IF(_xlpm.orden<90,"Profesional","Posgrado")))),IF(_xlpm.orden<10,"Bachiller",IF(_xlpm.orden<25,"Técnico",IF(_xlpm.orden<45,"Tecnólogo",IF(_xlpm.orden<85,"Profesional","Posgrado")))))) -> Técnico | I12: =_xlfn.LET(_xlpm.orden,MOD((ROW()-2)*173,479),IF(_xlpm.orden<150,"Trabajo actualmente como empleado",IF(_xlpm.orden<230,"Trabajo de manera independiente",IF(_xlpm.orden<320,"Actualmente no trabajo y estoy buscando empleo",IF(_xlpm.orden<380,"Busco mi primer empleo",IF(_xlpm.orden<440,"Estudio y quiero comenzar a trabajar","Tengo un emprendimiento o quiero iniciar uno")))))) -> Actualmente no trabajo y estoy buscando empleo | J12: =IF(I12="Trabajo actualmente como empleado",IF(MOD((COUNTIF($I$2:I12,"Trabajo actualmente como empleado")-1)*37,150)<100,"Empleado con contrato","Empleado sin contrato formal"),IF(I12="Trabajo de manera independiente","Trabajo independiente","")) | K12: =IF(OR(I12="Trabajo actualmente como empleado",I12="Trabajo de manera independiente"),CHOOSE(MOD(COUNTIF($I$2:I12,I12)-1,4)+1,"Menos de 3 meses","De 3 a 6 meses","De 7 a 12 meses","Más de un año"),"") | L12: =IF(OR(I12="Trabajo actualmente como empleado",I12="Trabajo de manera independiente"),CHOOSE(MOD(COUNTIF($I$2:I12,I12)-1,3)+1,"Sí, completamente","Parcialmente","No"),"") | M12: =IF(OR(I12="Trabajo actualmente como empleado",I12="Trabajo de manera independiente"),CHOOSE(MOD(INT((COUNTIF($I$2:I12,I12)-1)/3),4)+1,"1- Muy satisfecho/a","2- Satisfecho/a","3- Insatisfecho/a","4- Muy insatisfecho/a"),"") | N12: =IF(OR(I12="Trabajo actualmente como empleado",I12="Trabajo de manera independiente"),_xlfn.LET(_xlpm.opcion,MOD(INT((COUNTIF($I$2:I12,I12)-1)/5),6)+1,CHOOSE(IF(AND(_xlpm.opcion=6,L12="Sí, completamente"),5,_xlpm.opcion),"Salario","Estabilidad laboral","Horario","Acceso a prestaciones","Oportunidades de crecimiento","Trabajar en un área relacionada con mi formación")),"") | O12: =IF(OR(I12="Trabajo actualmente como empleado",I12="Trabajo de manera independiente"),_xlfn.LET(_xlpm.turno,MOD(COUNTIF($I$2:I12,I12)-1,5),_xlpm.nivel,VALUE(LEFT(M12,1)),IF(_xlpm.turno=4,"No estoy seguro/a",IF(_xlpm.turno<IF(_xlpm.nivel<=2,1,3),"Sí","No"))),"") | P12: =_xlfn.LET(_xlpm.perfil,I12,_xlpm.turno,COUNTIF($I$2:I12,_xlpm.perfil)-1,_xlpm.busca,OR(_xlpm.perfil="Actualmente no trabajo y estoy buscando empleo",_xlpm.perfil="Busco mi primer empleo"),_xlpm.trabaja,OR(_xlpm.perfil="Trabajo actualmente como empleado",_xlpm.perfil="Trabajo de manera independiente"),IF(_xlpm.busca,CHOOSE(MOD(_xlpm.turno*3,4)+1,"Menos de 1 mes","Entre 1 y 3 meses","Entre 4 y 6 meses","Más de 6 meses"),IF(OR(_xlpm.trabaja,_xlpm.perfil="Estudio y quiero comenzar a trabajar"),IF(AND(_xlpm.trabaja,O12="No"),"Todavía no he iniciado una búsqueda activa",CHOOSE(MOD(_xlpm.turno*3,5)+1,"Menos de 1 mes","Entre 1 y 3 meses","Entre 4 y 6 meses","Más de 6 meses","Todavía no he iniciado una búsqueda activa")),""))) -> Más de 6 meses | Q12: =IF(I12="Tengo un emprendimiento o quiero iniciar uno","",CHOOSE(MOD(INT((COUNTIF($I$2:I12,I12)-1)/7),3)+1,"Sí","No","Tengo una pero necesito actualizarla")) -> Sí | R12: =IF(I12="Tengo un emprendimiento o quiero iniciar uno","",IF(I12="Busco mi primer empleo","No",IF(MOD(COUNTIF($I$2:I12,I12)-1,2)=0,"Sí","No"))) -> No | S12: =IF(I12="Tengo un emprendimiento o quiero iniciar uno","",CHOOSE(MOD(INT((COUNTIF($I$2:I12,I12)-1)/3),10)+1,"Portales de empleo","Redes sociales","Familiares o conocidos","Empresas directamente","Ferias de empleo","Instituciones públicas","Institución educativa","No sé dónde buscar","Portales de empleo;Redes sociales","Familiares o conocidos;Empresas directamente")) -> Portales de empleo | T12: =IF(I12="Tengo un emprendimiento o quiero iniciar uno","",_xlfn.LET(_xlpm.opcion,MOD(INT((COUNTIF($I$2:I12,I12)-1)/4),6)+1,CHOOSE(IF(AND(_xlpm.opcion=3,Q12="Sí"),1,_xlpm.opcion),"Falta de experiencia","Falta de formación","Dificultades con la hoja de vida","Horarios disponibles","Transporte","Internet"))) -> Falta de experiencia | U12: =IF(I12="Tengo un emprendimiento o quiero iniciar uno","",IF(MOD(INT((COUNTIF($I$2:I12,I12)-1)/3),2)=0,"Sí","No")) -> Sí | V12: =IF(I12="Tengo un emprendimiento o quiero iniciar uno",CHOOSE(MOD(COUNTIF($I$2:I12,I12)-1,3)+1,"Tengo un emprendimiento","Estoy iniciando un emprendimiento","Me interesa emprender"),"") | W12: =IF(V12="Tengo un emprendimiento","Funcionamiento estable",IF(V12="Estoy iniciando un emprendimiento","Inicio","")) | X12: =IF(I12="Tengo un emprendimiento o quiero iniciar uno",CHOOSE(MOD(COUNTIF($I$2:I12,I12)-1,5)+1,"Falta de financiación","Falta de conocimientos administrativos","Falta de conocimientos financieros","Falta de tiempo","Falta de herramientas"),"") | Y12: =IF(I12="Tengo un emprendimiento o quiero iniciar uno",X12,"") | Z12: =IF(I12="Tengo un emprendimiento o quiero iniciar uno",CHOOSE(INT(MOD((COUNTIF($I$2:I12,I12)-1)*7,39)/13)+1,"Sí","No","No conozco programas de ese tipo"),"") | AA12: =CHOOSE(INT(MOD((ROW()-2)*191,479)/120)+1,"No puedo hacerlo","Puedo hacerlo con ayuda","Puedo hacerlo con dificultad","Puedo hacerlo sin ayuda") -> Puedo hacerlo sin ayuda | AB12: =CHOOSE(INT(MOD((ROW()-2)*191,479)/120)+1,"No puedo hacerlo","Puedo hacerlo con ayuda","Puedo hacerlo con dificultad","Puedo hacerlo sin ayuda") -> Puedo hacerlo sin ayuda | AC12: =CHOOSE(INT(MOD((ROW()-2)*157+83,479)/120)+1,"No puedo hacerlo","Puedo hacerlo con ayuda","Puedo hacerlo con dificultad","Puedo hacerlo sin ayuda") -> Puedo hacerlo con ayuda | AD12: =CHOOSE(INT(MOD((ROW()-2)*89+131,479)/120)+1,"No puedo hacerlo","Puedo hacerlo con ayuda","Puedo hacerlo con dificultad","Puedo hacerlo sin ayuda") -> No puedo hacerlo | AE12: =CHOOSE(INT(MOD((ROW()-2)*73+179,479)/120)+1,"No puedo hacerlo","Puedo hacerlo con ayuda","Puedo hacerlo con dificultad","Puedo hacerlo sin ayuda") -> Puedo hacerlo sin ayuda | AF12: =CHOOSE(MOD((ROW()-2)*61+23,10)+1,"Crear una hoja de vida","Preparación para entrevista","Comunicación","Liderazgo","Emprendimiento","Herramientas digitales","Educación financiera","Crear una hoja de vida;Preparación para entrevista","Comunicación;Liderazgo","Herramientas digitales;Educación financiera") -> Liderazgo | AG12: =CHOOSE(MOD(INT((ROW()-2)/3)*7,9)+1,"Costos de transporte","Distancia","Horarios","Falta de experiencia","Falta de información","Ninguna","Costos de transporte;Distancia","Horarios;Falta de información","Falta de experiencia;Falta de información") -> Falta de experiencia | AH12: =CHOOSE(INT(MOD((ROW()-2)*199+59,479)/120)+1,"Oficina de orientación laboral","Ferias de empleo","Programas de emprendimiento","No conozco ninguno") -> Ferias de empleo | AI12: =CHOOSE(INT(MOD((ROW()-2)*127+71,479)/120)+1,"Presencial","Virtual","Presencial y virtual","Me es indiferente") -> Me es indiferente | AJ12: =CHOOSE(INT(MOD((ROW()-2)*163+97,479)/120)+1,"Diurno","Nocturno","Mañana entre semana","Fines de semana") -> Mañana entre semana | AK12: =CHOOSE(INT(MOD((ROW()-2)*181+109,479)/120)+1,"WhatsApp","Correo electrónico","Redes sociales","Celular") -> WhatsApp
A13: ="SG"&TEXT(ROW()-1,"000") -> SG012 | B13: Urbana Consolidada | C13: SI, ACEPTO PARTICIPAR | D13: =IF(MOD((ROW()-2)*137,479)<230,"Masculino",IF(MOD((ROW()-2)*137,479)<460,"Femenino",IF(MOD((ROW()-2)*137,479)<470,"Otro","No quiero responder"))) -> Masculino | E13: =CHOOSE(MOD(ROW()-2,5)+1,"De 18 a 20 años","De 20 a 22 años","De 22 a 24 años","De 24 a 26 años","De 26 a 28 años") -> De 20 a 22 años | F13: =CHOOSE(MOD(ROW()-2,5)+1,18,20,22,24,26)+MOD(INT((ROW()-2)/5),IF(MOD(ROW()-2,5)=4,3,2)) -> 20 | G13: URBANA | H13: =_xlfn.LET(_xlpm.grupo,MOD(ROW()-2,5),_xlpm.turno,INT((ROW()-2)/5),_xlpm.orden,MOD(_xlpm.turno*37,IF(_xlpm.grupo=4,95,96)),CHOOSE(_xlpm.grupo+1,IF(_xlpm.orden<60,"Bachiller",IF(_xlpm.orden<84,"Técnico","Tecnólogo")),IF(_xlpm.orden<36,"Bachiller",IF(_xlpm.orden<66,"Técnico","Tecnólogo")),IF(_xlpm.orden<24,"Bachiller",IF(_xlpm.orden<48,"Técnico",IF(_xlpm.orden<72,"Tecnólogo","Profesional"))),IF(_xlpm.orden<12,"Bachiller",IF(_xlpm.orden<30,"Técnico",IF(_xlpm.orden<54,"Tecnólogo",IF(_xlpm.orden<90,"Profesional","Posgrado")))),IF(_xlpm.orden<10,"Bachiller",IF(_xlpm.orden<25,"Técnico",IF(_xlpm.orden<45,"Tecnólogo",IF(_xlpm.orden<85,"Profesional","Posgrado")))))) -> Tecnólogo | I13: =_xlfn.LET(_xlpm.orden,MOD((ROW()-2)*173,479),IF(_xlpm.orden<150,"Trabajo actualmente como empleado",IF(_xlpm.orden<230,"Trabajo de manera independiente",IF(_xlpm.orden<320,"Actualmente no trabajo y estoy buscando empleo",IF(_xlpm.orden<380,"Busco mi primer empleo",IF(_xlpm.orden<440,"Estudio y quiero comenzar a trabajar","Tengo un emprendimiento o quiero iniciar uno")))))) -> Tengo un emprendimiento o quiero iniciar uno | J13: =IF(I13="Trabajo actualmente como empleado",IF(MOD((COUNTIF($I$2:I13,"Trabajo actualmente como empleado")-1)*37,150)<100,"Empleado con contrato","Empleado sin contrato formal"),IF(I13="Trabajo de manera independiente","Trabajo independiente","")) | K13: =IF(OR(I13="Trabajo actualmente como empleado",I13="Trabajo de manera independiente"),CHOOSE(MOD(COUNTIF($I$2:I13,I13)-1,4)+1,"Menos de 3 meses","De 3 a 6 meses","De 7 a 12 meses","Más de un año"),"") | L13: =IF(OR(I13="Trabajo actualmente como empleado",I13="Trabajo de manera independiente"),CHOOSE(MOD(COUNTIF($I$2:I13,I13)-1,3)+1,"Sí, completamente","Parcialmente","No"),"") | M13: =IF(OR(I13="Trabajo actualmente como empleado",I13="Trabajo de manera independiente"),CHOOSE(MOD(INT((COUNTIF($I$2:I13,I13)-1)/3),4)+1,"1- Muy satisfecho/a","2- Satisfecho/a","3- Insatisfecho/a","4- Muy insatisfecho/a"),"") | N13: =IF(OR(I13="Trabajo actualmente como empleado",I13="Trabajo de manera independiente"),_xlfn.LET(_xlpm.opcion,MOD(INT((COUNTIF($I$2:I13,I13)-1)/5),6)+1,CHOOSE(IF(AND(_xlpm.opcion=6,L13="Sí, completamente"),5,_xlpm.opcion),"Salario","Estabilidad laboral","Horario","Acceso a prestaciones","Oportunidades de crecimiento","Trabajar en un área relacionada con mi formación")),"") | O13: =IF(OR(I13="Trabajo actualmente como empleado",I13="Trabajo de manera independiente"),_xlfn.LET(_xlpm.turno,MOD(COUNTIF($I$2:I13,I13)-1,5),_xlpm.nivel,VALUE(LEFT(M13,1)),IF(_xlpm.turno=4,"No estoy seguro/a",IF(_xlpm.turno<IF(_xlpm.nivel<=2,1,3),"Sí","No"))),"") | P13: =_xlfn.LET(_xlpm.perfil,I13,_xlpm.turno,COUNTIF($I$2:I13,_xlpm.perfil)-1,_xlpm.busca,OR(_xlpm.perfil="Actualmente no trabajo y estoy buscando empleo",_xlpm.perfil="Busco mi primer empleo"),_xlpm.trabaja,OR(_xlpm.perfil="Trabajo actualmente como empleado",_xlpm.perfil="Trabajo de manera independiente"),IF(_xlpm.busca,CHOOSE(MOD(_xlpm.turno*3,4)+1,"Menos de 1 mes","Entre 1 y 3 meses","Entre 4 y 6 meses","Más de 6 meses"),IF(OR(_xlpm.trabaja,_xlpm.perfil="Estudio y quiero comenzar a trabajar"),IF(AND(_xlpm.trabaja,O13="No"),"Todavía no he iniciado una búsqueda activa",CHOOSE(MOD(_xlpm.turno*3,5)+1,"Menos de 1 mes","Entre 1 y 3 meses","Entre 4 y 6 meses","Más de 6 meses","Todavía no he iniciado una búsqueda activa")),""))) | Q13: =IF(I13="Tengo un emprendimiento o quiero iniciar uno","",CHOOSE(MOD(INT((COUNTIF($I$2:I13,I13)-1)/7),3)+1,"Sí","No","Tengo una pero necesito actualizarla")) | R13: =IF(I13="Tengo un emprendimiento o quiero iniciar uno","",IF(I13="Busco mi primer empleo","No",IF(MOD(COUNTIF($I$2:I13,I13)-1,2)=0,"Sí","No"))) | S13: =IF(I13="Tengo un emprendimiento o quiero iniciar uno","",CHOOSE(MOD(INT((COUNTIF($I$2:I13,I13)-1)/3),10)+1,"Portales de empleo","Redes sociales","Familiares o conocidos","Empresas directamente","Ferias de empleo","Instituciones públicas","Institución educativa","No sé dónde buscar","Portales de empleo;Redes sociales","Familiares o conocidos;Empresas directamente")) | T13: =IF(I13="Tengo un emprendimiento o quiero iniciar uno","",_xlfn.LET(_xlpm.opcion,MOD(INT((COUNTIF($I$2:I13,I13)-1)/4),6)+1,CHOOSE(IF(AND(_xlpm.opcion=3,Q13="Sí"),1,_xlpm.opcion),"Falta de experiencia","Falta de formación","Dificultades con la hoja de vida","Horarios disponibles","Transporte","Internet"))) | U13: =IF(I13="Tengo un emprendimiento o quiero iniciar uno","",IF(MOD(INT((COUNTIF($I$2:I13,I13)-1)/3),2)=0,"Sí","No")) | V13: =IF(I13="Tengo un emprendimiento o quiero iniciar uno",CHOOSE(MOD(COUNTIF($I$2:I13,I13)-1,3)+1,"Tengo un emprendimiento","Estoy iniciando un emprendimiento","Me interesa emprender"),"") -> Tengo un emprendimiento | W13: =IF(V13="Tengo un emprendimiento","Funcionamiento estable",IF(V13="Estoy iniciando un emprendimiento","Inicio","")) -> Funcionamiento estable | X13: =IF(I13="Tengo un emprendimiento o quiero iniciar uno",CHOOSE(MOD(COUNTIF($I$2:I13,I13)-1,5)+1,"Falta de financiación","Falta de conocimientos administrativos","Falta de conocimientos financieros","Falta de tiempo","Falta de herramientas"),"") -> Falta de financiación | Y13: =IF(I13="Tengo un emprendimiento o quiero iniciar uno",X13,"") -> Falta de financiación | Z13: =IF(I13="Tengo un emprendimiento o quiero iniciar uno",CHOOSE(INT(MOD((COUNTIF($I$2:I13,I13)-1)*7,39)/13)+1,"Sí","No","No conozco programas de ese tipo"),"") -> Sí | AA13: =CHOOSE(INT(MOD((ROW()-2)*191,479)/120)+1,"No puedo hacerlo","Puedo hacerlo con ayuda","Puedo hacerlo con dificultad","Puedo hacerlo sin ayuda") -> Puedo hacerlo con ayuda | AB13: =CHOOSE(INT(MOD((ROW()-2)*191,479)/120)+1,"No puedo hacerlo","Puedo hacerlo con ayuda","Puedo hacerlo con dificultad","Puedo hacerlo sin ayuda") -> Puedo hacerlo con ayuda | AC13: =CHOOSE(INT(MOD((ROW()-2)*157+83,479)/120)+1,"No puedo hacerlo","Puedo hacerlo con ayuda","Puedo hacerlo con dificultad","Puedo hacerlo sin ayuda") -> Puedo hacerlo sin ayuda | AD13: =CHOOSE(INT(MOD((ROW()-2)*89+131,479)/120)+1,"No puedo hacerlo","Puedo hacerlo con ayuda","Puedo hacerlo con dificultad","Puedo hacerlo sin ayuda") -> Puedo hacerlo con ayuda | AE13: =CHOOSE(INT(MOD((ROW()-2)*73+179,479)/120)+1,"No puedo hacerlo","Puedo hacerlo con ayuda","Puedo hacerlo con dificultad","Puedo hacerlo sin ayuda") -> No puedo hacerlo | AF13: =CHOOSE(MOD((ROW()-2)*61+23,10)+1,"Crear una hoja de vida","Preparación para entrevista","Comunicación","Liderazgo","Emprendimiento","Herramientas digitales","Educación financiera","Crear una hoja de vida;Preparación para entrevista","Comunicación;Liderazgo","Herramientas digitales;Educación financiera") -> Emprendimiento | AG13: =CHOOSE(MOD(INT((ROW()-2)/3)*7,9)+1,"Costos de transporte","Distancia","Horarios","Falta de experiencia","Falta de información","Ninguna","Costos de transporte;Distancia","Horarios;Falta de información","Falta de experiencia;Falta de información") -> Falta de experiencia | AH13: =CHOOSE(INT(MOD((ROW()-2)*199+59,479)/120)+1,"Oficina de orientación laboral","Ferias de empleo","Programas de emprendimiento","No conozco ninguno") -> Programas de emprendimiento | AI13: =CHOOSE(INT(MOD((ROW()-2)*127+71,479)/120)+1,"Presencial","Virtual","Presencial y virtual","Me es indiferente") -> Presencial | AJ13: =CHOOSE(INT(MOD((ROW()-2)*163+97,479)/120)+1,"Diurno","Nocturno","Mañana entre semana","Fines de semana") -> Fines de semana | AK13: =CHOOSE(INT(MOD((ROW()-2)*181+109,479)/120)+1,"WhatsApp","Correo electrónico","Redes sociales","Celular") -> Correo electrónico
A14: ="SG"&TEXT(ROW()-1,"000") -> SG013 | B14: Urbana Consolidada | C14: SI, ACEPTO PARTICIPAR | D14: =IF(MOD((ROW()-2)*137,479)<230,"Masculino",IF(MOD((ROW()-2)*137,479)<460,"Femenino",IF(MOD((ROW()-2)*137,479)<470,"Otro","No quiero responder"))) -> Masculino | E14: =CHOOSE(MOD(ROW()-2,5)+1,"De 18 a 20 años","De 20 a 22 años","De 22 a 24 años","De 24 a 26 años","De 26 a 28 años") -> De 22 a 24 años | F14: =CHOOSE(MOD(ROW()-2,5)+1,18,20,22,24,26)+MOD(INT((ROW()-2)/5),IF(MOD(ROW()-2,5)=4,3,2)) -> 22 | G14: URBANA | H14: =_xlfn.LET(_xlpm.grupo,MOD(ROW()-2,5),_xlpm.turno,INT((ROW()-2)/5),_xlpm.orden,MOD(_xlpm.turno*37,IF(_xlpm.grupo=4,95,96)),CHOOSE(_xlpm.grupo+1,IF(_xlpm.orden<60,"Bachiller",IF(_xlpm.orden<84,"Técnico","Tecnólogo")),IF(_xlpm.orden<36,"Bachiller",IF(_xlpm.orden<66,"Técnico","Tecnólogo")),IF(_xlpm.orden<24,"Bachiller",IF(_xlpm.orden<48,"Técnico",IF(_xlpm.orden<72,"Tecnólogo","Profesional"))),IF(_xlpm.orden<12,"Bachiller",IF(_xlpm.orden<30,"Técnico",IF(_xlpm.orden<54,"Tecnólogo",IF(_xlpm.orden<90,"Profesional","Posgrado")))),IF(_xlpm.orden<10,"Bachiller",IF(_xlpm.orden<25,"Técnico",IF(_xlpm.orden<45,"Tecnólogo",IF(_xlpm.orden<85,"Profesional","Posgrado")))))) -> Profesional | I14: =_xlfn.LET(_xlpm.orden,MOD((ROW()-2)*173,479),IF(_xlpm.orden<150,"Trabajo actualmente como empleado",IF(_xlpm.orden<230,"Trabajo de manera independiente",IF(_xlpm.orden<320,"Actualmente no trabajo y estoy buscando empleo",IF(_xlpm.orden<380,"Busco mi primer empleo",IF(_xlpm.orden<440,"Estudio y quiero comenzar a trabajar","Tengo un emprendimiento o quiero iniciar uno")))))) -> Trabajo de manera independiente | J14: =IF(I14="Trabajo actualmente como empleado",IF(MOD((COUNTIF($I$2:I14,"Trabajo actualmente como empleado")-1)*37,150)<100,"Empleado con contrato","Empleado sin contrato formal"),IF(I14="Trabajo de manera independiente","Trabajo independiente","")) -> Trabajo independiente | K14: =IF(OR(I14="Trabajo actualmente como empleado",I14="Trabajo de manera independiente"),CHOOSE(MOD(COUNTIF($I$2:I14,I14)-1,4)+1,"Menos de 3 meses","De 3 a 6 meses","De 7 a 12 meses","Más de un año"),"") -> De 7 a 12 meses | L14: =IF(OR(I14="Trabajo actualmente como empleado",I14="Trabajo de manera independiente"),CHOOSE(MOD(COUNTIF($I$2:I14,I14)-1,3)+1,"Sí, completamente","Parcialmente","No"),"") -> No | M14: =IF(OR(I14="Trabajo actualmente como empleado",I14="Trabajo de manera independiente"),CHOOSE(MOD(INT((COUNTIF($I$2:I14,I14)-1)/3),4)+1,"1- Muy satisfecho/a","2- Satisfecho/a","3- Insatisfecho/a","4- Muy insatisfecho/a"),"") -> 1- Muy satisfecho/a | N14: =IF(OR(I14="Trabajo actualmente como empleado",I14="Trabajo de manera independiente"),_xlfn.LET(_xlpm.opcion,MOD(INT((COUNTIF($I$2:I14,I14)-1)/5),6)+1,CHOOSE(IF(AND(_xlpm.opcion=6,L14="Sí, completamente"),5,_xlpm.opcion),"Salario","Estabilidad laboral","Horario","Acceso a prestaciones","Oportunidades de crecimiento","Trabajar en un área relacionada con mi formación")),"") -> Salario | O14: =IF(OR(I14="Trabajo actualmente como empleado",I14="Trabajo de manera independiente"),_xlfn.LET(_xlpm.turno,MOD(COUNTIF($I$2:I14,I14)-1,5),_xlpm.nivel,VALUE(LEFT(M14,1)),IF(_xlpm.turno=4,"No estoy seguro/a",IF(_xlpm.turno<IF(_xlpm.nivel<=2,1,3),"Sí","No"))),"") -> No | P14: =_xlfn.LET(_xlpm.perfil,I14,_xlpm.turno,COUNTIF($I$2:I14,_xlpm.perfil)-1,_xlpm.busca,OR(_xlpm.perfil="Actualmente no trabajo y estoy buscando empleo",_xlpm.perfil="Busco mi primer empleo"),_xlpm.trabaja,OR(_xlpm.perfil="Trabajo actualmente como empleado",_xlpm.perfil="Trabajo de manera independiente"),IF(_xlpm.busca,CHOOSE(MOD(_xlpm.turno*3,4)+1,"Menos de 1 mes","Entre 1 y 3 meses","Entre 4 y 6 meses","Más de 6 meses"),IF(OR(_xlpm.trabaja,_xlpm.perfil="Estudio y quiero comenzar a trabajar"),IF(AND(_xlpm.trabaja,O14="No"),"Todavía no he iniciado una búsqueda activa",CHOOSE(MOD(_xlpm.turno*3,5)+1,"Menos de 1 mes","Entre 1 y 3 meses","Entre 4 y 6 meses","Más de 6 meses","Todavía no he iniciado una búsqueda activa")),""))) -> Todavía no he iniciado una búsqueda activa | Q14: =IF(I14="Tengo un emprendimiento o quiero iniciar uno","",CHOOSE(MOD(INT((COUNTIF($I$2:I14,I14)-1)/7),3)+1,"Sí","No","Tengo una pero necesito actualizarla")) -> Sí | R14: =IF(I14="Tengo un emprendimiento o quiero iniciar uno","",IF(I14="Busco mi primer empleo","No",IF(MOD(COUNTIF($I$2:I14,I14)-1,2)=0,"Sí","No"))) -> Sí | S14: =IF(I14="Tengo un emprendimiento o quiero iniciar uno","",CHOOSE(MOD(INT((COUNTIF($I$2:I14,I14)-1)/3),10)+1,"Portales de empleo","Redes sociales","Familiares o conocidos","Empresas directamente","Ferias de empleo","Instituciones públicas","Institución educativa","No sé dónde buscar","Portales de empleo;Redes sociales","Familiares o conocidos;Empresas directamente")) -> Portales de empleo | T14: =IF(I14="Tengo un emprendimiento o quiero iniciar uno","",_xlfn.LET(_xlpm.opcion,MOD(INT((COUNTIF($I$2:I14,I14)-1)/4),6)+1,CHOOSE(IF(AND(_xlpm.opcion=3,Q14="Sí"),1,_xlpm.opcion),"Falta de experiencia","Falta de formación","Dificultades con la hoja de vida","Horarios disponibles","Transporte","Internet"))) -> Falta de experiencia | U14: =IF(I14="Tengo un emprendimiento o quiero iniciar uno","",IF(MOD(INT((COUNTIF($I$2:I14,I14)-1)/3),2)=0,"Sí","No")) -> Sí | V14: =IF(I14="Tengo un emprendimiento o quiero iniciar uno",CHOOSE(MOD(COUNTIF($I$2:I14,I14)-1,3)+1,"Tengo un emprendimiento","Estoy iniciando un emprendimiento","Me interesa emprender"),"") | W14: =IF(V14="Tengo un emprendimiento","Funcionamiento estable",IF(V14="Estoy iniciando un emprendimiento","Inicio","")) | X14: =IF(I14="Tengo un emprendimiento o quiero iniciar uno",CHOOSE(MOD(COUNTIF($I$2:I14,I14)-1,5)+1,"Falta de financiación","Falta de conocimientos administrativos","Falta de conocimientos financieros","Falta de tiempo","Falta de herramientas"),"") | Y14: =IF(I14="Tengo un emprendimiento o quiero iniciar uno",X14,"") | Z14: =IF(I14="Tengo un emprendimiento o quiero iniciar uno",CHOOSE(INT(MOD((COUNTIF($I$2:I14,I14)-1)*7,39)/13)+1,"Sí","No","No conozco programas de ese tipo"),"") | AA14: =CHOOSE(INT(MOD((ROW()-2)*191,479)/120)+1,"No puedo hacerlo","Puedo hacerlo con ayuda","Puedo hacerlo con dificultad","Puedo hacerlo sin ayuda") -> Puedo hacerlo sin ayuda | AB14: =CHOOSE(INT(MOD((ROW()-2)*191,479)/120)+1,"No puedo hacerlo","Puedo hacerlo con ayuda","Puedo hacerlo con dificultad","Puedo hacerlo sin ayuda") -> Puedo hacerlo sin ayuda | AC14: =CHOOSE(INT(MOD((ROW()-2)*157+83,479)/120)+1,"No puedo hacerlo","Puedo hacerlo con ayuda","Puedo hacerlo con dificultad","Puedo hacerlo sin ayuda") -> No puedo hacerlo | AD14: =CHOOSE(INT(MOD((ROW()-2)*89+131,479)/120)+1,"No puedo hacerlo","Puedo hacerlo con ayuda","Puedo hacerlo con dificultad","Puedo hacerlo sin ayuda") -> Puedo hacerlo con dificultad | AE14: =CHOOSE(INT(MOD((ROW()-2)*73+179,479)/120)+1,"No puedo hacerlo","Puedo hacerlo con ayuda","Puedo hacerlo con dificultad","Puedo hacerlo sin ayuda") -> No puedo hacerlo | AF14: =CHOOSE(MOD((ROW()-2)*61+23,10)+1,"Crear una hoja de vida","Preparación para entrevista","Comunicación","Liderazgo","Emprendimiento","Herramientas digitales","Educación financiera","Crear una hoja de vida;Preparación para entrevista","Comunicación;Liderazgo","Herramientas digitales;Educación financiera") -> Herramientas digitales | AG14: =CHOOSE(MOD(INT((ROW()-2)/3)*7,9)+1,"Costos de transporte","Distancia","Horarios","Falta de experiencia","Falta de información","Ninguna","Costos de transporte;Distancia","Horarios;Falta de información","Falta de experiencia;Falta de información") -> Distancia | AH14: =CHOOSE(INT(MOD((ROW()-2)*199+59,479)/120)+1,"Oficina de orientación laboral","Ferias de empleo","Programas de emprendimiento","No conozco ninguno") -> Oficina de orientación laboral | AI14: =CHOOSE(INT(MOD((ROW()-2)*127+71,479)/120)+1,"Presencial","Virtual","Presencial y virtual","Me es indiferente") -> Virtual | AJ14: =CHOOSE(INT(MOD((ROW()-2)*163+97,479)/120)+1,"Diurno","Nocturno","Mañana entre semana","Fines de semana") -> Nocturno | AK14: =CHOOSE(INT(MOD((ROW()-2)*181+109,479)/120)+1,"WhatsApp","Correo electrónico","Redes sociales","Celular") -> Celular
... A370: ="SG"&TEXT(ROW()-1,"000") -> SG369 | B370: URBANA PERIFÉRICA | C370: SI, ACEPTO PARTICIPAR | D370: =IF(MOD((ROW()-2)*137,479)<230,"Masculino",IF(MOD((ROW()-2)*137,479)<460,"Femenino",IF(MOD((ROW()-2)*137,479)<470,"Otro","No quiero responder"))) -> Masculino | E370: =CHOOSE(MOD(ROW()-2,5)+1,"De 18 a 20 años","De 20 a 22 años","De 22 a 24 años","De 24 a 26 años","De 26 a 28 años") -> De 24 a 26 años | F370: =CHOOSE(MOD(ROW()-2,5)+1,18,20,22,24,26)+MOD(INT((ROW()-2)/5),IF(MOD(ROW()-2,5)=4,3,2)) -> 25 | G370: URBANO PERIFERICO | H370: =_xlfn.LET(_xlpm.grupo,MOD(ROW()-2,5),_xlpm.turno,INT((ROW()-2)/5),_xlpm.orden,MOD(_xlpm.turno*37,IF(_xlpm.grupo=4,95,96)),CHOOSE(_xlpm.grupo+1,IF(_xlpm.orden<60,"Bachiller",IF(_xlpm.orden<84,"Técnico","Tecnólogo")),IF(_xlpm.orden<36,"Bachiller",IF(_xlpm.orden<66,"Técnico","Tecnólogo")),IF(_xlpm.orden<24,"Bachiller",IF(_xlpm.orden<48,"Técnico",IF(_xlpm.orden<72,"Tecnólogo","Profesional"))),IF(_xlpm.orden<12,"Bachiller",IF(_xlpm.orden<30,"Técnico",IF(_xlpm.orden<54,"Tecnólogo",IF(_xlpm.orden<90,"Profesional","Posgrado")))),IF(_xlpm.orden<10,"Bachiller",IF(_xlpm.orden<25,"Técnico",IF(_xlpm.orden<45,"Tecnólogo",IF(_xlpm.orden<85,"Profesional","Posgrado")))))) -> Técnico | I370: =_xlfn.LET(_xlpm.orden,MOD((ROW()-2)*173,479),IF(_xlpm.orden<150,"Trabajo actualmente como empleado",IF(_xlpm.orden<230,"Trabajo de manera independiente",IF(_xlpm.orden<320,"Actualmente no trabajo y estoy buscando empleo",IF(_xlpm.orden<380,"Busco mi primer empleo",IF(_xlpm.orden<440,"Estudio y quiero comenzar a trabajar","Tengo un emprendimiento o quiero iniciar uno")))))) -> Estudio y quiero comenzar a trabajar | J370: =IF(I370="Trabajo actualmente como empleado",IF(MOD((COUNTIF($I$2:I370,"Trabajo actualmente como empleado")-1)*37,150)<100,"Empleado con contrato","Empleado sin contrato formal"),IF(I370="Trabajo de manera independiente","Trabajo independiente","")) | K370: =IF(OR(I370="Trabajo actualmente como empleado",I370="Trabajo de manera independiente"),CHOOSE(MOD(COUNTIF($I$2:I370,I370)-1,4)+1,"Menos de 3 meses","De 3 a 6 meses","De 7 a 12 meses","Más de un año"),"") | L370: =IF(OR(I370="Trabajo actualmente como empleado",I370="Trabajo de manera independiente"),CHOOSE(MOD(COUNTIF($I$2:I370,I370)-1,3)+1,"Sí, completamente","Parcialmente","No"),"") | M370: =IF(OR(I370="Trabajo actualmente como empleado",I370="Trabajo de manera independiente"),CHOOSE(MOD(INT((COUNTIF($I$2:I370,I370)-1)/3),4)+1,"1- Muy satisfecho/a","2- Satisfecho/a","3- Insatisfecho/a","4- Muy insatisfecho/a"),"") | N370: =IF(OR(I370="Trabajo actualmente como empleado",I370="Trabajo de manera independiente"),_xlfn.LET(_xlpm.opcion,MOD(INT((COUNTIF($I$2:I370,I370)-1)/5),6)+1,CHOOSE(IF(AND(_xlpm.opcion=6,L370="Sí, completamente"),5,_xlpm.opcion),"Salario","Estabilidad laboral","Horario","Acceso a prestaciones","Oportunidades de crecimiento","Trabajar en un área relacionada con mi formación")),"") | O370: =IF(OR(I370="Trabajo actualmente como empleado",I370="Trabajo de manera independiente"),_xlfn.LET(_xlpm.turno,MOD(COUNTIF($I$2:I370,I370)-1,5),_xlpm.nivel,VALUE(LEFT(M370,1)),IF(_xlpm.turno=4,"No estoy seguro/a",IF(_xlpm.turno<IF(_xlpm.nivel<=2,1,3),"Sí","No"))),"") | P370: =_xlfn.LET(_xlpm.perfil,I370,_xlpm.turno,COUNTIF($I$2:I370,_xlpm.perfil)-1,_xlpm.busca,OR(_xlpm.perfil="Actualmente no trabajo y estoy buscando empleo",_xlpm.perfil="Busco mi primer empleo"),_xlpm.trabaja,OR(_xlpm.perfil="Trabajo actualmente como empleado",_xlpm.perfil="Trabajo de manera independiente"),IF(_xlpm.busca,CHOOSE(MOD(_xlpm.turno*3,4)+1,"Menos de 1 mes","Entre 1 y 3 meses","Entre 4 y 6 meses","Más de 6 meses"),IF(OR(_xlpm.trabaja,_xlpm.perfil="Estudio y quiero comenzar a trabajar"),IF(AND(_xlpm.trabaja,O370="No"),"Todavía no he iniciado una búsqueda activa",CHOOSE(MOD(_xlpm.turno*3,5)+1,"Menos de 1 mes","Entre 1 y 3 meses","Entre 4 y 6 meses","Más de 6 meses","Todavía no he iniciado una búsqueda activa")),""))) -> Entre 4 y 6 meses | Q370: =IF(I370="Tengo un emprendimiento o quiero iniciar uno","",CHOOSE(MOD(INT((COUNTIF($I$2:I370,I370)-1)/7),3)+1,"Sí","No","Tengo una pero necesito actualizarla")) -> Sí | R370: =IF(I370="Tengo un emprendimiento o quiero iniciar uno","",IF(I370="Busco mi primer empleo","No",IF(MOD(COUNTIF($I$2:I370,I370)-1,2)=0,"Sí","No"))) -> Sí | S370: =IF(I370="Tengo un emprendimiento o quiero iniciar uno","",CHOOSE(MOD(INT((COUNTIF($I$2:I370,I370)-1)/3),10)+1,"Portales de empleo","Redes sociales","Familiares o conocidos","Empresas directamente","Ferias de empleo","Instituciones públicas","Institución educativa","No sé dónde buscar","Portales de empleo;Redes sociales","Familiares o conocidos;Empresas directamente")) -> Ferias de empleo | T370: =IF(I370="Tengo un emprendimiento o quiero iniciar uno","",_xlfn.LET(_xlpm.opcion,MOD(INT((COUNTIF($I$2:I370,I370)-1)/4),6)+1,CHOOSE(IF(AND(_xlpm.opcion=3,Q370="Sí"),1,_xlpm.opcion),"Falta de experiencia","Falta de formación","Dificultades con la hoja de vida","Horarios disponibles","Transporte","Internet"))) -> Internet | U370: =IF(I370="Tengo un emprendimiento o quiero iniciar uno","",IF(MOD(INT((COUNTIF($I$2:I370,I370)-1)/3),2)=0,"Sí","No")) -> Sí | V370: =IF(I370="Tengo un emprendimiento o quiero iniciar uno",CHOOSE(MOD(COUNTIF($I$2:I370,I370)-1,3)+1,"Tengo un emprendimiento","Estoy iniciando un emprendimiento","Me interesa emprender"),"") | W370: =IF(V370="Tengo un emprendimiento","Funcionamiento estable",IF(V370="Estoy iniciando un emprendimiento","Inicio","")) | X370: =IF(I370="Tengo un emprendimiento o quiero iniciar uno",CHOOSE(MOD(COUNTIF($I$2:I370,I370)-1,5)+1,"Falta de financiación","Falta de conocimientos administrativos","Falta de conocimientos financieros","Falta de tiempo","Falta de herramientas"),"") | Y370: =IF(I370="Tengo un emprendimiento o quiero iniciar uno",X370,"") | Z370: =IF(I370="Tengo un emprendimiento o quiero iniciar uno",CHOOSE(INT(MOD((COUNTIF($I$2:I370,I370)-1)*7,39)/13)+1,"Sí","No","No conozco programas de ese tipo"),"") | AA370: =CHOOSE(INT(MOD((ROW()-2)*191,479)/120)+1,"No puedo hacerlo","Puedo hacerlo con ayuda","Puedo hacerlo con dificultad","Puedo hacerlo sin ayuda") -> Puedo hacerlo con dificultad | AB370: =CHOOSE(INT(MOD((ROW()-2)*191,479)/120)+1,"No puedo hacerlo","Puedo hacerlo con ayuda","Puedo hacerlo con dificultad","Puedo hacerlo sin ayuda") -> Puedo hacerlo con dificultad | AC370: =CHOOSE(INT(MOD((ROW()-2)*157+83,479)/120)+1,"No puedo hacerlo","Puedo hacerlo con ayuda","Puedo hacerlo con dificultad","Puedo hacerlo sin ayuda") -> Puedo hacerlo sin ayuda | AD370: =CHOOSE(INT(MOD((ROW()-2)*89+131,479)/120)+1,"No puedo hacerlo","Puedo hacerlo con ayuda","Puedo hacerlo con dificultad","Puedo hacerlo sin ayuda") -> Puedo hacerlo con dificultad | AE370: =CHOOSE(INT(MOD((ROW()-2)*73+179,479)/120)+1,"No puedo hacerlo","Puedo hacerlo con ayuda","Puedo hacerlo con dificultad","Puedo hacerlo sin ayuda") -> Puedo hacerlo con ayuda | AF370: =CHOOSE(MOD((ROW()-2)*61+23,10)+1,"Crear una hoja de vida","Preparación para entrevista","Comunicación","Liderazgo","Emprendimiento","Herramientas digitales","Educación financiera","Crear una hoja de vida;Preparación para entrevista","Comunicación;Liderazgo","Herramientas digitales;Educación financiera") -> Preparación para entrevista | AG370: =CHOOSE(MOD(INT((ROW()-2)/3)*7,9)+1,"Costos de transporte","Distancia","Horarios","Falta de experiencia","Falta de información","Ninguna","Costos de transporte;Distancia","Horarios;Falta de información","Falta de experiencia;Falta de información") -> Falta de experiencia;Falta de información | AH370: =CHOOSE(INT(MOD((ROW()-2)*199+59,479)/120)+1,"Oficina de orientación laboral","Ferias de empleo","Programas de emprendimiento","No conozco ninguno") -> Oficina de orientación laboral | AI370: =CHOOSE(INT(MOD((ROW()-2)*127+71,479)/120)+1,"Presencial","Virtual","Presencial y virtual","Me es indiferente") -> Presencial y virtual | AJ370: =CHOOSE(INT(MOD((ROW()-2)*163+97,479)/120)+1,"Diurno","Nocturno","Mañana entre semana","Fines de semana") -> Nocturno | AK370: =CHOOSE(INT(MOD((ROW()-2)*181+109,479)/120)+1,"WhatsApp","Correo electrónico","Redes sociales","Celular") -> Correo electrónico
A371: ="SG"&TEXT(ROW()-1,"000") -> SG370 | B371: CENTROS POBLADOS Y RURAL | C371: SI, ACEPTO PARTICIPAR | D371: =IF(MOD((ROW()-2)*137,479)<230,"Masculino",IF(MOD((ROW()-2)*137,479)<460,"Femenino",IF(MOD((ROW()-2)*137,479)<470,"Otro","No quiero responder"))) -> Femenino | E371: =CHOOSE(MOD(ROW()-2,5)+1,"De 18 a 20 años","De 20 a 22 años","De 22 a 24 años","De 24 a 26 años","De 26 a 28 años") -> De 26 a 28 años | F371: =CHOOSE(MOD(ROW()-2,5)+1,18,20,22,24,26)+MOD(INT((ROW()-2)/5),IF(MOD(ROW()-2,5)=4,3,2)) -> 27 | G371: =IF(MOD(ROW()-371,2)=0,"Centro poblado","Rural") -> Centro poblado | H371: =_xlfn.LET(_xlpm.grupo,MOD(ROW()-2,5),_xlpm.turno,INT((ROW()-2)/5),_xlpm.orden,MOD(_xlpm.turno*37,IF(_xlpm.grupo=4,95,96)),CHOOSE(_xlpm.grupo+1,IF(_xlpm.orden<60,"Bachiller",IF(_xlpm.orden<84,"Técnico","Tecnólogo")),IF(_xlpm.orden<36,"Bachiller",IF(_xlpm.orden<66,"Técnico","Tecnólogo")),IF(_xlpm.orden<24,"Bachiller",IF(_xlpm.orden<48,"Técnico",IF(_xlpm.orden<72,"Tecnólogo","Profesional"))),IF(_xlpm.orden<12,"Bachiller",IF(_xlpm.orden<30,"Técnico",IF(_xlpm.orden<54,"Tecnólogo",IF(_xlpm.orden<90,"Profesional","Posgrado")))),IF(_xlpm.orden<10,"Bachiller",IF(_xlpm.orden<25,"Técnico",IF(_xlpm.orden<45,"Tecnólogo",IF(_xlpm.orden<85,"Profesional","Posgrado")))))) -> Tecnólogo | I371: =_xlfn.LET(_xlpm.orden,MOD((ROW()-2)*173,479),IF(_xlpm.orden<150,"Trabajo actualmente como empleado",IF(_xlpm.orden<230,"Trabajo de manera independiente",IF(_xlpm.orden<320,"Actualmente no trabajo y estoy buscando empleo",IF(_xlpm.orden<380,"Busco mi primer empleo",IF(_xlpm.orden<440,"Estudio y quiero comenzar a trabajar","Tengo un emprendimiento o quiero iniciar uno")))))) -> Trabajo actualmente como empleado | J371: =IF(I371="Trabajo actualmente como empleado",IF(MOD((COUNTIF($I$2:I371,"Trabajo actualmente como empleado")-1)*37,150)<100,"Empleado con contrato","Empleado sin contrato formal"),IF(I371="Trabajo de manera independiente","Trabajo independiente","")) -> Empleado con contrato | K371: =IF(OR(I371="Trabajo actualmente como empleado",I371="Trabajo de manera independiente"),CHOOSE(MOD(COUNTIF($I$2:I371,I371)-1,4)+1,"Menos de 3 meses","De 3 a 6 meses","De 7 a 12 meses","Más de un año"),"") -> Menos de 3 meses | L371: =IF(OR(I371="Trabajo actualmente como empleado",I371="Trabajo de manera independiente"),CHOOSE(MOD(COUNTIF($I$2:I371,I371)-1,3)+1,"Sí, completamente","Parcialmente","No"),"") -> No | M371: =IF(OR(I371="Trabajo actualmente como empleado",I371="Trabajo de manera independiente"),CHOOSE(MOD(INT((COUNTIF($I$2:I371,I371)-1)/3),4)+1,"1- Muy satisfecho/a","2- Satisfecho/a","3- Insatisfecho/a","4- Muy insatisfecho/a"),"") -> 3- Insatisfecho/a | N371: =IF(OR(I371="Trabajo actualmente como empleado",I371="Trabajo de manera independiente"),_xlfn.LET(_xlpm.opcion,MOD(INT((COUNTIF($I$2:I371,I371)-1)/5),6)+1,CHOOSE(IF(AND(_xlpm.opcion=6,L371="Sí, completamente"),5,_xlpm.opcion),"Salario","Estabilidad laboral","Horario","Acceso a prestaciones","Oportunidades de crecimiento","Trabajar en un área relacionada con mi formación")),"") -> Trabajar en un área relacionada con mi formación | O371: =IF(OR(I371="Trabajo actualmente como empleado",I371="Trabajo de manera independiente"),_xlfn.LET(_xlpm.turno,MOD(COUNTIF($I$2:I371,I371)-1,5),_xlpm.nivel,VALUE(LEFT(M371,1)),IF(_xlpm.turno=4,"No estoy seguro/a",IF(_xlpm.turno<IF(_xlpm.nivel<=2,1,3),"Sí","No"))),"") -> Sí | P371: =_xlfn.LET(_xlpm.perfil,I371,_xlpm.turno,COUNTIF($I$2:I371,_xlpm.perfil)-1,_xlpm.busca,OR(_xlpm.perfil="Actualmente no trabajo y estoy buscando empleo",_xlpm.perfil="Busco mi primer empleo"),_xlpm.trabaja,OR(_xlpm.perfil="Trabajo actualmente como empleado",_xlpm.perfil="Trabajo de manera independiente"),IF(_xlpm.busca,CHOOSE(MOD(_xlpm.turno*3,4)+1,"Menos de 1 mes","Entre 1 y 3 meses","Entre 4 y 6 meses","Más de 6 meses"),IF(OR(_xlpm.trabaja,_xlpm.perfil="Estudio y quiero comenzar a trabajar"),IF(AND(_xlpm.trabaja,O371="No"),"Todavía no he iniciado una búsqueda activa",CHOOSE(MOD(_xlpm.turno*3,5)+1,"Menos de 1 mes","Entre 1 y 3 meses","Entre 4 y 6 meses","Más de 6 meses","Todavía no he iniciado una búsqueda activa")),""))) -> Más de 6 meses | Q371: =IF(I371="Tengo un emprendimiento o quiero iniciar uno","",CHOOSE(MOD(INT((COUNTIF($I$2:I371,I371)-1)/7),3)+1,"Sí","No","Tengo una pero necesito actualizarla")) -> No | R371: =IF(I371="Tengo un emprendimiento o quiero iniciar uno","",IF(I371="Busco mi primer empleo","No",IF(MOD(COUNTIF($I$2:I371,I371)-1,2)=0,"Sí","No"))) -> Sí | S371: =IF(I371="Tengo un emprendimiento o quiero iniciar uno","",CHOOSE(MOD(INT((COUNTIF($I$2:I371,I371)-1)/3),10)+1,"Portales de empleo","Redes sociales","Familiares o conocidos","Empresas directamente","Ferias de empleo","Instituciones públicas","Institución educativa","No sé dónde buscar","Portales de empleo;Redes sociales","Familiares o conocidos;Empresas directamente")) -> Portales de empleo;Redes sociales | T371: =IF(I371="Tengo un emprendimiento o quiero iniciar uno","",_xlfn.LET(_xlpm.opcion,MOD(INT((COUNTIF($I$2:I371,I371)-1)/4),6)+1,CHOOSE(IF(AND(_xlpm.opcion=3,Q371="Sí"),1,_xlpm.opcion),"Falta de experiencia","Falta de formación","Dificultades con la hoja de vida","Horarios disponibles","Transporte","Internet"))) -> Internet | U371: =IF(I371="Tengo un emprendimiento o quiero iniciar uno","",IF(MOD(INT((COUNTIF($I$2:I371,I371)-1)/3),2)=0,"Sí","No")) -> Sí | V371: =IF(I371="Tengo un emprendimiento o quiero iniciar uno",CHOOSE(MOD(COUNTIF($I$2:I371,I371)-1,3)+1,"Tengo un emprendimiento","Estoy iniciando un emprendimiento","Me interesa emprender"),"") | W371: =IF(V371="Tengo un emprendimiento","Funcionamiento estable",IF(V371="Estoy iniciando un emprendimiento","Inicio","")) | X371: =IF(I371="Tengo un emprendimiento o quiero iniciar uno",CHOOSE(MOD(COUNTIF($I$2:I371,I371)-1,5)+1,"Falta de financiación","Falta de conocimientos administrativos","Falta de conocimientos financieros","Falta de tiempo","Falta de herramientas"),"") | Y371: =IF(I371="Tengo un emprendimiento o quiero iniciar uno",X371,"") | Z371: =IF(I371="Tengo un emprendimiento o quiero iniciar uno",CHOOSE(INT(MOD((COUNTIF($I$2:I371,I371)-1)*7,39)/13)+1,"Sí","No","No conozco programas de ese tipo"),"") | AA371: =CHOOSE(INT(MOD((ROW()-2)*191,479)/120)+1,"No puedo hacerlo","Puedo hacerlo con ayuda","Puedo hacerlo con dificultad","Puedo hacerlo sin ayuda") -> No puedo hacerlo | AB371: =CHOOSE(INT(MOD((ROW()-2)*191,479)/120)+1,"No puedo hacerlo","Puedo hacerlo con ayuda","Puedo hacerlo con dificultad","Puedo hacerlo sin ayuda") -> No puedo hacerlo | AC371: =CHOOSE(INT(MOD((ROW()-2)*157+83,479)/120)+1,"No puedo hacerlo","Puedo hacerlo con ayuda","Puedo hacerlo con dificultad","Puedo hacerlo sin ayuda") -> No puedo hacerlo | AD371: =CHOOSE(INT(MOD((ROW()-2)*89+131,479)/120)+1,"No puedo hacerlo","Puedo hacerlo con ayuda","Puedo hacerlo con dificultad","Puedo hacerlo sin ayuda") -> Puedo hacerlo sin ayuda | AE371: =CHOOSE(INT(MOD((ROW()-2)*73+179,479)/120)+1,"No puedo hacerlo","Puedo hacerlo con ayuda","Puedo hacerlo con dificultad","Puedo hacerlo sin ayuda") -> Puedo hacerlo con dificultad | AF371: =CHOOSE(MOD((ROW()-2)*61+23,10)+1,"Crear una hoja de vida","Preparación para entrevista","Comunicación","Liderazgo","Emprendimiento","Herramientas digitales","Educación financiera","Crear una hoja de vida;Preparación para entrevista","Comunicación;Liderazgo","Herramientas digitales;Educación financiera") -> Comunicación | AG371: =CHOOSE(MOD(INT((ROW()-2)/3)*7,9)+1,"Costos de transporte","Distancia","Horarios","Falta de experiencia","Falta de información","Ninguna","Costos de transporte;Distancia","Horarios;Falta de información","Falta de experiencia;Falta de información") -> Costos de transporte;Distancia | AH371: =CHOOSE(INT(MOD((ROW()-2)*199+59,479)/120)+1,"Oficina de orientación laboral","Ferias de empleo","Programas de emprendimiento","No conozco ninguno") -> Ferias de empleo | AI371: =CHOOSE(INT(MOD((ROW()-2)*127+71,479)/120)+1,"Presencial","Virtual","Presencial y virtual","Me es indiferente") -> Me es indiferente | AJ371: =CHOOSE(INT(MOD((ROW()-2)*163+97,479)/120)+1,"Diurno","Nocturno","Mañana entre semana","Fines de semana") -> Fines de semana | AK371: =CHOOSE(INT(MOD((ROW()-2)*181+109,479)/120)+1,"WhatsApp","Correo electrónico","Redes sociales","Celular") -> Redes sociales
A372: ="SG"&TEXT(ROW()-1,"000") -> SG371 | B372: CENTROS POBLADOS Y RURAL | C372: SI, ACEPTO PARTICIPAR | D372: =IF(MOD((ROW()-2)*137,479)<230,"Masculino",IF(MOD((ROW()-2)*137,479)<460,"Femenino",IF(MOD((ROW()-2)*137,479)<470,"Otro","No quiero responder"))) -> Femenino | E372: =CHOOSE(MOD(ROW()-2,5)+1,"De 18 a 20 años","De 20 a 22 años","De 22 a 24 años","De 24 a 26 años","De 26 a 28 años") -> De 18 a 20 años | F372: =CHOOSE(MOD(ROW()-2,5)+1,18,20,22,24,26)+MOD(INT((ROW()-2)/5),IF(MOD(ROW()-2,5)=4,3,2)) -> 18 | G372: =IF(MOD(ROW()-371,2)=0,"Centro poblado","Rural") -> Rural | H372: =_xlfn.LET(_xlpm.grupo,MOD(ROW()-2,5),_xlpm.turno,INT((ROW()-2)/5),_xlpm.orden,MOD(_xlpm.turno*37,IF(_xlpm.grupo=4,95,96)),CHOOSE(_xlpm.grupo+1,IF(_xlpm.orden<60,"Bachiller",IF(_xlpm.orden<84,"Técnico","Tecnólogo")),IF(_xlpm.orden<36,"Bachiller",IF(_xlpm.orden<66,"Técnico","Tecnólogo")),IF(_xlpm.orden<24,"Bachiller",IF(_xlpm.orden<48,"Técnico",IF(_xlpm.orden<72,"Tecnólogo","Profesional"))),IF(_xlpm.orden<12,"Bachiller",IF(_xlpm.orden<30,"Técnico",IF(_xlpm.orden<54,"Tecnólogo",IF(_xlpm.orden<90,"Profesional","Posgrado")))),IF(_xlpm.orden<10,"Bachiller",IF(_xlpm.orden<25,"Técnico",IF(_xlpm.orden<45,"Tecnólogo",IF(_xlpm.orden<85,"Profesional","Posgrado")))))) -> Bachiller | I372: =_xlfn.LET(_xlpm.orden,MOD((ROW()-2)*173,479),IF(_xlpm.orden<150,"Trabajo actualmente como empleado",IF(_xlpm.orden<230,"Trabajo de manera independiente",IF(_xlpm.orden<320,"Actualmente no trabajo y estoy buscando empleo",IF(_xlpm.orden<380,"Busco mi primer empleo",IF(_xlpm.orden<440,"Estudio y quiero comenzar a trabajar","Tengo un emprendimiento o quiero iniciar uno")))))) -> Actualmente no trabajo y estoy buscando empleo | J372: =IF(I372="Trabajo actualmente como empleado",IF(MOD((COUNTIF($I$2:I372,"Trabajo actualmente como empleado")-1)*37,150)<100,"Empleado con contrato","Empleado sin contrato formal"),IF(I372="Trabajo de manera independiente","Trabajo independiente","")) | K372: =IF(OR(I372="Trabajo actualmente como empleado",I372="Trabajo de manera independiente"),CHOOSE(MOD(COUNTIF($I$2:I372,I372)-1,4)+1,"Menos de 3 meses","De 3 a 6 meses","De 7 a 12 meses","Más de un año"),"") | L372: =IF(OR(I372="Trabajo actualmente como empleado",I372="Trabajo de manera independiente"),CHOOSE(MOD(COUNTIF($I$2:I372,I372)-1,3)+1,"Sí, completamente","Parcialmente","No"),"") | M372: =IF(OR(I372="Trabajo actualmente como empleado",I372="Trabajo de manera independiente"),CHOOSE(MOD(INT((COUNTIF($I$2:I372,I372)-1)/3),4)+1,"1- Muy satisfecho/a","2- Satisfecho/a","3- Insatisfecho/a","4- Muy insatisfecho/a"),"") | N372: =IF(OR(I372="Trabajo actualmente como empleado",I372="Trabajo de manera independiente"),_xlfn.LET(_xlpm.opcion,MOD(INT((COUNTIF($I$2:I372,I372)-1)/5),6)+1,CHOOSE(IF(AND(_xlpm.opcion=6,L372="Sí, completamente"),5,_xlpm.opcion),"Salario","Estabilidad laboral","Horario","Acceso a prestaciones","Oportunidades de crecimiento","Trabajar en un área relacionada con mi formación")),"") | O372: =IF(OR(I372="Trabajo actualmente como empleado",I372="Trabajo de manera independiente"),_xlfn.LET(_xlpm.turno,MOD(COUNTIF($I$2:I372,I372)-1,5),_xlpm.nivel,VALUE(LEFT(M372,1)),IF(_xlpm.turno=4,"No estoy seguro/a",IF(_xlpm.turno<IF(_xlpm.nivel<=2,1,3),"Sí","No"))),"") | P372: =_xlfn.LET(_xlpm.perfil,I372,_xlpm.turno,COUNTIF($I$2:I372,_xlpm.perfil)-1,_xlpm.busca,OR(_xlpm.perfil="Actualmente no trabajo y estoy buscando empleo",_xlpm.perfil="Busco mi primer empleo"),_xlpm.trabaja,OR(_xlpm.perfil="Trabajo actualmente como empleado",_xlpm.perfil="Trabajo de manera independiente"),IF(_xlpm.busca,CHOOSE(MOD(_xlpm.turno*3,4)+1,"Menos de 1 mes","Entre 1 y 3 meses","Entre 4 y 6 meses","Más de 6 meses"),IF(OR(_xlpm.trabaja,_xlpm.perfil="Estudio y quiero comenzar a trabajar"),IF(AND(_xlpm.trabaja,O372="No"),"Todavía no he iniciado una búsqueda activa",CHOOSE(MOD(_xlpm.turno*3,5)+1,"Menos de 1 mes","Entre 1 y 3 meses","Entre 4 y 6 meses","Más de 6 meses","Todavía no he iniciado una búsqueda activa")),""))) -> Menos de 1 mes | Q372: =IF(I372="Tengo un emprendimiento o quiero iniciar uno","",CHOOSE(MOD(INT((COUNTIF($I$2:I372,I372)-1)/7),3)+1,"Sí","No","Tengo una pero necesito actualizarla")) -> Sí | R372: =IF(I372="Tengo un emprendimiento o quiero iniciar uno","",IF(I372="Busco mi primer empleo","No",IF(MOD(COUNTIF($I$2:I372,I372)-1,2)=0,"Sí","No"))) -> Sí | S372: =IF(I372="Tengo un emprendimiento o quiero iniciar uno","",CHOOSE(MOD(INT((COUNTIF($I$2:I372,I372)-1)/3),10)+1,"Portales de empleo","Redes sociales","Familiares o conocidos","Empresas directamente","Ferias de empleo","Instituciones públicas","Institución educativa","No sé dónde buscar","Portales de empleo;Redes sociales","Familiares o conocidos;Empresas directamente")) -> Familiares o conocidos | T372: =IF(I372="Tengo un emprendimiento o quiero iniciar uno","",_xlfn.LET(_xlpm.opcion,MOD(INT((COUNTIF($I$2:I372,I372)-1)/4),6)+1,CHOOSE(IF(AND(_xlpm.opcion=3,Q372="Sí"),1,_xlpm.opcion),"Falta de experiencia","Falta de formación","Dificultades con la hoja de vida","Horarios disponibles","Transporte","Internet"))) -> Internet | U372: =IF(I372="Tengo un emprendimiento o quiero iniciar uno","",IF(MOD(INT((COUNTIF($I$2:I372,I372)-1)/3),2)=0,"Sí","No")) -> Sí | V372: =IF(I372="Tengo un emprendimiento o quiero iniciar uno",CHOOSE(MOD(COUNTIF($I$2:I372,I372)-1,3)+1,"Tengo un emprendimiento","Estoy iniciando un emprendimiento","Me interesa emprender"),"") | W372: =IF(V372="Tengo un emprendimiento","Funcionamiento estable",IF(V372="Estoy iniciando un emprendimiento","Inicio","")) | X372: =IF(I372="Tengo un emprendimiento o quiero iniciar uno",CHOOSE(MOD(COUNTIF($I$2:I372,I372)-1,5)+1,"Falta de financiación","Falta de conocimientos administrativos","Falta de conocimientos financieros","Falta de tiempo","Falta de herramientas"),"") | Y372: =IF(I372="Tengo un emprendimiento o quiero iniciar uno",X372,"") | Z372: =IF(I372="Tengo un emprendimiento o quiero iniciar uno",CHOOSE(INT(MOD((COUNTIF($I$2:I372,I372)-1)*7,39)/13)+1,"Sí","No","No conozco programas de ese tipo"),"") | AA372: =CHOOSE(INT(MOD((ROW()-2)*191,479)/120)+1,"No puedo hacerlo","Puedo hacerlo con ayuda","Puedo hacerlo con dificultad","Puedo hacerlo sin ayuda") -> Puedo hacerlo con dificultad | AB372: =CHOOSE(INT(MOD((ROW()-2)*191,479)/120)+1,"No puedo hacerlo","Puedo hacerlo con ayuda","Puedo hacerlo con dificultad","Puedo hacerlo sin ayuda") -> Puedo hacerlo con dificultad | AC372: =CHOOSE(INT(MOD((ROW()-2)*157+83,479)/120)+1,"No puedo hacerlo","Puedo hacerlo con ayuda","Puedo hacerlo con dificultad","Puedo hacerlo sin ayuda") -> Puedo hacerlo con ayuda | AD372: =CHOOSE(INT(MOD((ROW()-2)*89+131,479)/120)+1,"No puedo hacerlo","Puedo hacerlo con ayuda","Puedo hacerlo con dificultad","Puedo hacerlo sin ayuda") -> No puedo hacerlo | AE372: =CHOOSE(INT(MOD((ROW()-2)*73+179,479)/120)+1,"No puedo hacerlo","Puedo hacerlo con ayuda","Puedo hacerlo con dificultad","Puedo hacerlo sin ayuda") -> Puedo hacerlo sin ayuda | AF372: =CHOOSE(MOD((ROW()-2)*61+23,10)+1,"Crear una hoja de vida","Preparación para entrevista","Comunicación","Liderazgo","Emprendimiento","Herramientas digitales","Educación financiera","Crear una hoja de vida;Preparación para entrevista","Comunicación;Liderazgo","Herramientas digitales;Educación financiera") -> Liderazgo | AG372: =CHOOSE(MOD(INT((ROW()-2)/3)*7,9)+1,"Costos de transporte","Distancia","Horarios","Falta de experiencia","Falta de información","Ninguna","Costos de transporte;Distancia","Horarios;Falta de información","Falta de experiencia;Falta de información") -> Costos de transporte;Distancia | AH372: =CHOOSE(INT(MOD((ROW()-2)*199+59,479)/120)+1,"Oficina de orientación laboral","Ferias de empleo","Programas de emprendimiento","No conozco ninguno") -> No conozco ninguno | AI372: =CHOOSE(INT(MOD((ROW()-2)*127+71,479)/120)+1,"Presencial","Virtual","Presencial y virtual","Me es indiferente") -> Presencial | AJ372: =CHOOSE(INT(MOD((ROW()-2)*163+97,479)/120)+1,"Diurno","Nocturno","Mañana entre semana","Fines de semana") -> Diurno | AK372: =CHOOSE(INT(MOD((ROW()-2)*181+109,479)/120)+1,"WhatsApp","Correo electrónico","Redes sociales","Celular") -> WhatsApp
A373: ="SG"&TEXT(ROW()-1,"000") -> SG372 | B373: CENTROS POBLADOS Y RURAL | C373: SI, ACEPTO PARTICIPAR | D373: =IF(MOD((ROW()-2)*137,479)<230,"Masculino",IF(MOD((ROW()-2)*137,479)<460,"Femenino",IF(MOD((ROW()-2)*137,479)<470,"Otro","No quiero responder"))) -> Masculino | E373: =CHOOSE(MOD(ROW()-2,5)+1,"De 18 a 20 años","De 20 a 22 años","De 22 a 24 años","De 24 a 26 años","De 26 a 28 años") -> De 20 a 22 años | F373: =CHOOSE(MOD(ROW()-2,5)+1,18,20,22,24,26)+MOD(INT((ROW()-2)/5),IF(MOD(ROW()-2,5)=4,3,2)) -> 20 | G373: =IF(MOD(ROW()-371,2)=0,"Centro poblado","Rural") -> Centro poblado | H373: =_xlfn.LET(_xlpm.grupo,MOD(ROW()-2,5),_xlpm.turno,INT((ROW()-2)/5),_xlpm.orden,MOD(_xlpm.turno*37,IF(_xlpm.grupo=4,95,96)),CHOOSE(_xlpm.grupo+1,IF(_xlpm.orden<60,"Bachiller",IF(_xlpm.orden<84,"Técnico","Tecnólogo")),IF(_xlpm.orden<36,"Bachiller",IF(_xlpm.orden<66,"Técnico","Tecnólogo")),IF(_xlpm.orden<24,"Bachiller",IF(_xlpm.orden<48,"Técnico",IF(_xlpm.orden<72,"Tecnólogo","Profesional"))),IF(_xlpm.orden<12,"Bachiller",IF(_xlpm.orden<30,"Técnico",IF(_xlpm.orden<54,"Tecnólogo",IF(_xlpm.orden<90,"Profesional","Posgrado")))),IF(_xlpm.orden<10,"Bachiller",IF(_xlpm.orden<25,"Técnico",IF(_xlpm.orden<45,"Tecnólogo",IF(_xlpm.orden<85,"Profesional","Posgrado")))))) -> Técnico | I373: =_xlfn.LET(_xlpm.orden,MOD((ROW()-2)*173,479),IF(_xlpm.orden<150,"Trabajo actualmente como empleado",IF(_xlpm.orden<230,"Trabajo de manera independiente",IF(_xlpm.orden<320,"Actualmente no trabajo y estoy buscando empleo",IF(_xlpm.orden<380,"Busco mi primer empleo",IF(_xlpm.orden<440,"Estudio y quiero comenzar a trabajar","Tengo un emprendimiento o quiero iniciar uno")))))) -> Tengo un emprendimiento o quiero iniciar uno | J373: =IF(I373="Trabajo actualmente como empleado",IF(MOD((COUNTIF($I$2:I373,"Trabajo actualmente como empleado")-1)*37,150)<100,"Empleado con contrato","Empleado sin contrato formal"),IF(I373="Trabajo de manera independiente","Trabajo independiente","")) | K373: =IF(OR(I373="Trabajo actualmente como empleado",I373="Trabajo de manera independiente"),CHOOSE(MOD(COUNTIF($I$2:I373,I373)-1,4)+1,"Menos de 3 meses","De 3 a 6 meses","De 7 a 12 meses","Más de un año"),"") | L373: =IF(OR(I373="Trabajo actualmente como empleado",I373="Trabajo de manera independiente"),CHOOSE(MOD(COUNTIF($I$2:I373,I373)-1,3)+1,"Sí, completamente","Parcialmente","No"),"") | M373: =IF(OR(I373="Trabajo actualmente como empleado",I373="Trabajo de manera independiente"),CHOOSE(MOD(INT((COUNTIF($I$2:I373,I373)-1)/3),4)+1,"1- Muy satisfecho/a","2- Satisfecho/a","3- Insatisfecho/a","4- Muy insatisfecho/a"),"") | N373: =IF(OR(I373="Trabajo actualmente como empleado",I373="Trabajo de manera independiente"),_xlfn.LET(_xlpm.opcion,MOD(INT((COUNTIF($I$2:I373,I373)-1)/5),6)+1,CHOOSE(IF(AND(_xlpm.opcion=6,L373="Sí, completamente"),5,_xlpm.opcion),"Salario","Estabilidad laboral","Horario","Acceso a prestaciones","Oportunidades de crecimiento","Trabajar en un área relacionada con mi formación")),"") | O373: =IF(OR(I373="Trabajo actualmente como empleado",I373="Trabajo de manera independiente"),_xlfn.LET(_xlpm.turno,MOD(COUNTIF($I$2:I373,I373)-1,5),_xlpm.nivel,VALUE(LEFT(M373,1)),IF(_xlpm.turno=4,"No estoy seguro/a",IF(_xlpm.turno<IF(_xlpm.nivel<=2,1,3),"Sí","No"))),"") | P373: =_xlfn.LET(_xlpm.perfil,I373,_xlpm.turno,COUNTIF($I$2:I373,_xlpm.perfil)-1,_xlpm.busca,OR(_xlpm.perfil="Actualmente no trabajo y estoy buscando empleo",_xlpm.perfil="Busco mi primer empleo"),_xlpm.trabaja,OR(_xlpm.perfil="Trabajo actualmente como empleado",_xlpm.perfil="Trabajo de manera independiente"),IF(_xlpm.busca,CHOOSE(MOD(_xlpm.turno*3,4)+1,"Menos de 1 mes","Entre 1 y 3 meses","Entre 4 y 6 meses","Más de 6 meses"),IF(OR(_xlpm.trabaja,_xlpm.perfil="Estudio y quiero comenzar a trabajar"),IF(AND(_xlpm.trabaja,O373="No"),"Todavía no he iniciado una búsqueda activa",CHOOSE(MOD(_xlpm.turno*3,5)+1,"Menos de 1 mes","Entre 1 y 3 meses","Entre 4 y 6 meses","Más de 6 meses","Todavía no he iniciado una búsqueda activa")),""))) | Q373: =IF(I373="Tengo un emprendimiento o quiero iniciar uno","",CHOOSE(MOD(INT((COUNTIF($I$2:I373,I373)-1)/7),3)+1,"Sí","No","Tengo una pero necesito actualizarla")) | R373: =IF(I373="Tengo un emprendimiento o quiero iniciar uno","",IF(I373="Busco mi primer empleo","No",IF(MOD(COUNTIF($I$2:I373,I373)-1,2)=0,"Sí","No"))) | S373: =IF(I373="Tengo un emprendimiento o quiero iniciar uno","",CHOOSE(MOD(INT((COUNTIF($I$2:I373,I373)-1)/3),10)+1,"Portales de empleo","Redes sociales","Familiares o conocidos","Empresas directamente","Ferias de empleo","Instituciones públicas","Institución educativa","No sé dónde buscar","Portales de empleo;Redes sociales","Familiares o conocidos;Empresas directamente")) | T373: =IF(I373="Tengo un emprendimiento o quiero iniciar uno","",_xlfn.LET(_xlpm.opcion,MOD(INT((COUNTIF($I$2:I373,I373)-1)/4),6)+1,CHOOSE(IF(AND(_xlpm.opcion=3,Q373="Sí"),1,_xlpm.opcion),"Falta de experiencia","Falta de formación","Dificultades con la hoja de vida","Horarios disponibles","Transporte","Internet"))) | U373: =IF(I373="Tengo un emprendimiento o quiero iniciar uno","",IF(MOD(INT((COUNTIF($I$2:I373,I373)-1)/3),2)=0,"Sí","No")) | V373: =IF(I373="Tengo un emprendimiento o quiero iniciar uno",CHOOSE(MOD(COUNTIF($I$2:I373,I373)-1,3)+1,"Tengo un emprendimiento","Estoy iniciando un emprendimiento","Me interesa emprender"),"") -> Tengo un emprendimiento | W373: =IF(V373="Tengo un emprendimiento","Funcionamiento estable",IF(V373="Estoy iniciando un emprendimiento","Inicio","")) -> Funcionamiento estable | X373: =IF(I373="Tengo un emprendimiento o quiero iniciar uno",CHOOSE(MOD(COUNTIF($I$2:I373,I373)-1,5)+1,"Falta de financiación","Falta de conocimientos administrativos","Falta de conocimientos financieros","Falta de tiempo","Falta de herramientas"),"") -> Falta de financiación | Y373: =IF(I373="Tengo un emprendimiento o quiero iniciar uno",X373,"") -> Falta de financiación | Z373: =IF(I373="Tengo un emprendimiento o quiero iniciar uno",CHOOSE(INT(MOD((COUNTIF($I$2:I373,I373)-1)*7,39)/13)+1,"Sí","No","No conozco programas de ese tipo"),"") -> No | AA373: =CHOOSE(INT(MOD((ROW()-2)*191,479)/120)+1,"No puedo hacerlo","Puedo hacerlo con ayuda","Puedo hacerlo con dificultad","Puedo hacerlo sin ayuda") -> Puedo hacerlo sin ayuda | AB373: =CHOOSE(INT(MOD((ROW()-2)*191,479)/120)+1,"No puedo hacerlo","Puedo hacerlo con ayuda","Puedo hacerlo con dificultad","Puedo hacerlo sin ayuda") -> Puedo hacerlo sin ayuda | AC373: =CHOOSE(INT(MOD((ROW()-2)*157+83,479)/120)+1,"No puedo hacerlo","Puedo hacerlo con ayuda","Puedo hacerlo con dificultad","Puedo hacerlo sin ayuda") -> Puedo hacerlo sin ayuda | AD373: =CHOOSE(INT(MOD((ROW()-2)*89+131,479)/120)+1,"No puedo hacerlo","Puedo hacerlo con ayuda","Puedo hacerlo con dificultad","Puedo hacerlo sin ayuda") -> No puedo hacerlo | AE373: =CHOOSE(INT(MOD((ROW()-2)*73+179,479)/120)+1,"No puedo hacerlo","Puedo hacerlo con ayuda","Puedo hacerlo con dificultad","Puedo hacerlo sin ayuda") -> Puedo hacerlo sin ayuda | AF373: =CHOOSE(MOD((ROW()-2)*61+23,10)+1,"Crear una hoja de vida","Preparación para entrevista","Comunicación","Liderazgo","Emprendimiento","Herramientas digitales","Educación financiera","Crear una hoja de vida;Preparación para entrevista","Comunicación;Liderazgo","Herramientas digitales;Educación financiera") -> Emprendimiento | AG373: =CHOOSE(MOD(INT((ROW()-2)/3)*7,9)+1,"Costos de transporte","Distancia","Horarios","Falta de experiencia","Falta de información","Ninguna","Costos de transporte;Distancia","Horarios;Falta de información","Falta de experiencia;Falta de información") -> Costos de transporte;Distancia | AH373: =CHOOSE(INT(MOD((ROW()-2)*199+59,479)/120)+1,"Oficina de orientación laboral","Ferias de empleo","Programas de emprendimiento","No conozco ninguno") -> Ferias de empleo | AI373: =CHOOSE(INT(MOD((ROW()-2)*127+71,479)/120)+1,"Presencial","Virtual","Presencial y virtual","Me es indiferente") -> Presencial y virtual | AJ373: =CHOOSE(INT(MOD((ROW()-2)*163+97,479)/120)+1,"Diurno","Nocturno","Mañana entre semana","Fines de semana") -> Nocturno | AK373: =CHOOSE(INT(MOD((ROW()-2)*181+109,479)/120)+1,"WhatsApp","Correo electrónico","Redes sociales","Celular") -> Correo electrónico
A374: ="SG"&TEXT(ROW()-1,"000") -> SG373 | B374: CENTROS POBLADOS Y RURAL | C374: SI, ACEPTO PARTICIPAR | D374: =IF(MOD((ROW()-2)*137,479)<230,"Masculino",IF(MOD((ROW()-2)*137,479)<460,"Femenino",IF(MOD((ROW()-2)*137,479)<470,"Otro","No quiero responder"))) -> Masculino | E374: =CHOOSE(MOD(ROW()-2,5)+1,"De 18 a 20 años","De 20 a 22 años","De 22 a 24 años","De 24 a 26 años","De 26 a 28 años") -> De 22 a 24 años | F374: =CHOOSE(MOD(ROW()-2,5)+1,18,20,22,24,26)+MOD(INT((ROW()-2)/5),IF(MOD(ROW()-2,5)=4,3,2)) -> 22 | G374: =IF(MOD(ROW()-371,2)=0,"Centro poblado","Rural") -> Rural | H374: =_xlfn.LET(_xlpm.grupo,MOD(ROW()-2,5),_xlpm.turno,INT((ROW()-2)/5),_xlpm.orden,MOD(_xlpm.turno*37,IF(_xlpm.grupo=4,95,96)),CHOOSE(_xlpm.grupo+1,IF(_xlpm.orden<60,"Bachiller",IF(_xlpm.orden<84,"Técnico","Tecnólogo")),IF(_xlpm.orden<36,"Bachiller",IF(_xlpm.orden<66,"Técnico","Tecnólogo")),IF(_xlpm.orden<24,"Bachiller",IF(_xlpm.orden<48,"Técnico",IF(_xlpm.orden<72,"Tecnólogo","Profesional"))),IF(_xlpm.orden<12,"Bachiller",IF(_xlpm.orden<30,"Técnico",IF(_xlpm.orden<54,"Tecnólogo",IF(_xlpm.orden<90,"Profesional","Posgrado")))),IF(_xlpm.orden<10,"Bachiller",IF(_xlpm.orden<25,"Técnico",IF(_xlpm.orden<45,"Tecnólogo",IF(_xlpm.orden<85,"Profesional","Posgrado")))))) -> Tecnólogo | I374: =_xlfn.LET(_xlpm.orden,MOD((ROW()-2)*173,479),IF(_xlpm.orden<150,"Trabajo actualmente como empleado",IF(_xlpm.orden<230,"Trabajo de manera independiente",IF(_xlpm.orden<320,"Actualmente no trabajo y estoy buscando empleo",IF(_xlpm.orden<380,"Busco mi primer empleo",IF(_xlpm.orden<440,"Estudio y quiero comenzar a trabajar","Tengo un emprendimiento o quiero iniciar uno")))))) -> Trabajo de manera independiente | J374: =IF(I374="Trabajo actualmente como empleado",IF(MOD((COUNTIF($I$2:I374,"Trabajo actualmente como empleado")-1)*37,150)<100,"Empleado con contrato","Empleado sin contrato formal"),IF(I374="Trabajo de manera independiente","Trabajo independiente","")) -> Trabajo independiente | K374: =IF(OR(I374="Trabajo actualmente como empleado",I374="Trabajo de manera independiente"),CHOOSE(MOD(COUNTIF($I$2:I374,I374)-1,4)+1,"Menos de 3 meses","De 3 a 6 meses","De 7 a 12 meses","Más de un año"),"") -> De 7 a 12 meses | L374: =IF(OR(I374="Trabajo actualmente como empleado",I374="Trabajo de manera independiente"),CHOOSE(MOD(COUNTIF($I$2:I374,I374)-1,3)+1,"Sí, completamente","Parcialmente","No"),"") -> No | M374: =IF(OR(I374="Trabajo actualmente como empleado",I374="Trabajo de manera independiente"),CHOOSE(MOD(INT((COUNTIF($I$2:I374,I374)-1)/3),4)+1,"1- Muy satisfecho/a","2- Satisfecho/a","3- Insatisfecho/a","4- Muy insatisfecho/a"),"") -> 1- Muy satisfecho/a | N374: =IF(OR(I374="Trabajo actualmente como empleado",I374="Trabajo de manera independiente"),_xlfn.LET(_xlpm.opcion,MOD(INT((COUNTIF($I$2:I374,I374)-1)/5),6)+1,CHOOSE(IF(AND(_xlpm.opcion=6,L374="Sí, completamente"),5,_xlpm.opcion),"Salario","Estabilidad laboral","Horario","Acceso a prestaciones","Oportunidades de crecimiento","Trabajar en un área relacionada con mi formación")),"") -> Salario | O374: =IF(OR(I374="Trabajo actualmente como empleado",I374="Trabajo de manera independiente"),_xlfn.LET(_xlpm.turno,MOD(COUNTIF($I$2:I374,I374)-1,5),_xlpm.nivel,VALUE(LEFT(M374,1)),IF(_xlpm.turno=4,"No estoy seguro/a",IF(_xlpm.turno<IF(_xlpm.nivel<=2,1,3),"Sí","No"))),"") -> No | P374: =_xlfn.LET(_xlpm.perfil,I374,_xlpm.turno,COUNTIF($I$2:I374,_xlpm.perfil)-1,_xlpm.busca,OR(_xlpm.perfil="Actualmente no trabajo y estoy buscando empleo",_xlpm.perfil="Busco mi primer empleo"),_xlpm.trabaja,OR(_xlpm.perfil="Trabajo actualmente como empleado",_xlpm.perfil="Trabajo de manera independiente"),IF(_xlpm.busca,CHOOSE(MOD(_xlpm.turno*3,4)+1,"Menos de 1 mes","Entre 1 y 3 meses","Entre 4 y 6 meses","Más de 6 meses"),IF(OR(_xlpm.trabaja,_xlpm.perfil="Estudio y quiero comenzar a trabajar"),IF(AND(_xlpm.trabaja,O374="No"),"Todavía no he iniciado una búsqueda activa",CHOOSE(MOD(_xlpm.turno*3,5)+1,"Menos de 1 mes","Entre 1 y 3 meses","Entre 4 y 6 meses","Más de 6 meses","Todavía no he iniciado una búsqueda activa")),""))) -> Todavía no he iniciado una búsqueda activa | Q374: =IF(I374="Tengo un emprendimiento o quiero iniciar uno","",CHOOSE(MOD(INT((COUNTIF($I$2:I374,I374)-1)/7),3)+1,"Sí","No","Tengo una pero necesito actualizarla")) -> Tengo una pero necesito actualizarla | R374: =IF(I374="Tengo un emprendimiento o quiero iniciar uno","",IF(I374="Busco mi primer empleo","No",IF(MOD(COUNTIF($I$2:I374,I374)-1,2)=0,"Sí","No"))) -> Sí | S374: =IF(I374="Tengo un emprendimiento o quiero iniciar uno","",CHOOSE(MOD(INT((COUNTIF($I$2:I374,I374)-1)/3),10)+1,"Portales de empleo","Redes sociales","Familiares o conocidos","Empresas directamente","Ferias de empleo","Instituciones públicas","Institución educativa","No sé dónde buscar","Portales de empleo;Redes sociales","Familiares o conocidos;Empresas directamente")) -> Portales de empleo | T374: =IF(I374="Tengo un emprendimiento o quiero iniciar uno","",_xlfn.LET(_xlpm.opcion,MOD(INT((COUNTIF($I$2:I374,I374)-1)/4),6)+1,CHOOSE(IF(AND(_xlpm.opcion=3,Q374="Sí"),1,_xlpm.opcion),"Falta de experiencia","Falta de formación","Dificultades con la hoja de vida","Horarios disponibles","Transporte","Internet"))) -> Horarios disponibles | U374: =IF(I374="Tengo un emprendimiento o quiero iniciar uno","",IF(MOD(INT((COUNTIF($I$2:I374,I374)-1)/3),2)=0,"Sí","No")) -> Sí | V374: =IF(I374="Tengo un emprendimiento o quiero iniciar uno",CHOOSE(MOD(COUNTIF($I$2:I374,I374)-1,3)+1,"Tengo un emprendimiento","Estoy iniciando un emprendimiento","Me interesa emprender"),"") | W374: =IF(V374="Tengo un emprendimiento","Funcionamiento estable",IF(V374="Estoy iniciando un emprendimiento","Inicio","")) | X374: =IF(I374="Tengo un emprendimiento o quiero iniciar uno",CHOOSE(MOD(COUNTIF($I$2:I374,I374)-1,5)+1,"Falta de financiación","Falta de conocimientos administrativos","Falta de conocimientos financieros","Falta de tiempo","Falta de herramientas"),"") | Y374: =IF(I374="Tengo un emprendimiento o quiero iniciar uno",X374,"") | Z374: =IF(I374="Tengo un emprendimiento o quiero iniciar uno",CHOOSE(INT(MOD((COUNTIF($I$2:I374,I374)-1)*7,39)/13)+1,"Sí","No","No conozco programas de ese tipo"),"") | AA374: =CHOOSE(INT(MOD((ROW()-2)*191,479)/120)+1,"No puedo hacerlo","Puedo hacerlo con ayuda","Puedo hacerlo con dificultad","Puedo hacerlo sin ayuda") -> Puedo hacerlo con ayuda | AB374: =CHOOSE(INT(MOD((ROW()-2)*191,479)/120)+1,"No puedo hacerlo","Puedo hacerlo con ayuda","Puedo hacerlo con dificultad","Puedo hacerlo sin ayuda") -> Puedo hacerlo con ayuda | AC374: =CHOOSE(INT(MOD((ROW()-2)*157+83,479)/120)+1,"No puedo hacerlo","Puedo hacerlo con ayuda","Puedo hacerlo con dificultad","Puedo hacerlo sin ayuda") -> No puedo hacerlo | AD374: =CHOOSE(INT(MOD((ROW()-2)*89+131,479)/120)+1,"No puedo hacerlo","Puedo hacerlo con ayuda","Puedo hacerlo con dificultad","Puedo hacerlo sin ayuda") -> Puedo hacerlo con ayuda | AE374: =CHOOSE(INT(MOD((ROW()-2)*73+179,479)/120)+1,"No puedo hacerlo","Puedo hacerlo con ayuda","Puedo hacerlo con dificultad","Puedo hacerlo sin ayuda") -> No puedo hacerlo | AF374: =CHOOSE(MOD((ROW()-2)*61+23,10)+1,"Crear una hoja de vida","Preparación para entrevista","Comunicación","Liderazgo","Emprendimiento","Herramientas digitales","Educación financiera","Crear una hoja de vida;Preparación para entrevista","Comunicación;Liderazgo","Herramientas digitales;Educación financiera") -> Herramientas digitales | AG374: =CHOOSE(MOD(INT((ROW()-2)/3)*7,9)+1,"Costos de transporte","Distancia","Horarios","Falta de experiencia","Falta de información","Ninguna","Costos de transporte;Distancia","Horarios;Falta de información","Falta de experiencia;Falta de información") -> Falta de información | AH374: =CHOOSE(INT(MOD((ROW()-2)*199+59,479)/120)+1,"Oficina de orientación laboral","Ferias de empleo","Programas de emprendimiento","No conozco ninguno") -> Programas de emprendimiento | AI374: =CHOOSE(INT(MOD((ROW()-2)*127+71,479)/120)+1,"Presencial","Virtual","Presencial y virtual","Me es indiferente") -> Me es indiferente | AJ374: =CHOOSE(INT(MOD((ROW()-2)*163+97,479)/120)+1,"Diurno","Nocturno","Mañana entre semana","Fines de semana") -> Fines de semana | AK374: =CHOOSE(INT(MOD((ROW()-2)*181+109,479)/120)+1,"WhatsApp","Correo electrónico","Redes sociales","Celular") -> Celular
A375: ="SG"&TEXT(ROW()-1,"000") -> SG374 | B375: CENTROS POBLADOS Y RURAL | C375: SI, ACEPTO PARTICIPAR | D375: =IF(MOD((ROW()-2)*137,479)<230,"Masculino",IF(MOD((ROW()-2)*137,479)<460,"Femenino",IF(MOD((ROW()-2)*137,479)<470,"Otro","No quiero responder"))) -> Femenino | E375: De 24 a 26 años | F375: =CHOOSE(MOD(ROW()-2,5)+1,18,20,22,24,26)+MOD(INT((ROW()-2)/5),IF(MOD(ROW()-2,5)=4,3,2)) -> 24 | G375: =IF(MOD(ROW()-371,2)=0,"Centro poblado","Rural") -> Centro poblado | H375: =_xlfn.LET(_xlpm.grupo,MOD(ROW()-2,5),_xlpm.turno,INT((ROW()-2)/5),_xlpm.orden,MOD(_xlpm.turno*37,IF(_xlpm.grupo=4,95,96)),CHOOSE(_xlpm.grupo+1,IF(_xlpm.orden<60,"Bachiller",IF(_xlpm.orden<84,"Técnico","Tecnólogo")),IF(_xlpm.orden<36,"Bachiller",IF(_xlpm.orden<66,"Técnico","Tecnólogo")),IF(_xlpm.orden<24,"Bachiller",IF(_xlpm.orden<48,"Técnico",IF(_xlpm.orden<72,"Tecnólogo","Profesional"))),IF(_xlpm.orden<12,"Bachiller",IF(_xlpm.orden<30,"Técnico",IF(_xlpm.orden<54,"Tecnólogo",IF(_xlpm.orden<90,"Profesional","Posgrado")))),IF(_xlpm.orden<10,"Bachiller",IF(_xlpm.orden<25,"Técnico",IF(_xlpm.orden<45,"Tecnólogo",IF(_xlpm.orden<85,"Profesional","Posgrado")))))) -> Tecnólogo | I375: =_xlfn.LET(_xlpm.orden,MOD((ROW()-2)*173,479),IF(_xlpm.orden<150,"Trabajo actualmente como empleado",IF(_xlpm.orden<230,"Trabajo de manera independiente",IF(_xlpm.orden<320,"Actualmente no trabajo y estoy buscando empleo",IF(_xlpm.orden<380,"Busco mi primer empleo",IF(_xlpm.orden<440,"Estudio y quiero comenzar a trabajar","Tengo un emprendimiento o quiero iniciar uno")))))) -> Busco mi primer empleo | J375: =IF(I375="Trabajo actualmente como empleado",IF(MOD((COUNTIF($I$2:I375,"Trabajo actualmente como empleado")-1)*37,150)<100,"Empleado con contrato","Empleado sin contrato formal"),IF(I375="Trabajo de manera independiente","Trabajo independiente","")) | K375: =IF(OR(I375="Trabajo actualmente como empleado",I375="Trabajo de manera independiente"),CHOOSE(MOD(COUNTIF($I$2:I375,I375)-1,4)+1,"Menos de 3 meses","De 3 a 6 meses","De 7 a 12 meses","Más de un año"),"") | L375: =IF(OR(I375="Trabajo actualmente como empleado",I375="Trabajo de manera independiente"),CHOOSE(MOD(COUNTIF($I$2:I375,I375)-1,3)+1,"Sí, completamente","Parcialmente","No"),"") | M375: =IF(OR(I375="Trabajo actualmente como empleado",I375="Trabajo de manera independiente"),CHOOSE(MOD(INT((COUNTIF($I$2:I375,I375)-1)/3),4)+1,"1- Muy satisfecho/a","2- Satisfecho/a","3- Insatisfecho/a","4- Muy insatisfecho/a"),"") | N375: =IF(OR(I375="Trabajo actualmente como empleado",I375="Trabajo de manera independiente"),_xlfn.LET(_xlpm.opcion,MOD(INT((COUNTIF($I$2:I375,I375)-1)/5),6)+1,CHOOSE(IF(AND(_xlpm.opcion=6,L375="Sí, completamente"),5,_xlpm.opcion),"Salario","Estabilidad laboral","Horario","Acceso a prestaciones","Oportunidades de crecimiento","Trabajar en un área relacionada con mi formación")),"") | O375: =IF(OR(I375="Trabajo actualmente como empleado",I375="Trabajo de manera independiente"),_xlfn.LET(_xlpm.turno,MOD(COUNTIF($I$2:I375,I375)-1,5),_xlpm.nivel,VALUE(LEFT(M375,1)),IF(_xlpm.turno=4,"No estoy seguro/a",IF(_xlpm.turno<IF(_xlpm.nivel<=2,1,3),"Sí","No"))),"") | P375: =_xlfn.LET(_xlpm.perfil,I375,_xlpm.turno,COUNTIF($I$2:I375,_xlpm.perfil)-1,_xlpm.busca,OR(_xlpm.perfil="Actualmente no trabajo y estoy buscando empleo",_xlpm.perfil="Busco mi primer empleo"),_xlpm.trabaja,OR(_xlpm.perfil="Trabajo actualmente como empleado",_xlpm.perfil="Trabajo de manera independiente"),IF(_xlpm.busca,CHOOSE(MOD(_xlpm.turno*3,4)+1,"Menos de 1 mes","Entre 1 y 3 meses","Entre 4 y 6 meses","Más de 6 meses"),IF(OR(_xlpm.trabaja,_xlpm.perfil="Estudio y quiero comenzar a trabajar"),IF(AND(_xlpm.trabaja,O375="No"),"Todavía no he iniciado una búsqueda activa",CHOOSE(MOD(_xlpm.turno*3,5)+1,"Menos de 1 mes","Entre 1 y 3 meses","Entre 4 y 6 meses","Más de 6 meses","Todavía no he iniciado una búsqueda activa")),""))) -> Menos de 1 mes | Q375: =IF(I375="Tengo un emprendimiento o quiero iniciar uno","",CHOOSE(MOD(INT((COUNTIF($I$2:I375,I375)-1)/7),3)+1,"Sí","No","Tengo una pero necesito actualizarla")) -> Sí | R375: =IF(I375="Tengo un emprendimiento o quiero iniciar uno","",IF(I375="Busco mi primer empleo","No",IF(MOD(COUNTIF($I$2:I375,I375)-1,2)=0,"Sí","No"))) -> No | S375: =IF(I375="Tengo un emprendimiento o quiero iniciar uno","",CHOOSE(MOD(INT((COUNTIF($I$2:I375,I375)-1)/3),10)+1,"Portales de empleo","Redes sociales","Familiares o conocidos","Empresas directamente","Ferias de empleo","Instituciones públicas","Institución educativa","No sé dónde buscar","Portales de empleo;Redes sociales","Familiares o conocidos;Empresas directamente")) -> Institución educativa | T375: =IF(I375="Tengo un emprendimiento o quiero iniciar uno","",_xlfn.LET(_xlpm.opcion,MOD(INT((COUNTIF($I$2:I375,I375)-1)/4),6)+1,CHOOSE(IF(AND(_xlpm.opcion=3,Q375="Sí"),1,_xlpm.opcion),"Falta de experiencia","Falta de formación","Dificultades con la hoja de vida","Horarios disponibles","Transporte","Internet"))) -> Falta de experiencia | U375: =IF(I375="Tengo un emprendimiento o quiero iniciar uno","",IF(MOD(INT((COUNTIF($I$2:I375,I375)-1)/3),2)=0,"Sí","No")) -> Sí | V375: =IF(I375="Tengo un emprendimiento o quiero iniciar uno",CHOOSE(MOD(COUNTIF($I$2:I375,I375)-1,3)+1,"Tengo un emprendimiento","Estoy iniciando un emprendimiento","Me interesa emprender"),"") | W375: =IF(V375="Tengo un emprendimiento","Funcionamiento estable",IF(V375="Estoy iniciando un emprendimiento","Inicio","")) | X375: =IF(I375="Tengo un emprendimiento o quiero iniciar uno",CHOOSE(MOD(COUNTIF($I$2:I375,I375)-1,5)+1,"Falta de financiación","Falta de conocimientos administrativos","Falta de conocimientos financieros","Falta de tiempo","Falta de herramientas"),"") | Y375: =IF(I375="Tengo un emprendimiento o quiero iniciar uno",X375,"") | Z375: =IF(I375="Tengo un emprendimiento o quiero iniciar uno",CHOOSE(INT(MOD((COUNTIF($I$2:I375,I375)-1)*7,39)/13)+1,"Sí","No","No conozco programas de ese tipo"),"") | AA375: =CHOOSE(INT(MOD((ROW()-2)*191,479)/120)+1,"No puedo hacerlo","Puedo hacerlo con ayuda","Puedo hacerlo con dificultad","Puedo hacerlo sin ayuda") -> Puedo hacerlo con dificultad | AB375: =CHOOSE(INT(MOD((ROW()-2)*191,479)/120)+1,"No puedo hacerlo","Puedo hacerlo con ayuda","Puedo hacerlo con dificultad","Puedo hacerlo sin ayuda") -> Puedo hacerlo con dificultad | AC375: =CHOOSE(INT(MOD((ROW()-2)*157+83,479)/120)+1,"No puedo hacerlo","Puedo hacerlo con ayuda","Puedo hacerlo con dificultad","Puedo hacerlo sin ayuda") -> Puedo hacerlo con ayuda | AD375: =CHOOSE(INT(MOD((ROW()-2)*89+131,479)/120)+1,"No puedo hacerlo","Puedo hacerlo con ayuda","Puedo hacerlo con dificultad","Puedo hacerlo sin ayuda") -> Puedo hacerlo con dificultad | AE375: =CHOOSE(INT(MOD((ROW()-2)*73+179,479)/120)+1,"No puedo hacerlo","Puedo hacerlo con ayuda","Puedo hacerlo con dificultad","Puedo hacerlo sin ayuda") -> No puedo hacerlo | AF375: =CHOOSE(MOD((ROW()-2)*61+23,10)+1,"Crear una hoja de vida","Preparación para entrevista","Comunicación","Liderazgo","Emprendimiento","Herramientas digitales","Educación financiera","Crear una hoja de vida;Preparación para entrevista","Comunicación;Liderazgo","Herramientas digitales;Educación financiera") -> Educación financiera | AG375: =CHOOSE(MOD(INT((ROW()-2)/3)*7,9)+1,"Costos de transporte","Distancia","Horarios","Falta de experiencia","Falta de información","Ninguna","Costos de transporte;Distancia","Horarios;Falta de información","Falta de experiencia;Falta de información") -> Falta de información | AH375: =CHOOSE(INT(MOD((ROW()-2)*199+59,479)/120)+1,"Oficina de orientación laboral","Ferias de empleo","Programas de emprendimiento","No conozco ninguno") -> Oficina de orientación laboral | AI375: =CHOOSE(INT(MOD((ROW()-2)*127+71,479)/120)+1,"Presencial","Virtual","Presencial y virtual","Me es indiferente") -> Presencial | AJ375: =CHOOSE(INT(MOD((ROW()-2)*163+97,479)/120)+1,"Diurno","Nocturno","Mañana entre semana","Fines de semana") -> Diurno | AK375: =CHOOSE(INT(MOD((ROW()-2)*181+109,479)/120)+1,"WhatsApp","Correo electrónico","Redes sociales","Celular") -> WhatsApp
A376: ="SG"&TEXT(ROW()-1,"000") -> SG375 | B376: CENTROS POBLADOS Y RURAL | C376: SI, ACEPTO PARTICIPAR | D376: =IF(MOD((ROW()-2)*137,479)<230,"Masculino",IF(MOD((ROW()-2)*137,479)<460,"Femenino",IF(MOD((ROW()-2)*137,479)<470,"Otro","No quiero responder"))) -> Otro | E376: =CHOOSE(MOD(ROW()-2,5)+1,"De 18 a 20 años","De 20 a 22 años","De 22 a 24 años","De 24 a 26 años","De 26 a 28 años") -> De 26 a 28 años | F376: =CHOOSE(MOD(ROW()-2,5)+1,18,20,22,24,26)+MOD(INT((ROW()-2)/5),IF(MOD(ROW()-2,5)=4,3,2)) -> 28 | G376: =IF(MOD(ROW()-371,2)=0,"Centro poblado","Rural") -> Rural | H376: =_xlfn.LET(_xlpm.grupo,MOD(ROW()-2,5),_xlpm.turno,INT((ROW()-2)/5),_xlpm.orden,MOD(_xlpm.turno*37,IF(_xlpm.grupo=4,95,96)),CHOOSE(_xlpm.grupo+1,IF(_xlpm.orden<60,"Bachiller",IF(_xlpm.orden<84,"Técnico","Tecnólogo")),IF(_xlpm.orden<36,"Bachiller",IF(_xlpm.orden<66,"Técnico","Tecnólogo")),IF(_xlpm.orden<24,"Bachiller",IF(_xlpm.orden<48,"Técnico",IF(_xlpm.orden<72,"Tecnólogo","Profesional"))),IF(_xlpm.orden<12,"Bachiller",IF(_xlpm.orden<30,"Técnico",IF(_xlpm.orden<54,"Tecnólogo",IF(_xlpm.orden<90,"Profesional","Posgrado")))),IF(_xlpm.orden<10,"Bachiller",IF(_xlpm.orden<25,"Técnico",IF(_xlpm.orden<45,"Tecnólogo",IF(_xlpm.orden<85,"Profesional","Posgrado")))))) -> Profesional | I376: =_xlfn.LET(_xlpm.orden,MOD((ROW()-2)*173,479),IF(_xlpm.orden<150,"Trabajo actualmente como empleado",IF(_xlpm.orden<230,"Trabajo de manera independiente",IF(_xlpm.orden<320,"Actualmente no trabajo y estoy buscando empleo",IF(_xlpm.orden<380,"Busco mi primer empleo",IF(_xlpm.orden<440,"Estudio y quiero comenzar a trabajar","Tengo un emprendimiento o quiero iniciar uno")))))) -> Trabajo actualmente como empleado | J376: =IF(I376="Trabajo actualmente como empleado",IF(MOD((COUNTIF($I$2:I376,"Trabajo actualmente como empleado")-1)*37,150)<100,"Empleado con contrato","Empleado sin contrato formal"),IF(I376="Trabajo de manera independiente","Trabajo independiente","")) -> Empleado sin contrato formal | K376: =IF(OR(I376="Trabajo actualmente como empleado",I376="Trabajo de manera independiente"),CHOOSE(MOD(COUNTIF($I$2:I376,I376)-1,4)+1,"Menos de 3 meses","De 3 a 6 meses","De 7 a 12 meses","Más de un año"),"") -> De 3 a 6 meses | L376: =IF(OR(I376="Trabajo actualmente como empleado",I376="Trabajo de manera independiente"),CHOOSE(MOD(COUNTIF($I$2:I376,I376)-1,3)+1,"Sí, completamente","Parcialmente","No"),"") -> Sí, completamente | M376: =IF(OR(I376="Trabajo actualmente como empleado",I376="Trabajo de manera independiente"),CHOOSE(MOD(INT((COUNTIF($I$2:I376,I376)-1)/3),4)+1,"1- Muy satisfecho/a","2- Satisfecho/a","3- Insatisfecho/a","4- Muy insatisfecho/a"),"") -> 4- Muy insatisfecho/a | N376: =IF(OR(I376="Trabajo actualmente como empleado",I376="Trabajo de manera independiente"),_xlfn.LET(_xlpm.opcion,MOD(INT((COUNTIF($I$2:I376,I376)-1)/5),6)+1,CHOOSE(IF(AND(_xlpm.opcion=6,L376="Sí, completamente"),5,_xlpm.opcion),"Salario","Estabilidad laboral","Horario","Acceso a prestaciones","Oportunidades de crecimiento","Trabajar en un área relacionada con mi formación")),"") -> Oportunidades de crecimiento | O376: =IF(OR(I376="Trabajo actualmente como empleado",I376="Trabajo de manera independiente"),_xlfn.LET(_xlpm.turno,MOD(COUNTIF($I$2:I376,I376)-1,5),_xlpm.nivel,VALUE(LEFT(M376,1)),IF(_xlpm.turno=4,"No estoy seguro/a",IF(_xlpm.turno<IF(_xlpm.nivel<=2,1,3),"Sí","No"))),"") -> Sí | P376: =_xlfn.LET(_xlpm.perfil,I376,_xlpm.turno,COUNTIF($I$2:I376,_xlpm.perfil)-1,_xlpm.busca,OR(_xlpm.perfil="Actualmente no trabajo y estoy buscando empleo",_xlpm.perfil="Busco mi primer empleo"),_xlpm.trabaja,OR(_xlpm.perfil="Trabajo actualmente como empleado",_xlpm.perfil="Trabajo de manera independiente"),IF(_xlpm.busca,CHOOSE(MOD(_xlpm.turno*3,4)+1,"Menos de 1 mes","Entre 1 y 3 meses","Entre 4 y 6 meses","Más de 6 meses"),IF(OR(_xlpm.trabaja,_xlpm.perfil="Estudio y quiero comenzar a trabajar"),IF(AND(_xlpm.trabaja,O376="No"),"Todavía no he iniciado una búsqueda activa",CHOOSE(MOD(_xlpm.turno*3,5)+1,"Menos de 1 mes","Entre 1 y 3 meses","Entre 4 y 6 meses","Más de 6 meses","Todavía no he iniciado una búsqueda activa")),""))) -> Entre 1 y 3 meses | Q376: =IF(I376="Tengo un emprendimiento o quiero iniciar uno","",CHOOSE(MOD(INT((COUNTIF($I$2:I376,I376)-1)/7),3)+1,"Sí","No","Tengo una pero necesito actualizarla")) -> No | R376: =IF(I376="Tengo un emprendimiento o quiero iniciar uno","",IF(I376="Busco mi primer empleo","No",IF(MOD(COUNTIF($I$2:I376,I376)-1,2)=0,"Sí","No"))) -> No | S376: =IF(I376="Tengo un emprendimiento o quiero iniciar uno","",CHOOSE(MOD(INT((COUNTIF($I$2:I376,I376)-1)/3),10)+1,"Portales de empleo","Redes sociales","Familiares o conocidos","Empresas directamente","Ferias de empleo","Instituciones públicas","Institución educativa","No sé dónde buscar","Portales de empleo;Redes sociales","Familiares o conocidos;Empresas directamente")) -> Familiares o conocidos;Empresas directamente | T376: =IF(I376="Tengo un emprendimiento o quiero iniciar uno","",_xlfn.LET(_xlpm.opcion,MOD(INT((COUNTIF($I$2:I376,I376)-1)/4),6)+1,CHOOSE(IF(AND(_xlpm.opcion=3,Q376="Sí"),1,_xlpm.opcion),"Falta de experiencia","Falta de formación","Dificultades con la hoja de vida","Horarios disponibles","Transporte","Internet"))) -> Internet | U376: =IF(I376="Tengo un emprendimiento o quiero iniciar uno","",IF(MOD(INT((COUNTIF($I$2:I376,I376)-1)/3),2)=0,"Sí","No")) -> No | V376: =IF(I376="Tengo un emprendimiento o quiero iniciar uno",CHOOSE(MOD(COUNTIF($I$2:I376,I376)-1,3)+1,"Tengo un emprendimiento","Estoy iniciando un emprendimiento","Me interesa emprender"),"") | W376: =IF(V376="Tengo un emprendimiento","Funcionamiento estable",IF(V376="Estoy iniciando un emprendimiento","Inicio","")) | X376: =IF(I376="Tengo un emprendimiento o quiero iniciar uno",CHOOSE(MOD(COUNTIF($I$2:I376,I376)-1,5)+1,"Falta de financiación","Falta de conocimientos administrativos","Falta de conocimientos financieros","Falta de tiempo","Falta de herramientas"),"") | Y376: =IF(I376="Tengo un emprendimiento o quiero iniciar uno",X376,"") | Z376: =IF(I376="Tengo un emprendimiento o quiero iniciar uno",CHOOSE(INT(MOD((COUNTIF($I$2:I376,I376)-1)*7,39)/13)+1,"Sí","No","No conozco programas de ese tipo"),"") | AA376: =CHOOSE(INT(MOD((ROW()-2)*191,479)/120)+1,"No puedo hacerlo","Puedo hacerlo con ayuda","Puedo hacerlo con dificultad","Puedo hacerlo sin ayuda") -> No puedo hacerlo | AB376: =CHOOSE(INT(MOD((ROW()-2)*191,479)/120)+1,"No puedo hacerlo","Puedo hacerlo con ayuda","Puedo hacerlo con dificultad","Puedo hacerlo sin ayuda") -> No puedo hacerlo | AC376: =CHOOSE(INT(MOD((ROW()-2)*157+83,479)/120)+1,"No puedo hacerlo","Puedo hacerlo con ayuda","Puedo hacerlo con dificultad","Puedo hacerlo sin ayuda") -> Puedo hacerlo sin ayuda | AD376: =CHOOSE(INT(MOD((ROW()-2)*89+131,479)/120)+1,"No puedo hacerlo","Puedo hacerlo con ayuda","Puedo hacerlo con dificultad","Puedo hacerlo sin ayuda") -> Puedo hacerlo sin ayuda | AE376: =CHOOSE(INT(MOD((ROW()-2)*73+179,479)/120)+1,"No puedo hacerlo","Puedo hacerlo con ayuda","Puedo hacerlo con dificultad","Puedo hacerlo sin ayuda") -> Puedo hacerlo con ayuda | AF376: =CHOOSE(MOD((ROW()-2)*61+23,10)+1,"Crear una hoja de vida","Preparación para entrevista","Comunicación","Liderazgo","Emprendimiento","Herramientas digitales","Educación financiera","Crear una hoja de vida;Preparación para entrevista","Comunicación;Liderazgo","Herramientas digitales;Educación financiera") -> Crear una hoja de vida;Preparación para entrevista | AG376: =CHOOSE(MOD(INT((ROW()-2)/3)*7,9)+1,"Costos de transporte","Distancia","Horarios","Falta de experiencia","Falta de información","Ninguna","Costos de transporte;Distancia","Horarios;Falta de información","Falta de experiencia;Falta de información") -> Falta de información | AH376: =CHOOSE(INT(MOD((ROW()-2)*199+59,479)/120)+1,"Oficina de orientación laboral","Ferias de empleo","Programas de emprendimiento","No conozco ninguno") -> Programas de emprendimiento | AI376: =CHOOSE(INT(MOD((ROW()-2)*127+71,479)/120)+1,"Presencial","Virtual","Presencial y virtual","Me es indiferente") -> Virtual | AJ376: =CHOOSE(INT(MOD((ROW()-2)*163+97,479)/120)+1,"Diurno","Nocturno","Mañana entre semana","Fines de semana") -> Nocturno | AK376: =CHOOSE(INT(MOD((ROW()-2)*181+109,479)/120)+1,"WhatsApp","Correo electrónico","Redes sociales","Celular") -> Redes sociales
A377: ="SG"&TEXT(ROW()-1,"000") -> SG376 | B377: CENTROS POBLADOS Y RURAL | C377: SI, ACEPTO PARTICIPAR | D377: =IF(MOD((ROW()-2)*137,479)<230,"Masculino",IF(MOD((ROW()-2)*137,479)<460,"Femenino",IF(MOD((ROW()-2)*137,479)<470,"Otro","No quiero responder"))) -> Masculino | E377: =CHOOSE(MOD(ROW()-2,5)+1,"De 18 a 20 años","De 20 a 22 años","De 22 a 24 años","De 24 a 26 años","De 26 a 28 años") -> De 18 a 20 años | F377: =CHOOSE(MOD(ROW()-2,5)+1,18,20,22,24,26)+MOD(INT((ROW()-2)/5),IF(MOD(ROW()-2,5)=4,3,2)) -> 19 | G377: =IF(MOD(ROW()-371,2)=0,"Centro poblado","Rural") -> Centro poblado | H377: =_xlfn.LET(_xlpm.grupo,MOD(ROW()-2,5),_xlpm.turno,INT((ROW()-2)/5),_xlpm.orden,MOD(_xlpm.turno*37,IF(_xlpm.grupo=4,95,96)),CHOOSE(_xlpm.grupo+1,IF(_xlpm.orden<60,"Bachiller",IF(_xlpm.orden<84,"Técnico","Tecnólogo")),IF(_xlpm.orden<36,"Bachiller",IF(_xlpm.orden<66,"Técnico","Tecnólogo")),IF(_xlpm.orden<24,"Bachiller",IF(_xlpm.orden<48,"Técnico",IF(_xlpm.orden<72,"Tecnólogo","Profesional"))),IF(_xlpm.orden<12,"Bachiller",IF(_xlpm.orden<30,"Técnico",IF(_xlpm.orden<54,"Tecnólogo",IF(_xlpm.orden<90,"Profesional","Posgrado")))),IF(_xlpm.orden<10,"Bachiller",IF(_xlpm.orden<25,"Técnico",IF(_xlpm.orden<45,"Tecnólogo",IF(_xlpm.orden<85,"Profesional","Posgrado")))))) -> Tecnólogo | I377: =_xlfn.LET(_xlpm.orden,MOD((ROW()-2)*173,479),IF(_xlpm.orden<150,"Trabajo actualmente como empleado",IF(_xlpm.orden<230,"Trabajo de manera independiente",IF(_xlpm.orden<320,"Actualmente no trabajo y estoy buscando empleo",IF(_xlpm.orden<380,"Busco mi primer empleo",IF(_xlpm.orden<440,"Estudio y quiero comenzar a trabajar","Tengo un emprendimiento o quiero iniciar uno")))))) -> Trabajo de manera independiente | J377: =IF(I377="Trabajo actualmente como empleado",IF(MOD((COUNTIF($I$2:I377,"Trabajo actualmente como empleado")-1)*37,150)<100,"Empleado con contrato","Empleado sin contrato formal"),IF(I377="Trabajo de manera independiente","Trabajo independiente","")) -> Trabajo independiente | K377: =IF(OR(I377="Trabajo actualmente como empleado",I377="Trabajo de manera independiente"),CHOOSE(MOD(COUNTIF($I$2:I377,I377)-1,4)+1,"Menos de 3 meses","De 3 a 6 meses","De 7 a 12 meses","Más de un año"),"") -> Más de un año | L377: =IF(OR(I377="Trabajo actualmente como empleado",I377="Trabajo de manera independiente"),CHOOSE(MOD(COUNTIF($I$2:I377,I377)-1,3)+1,"Sí, completamente","Parcialmente","No"),"") -> Sí, completamente | M377: =IF(OR(I377="Trabajo actualmente como empleado",I377="Trabajo de manera independiente"),CHOOSE(MOD(INT((COUNTIF($I$2:I377,I377)-1)/3),4)+1,"1- Muy satisfecho/a","2- Satisfecho/a","3- Insatisfecho/a","4- Muy insatisfecho/a"),"") -> 2- Satisfecho/a | N377: =IF(OR(I377="Trabajo actualmente como empleado",I377="Trabajo de manera independiente"),_xlfn.LET(_xlpm.opcion,MOD(INT((COUNTIF($I$2:I377,I377)-1)/5),6)+1,CHOOSE(IF(AND(_xlpm.opcion=6,L377="Sí, completamente"),5,_xlpm.opcion),"Salario","Estabilidad laboral","Horario","Acceso a prestaciones","Oportunidades de crecimiento","Trabajar en un área relacionada con mi formación")),"") -> Salario | O377: =IF(OR(I377="Trabajo actualmente como empleado",I377="Trabajo de manera independiente"),_xlfn.LET(_xlpm.turno,MOD(COUNTIF($I$2:I377,I377)-1,5),_xlpm.nivel,VALUE(LEFT(M377,1)),IF(_xlpm.turno=4,"No estoy seguro/a",IF(_xlpm.turno<IF(_xlpm.nivel<=2,1,3),"Sí","No"))),"") -> No | P377: =_xlfn.LET(_xlpm.perfil,I377,_xlpm.turno,COUNTIF($I$2:I377,_xlpm.perfil)-1,_xlpm.busca,OR(_xlpm.perfil="Actualmente no trabajo y estoy buscando empleo",_xlpm.perfil="Busco mi primer empleo"),_xlpm.trabaja,OR(_xlpm.perfil="Trabajo actualmente como empleado",_xlpm.perfil="Trabajo de manera independiente"),IF(_xlpm.busca,CHOOSE(MOD(_xlpm.turno*3,4)+1,"Menos de 1 mes","Entre 1 y 3 meses","Entre 4 y 6 meses","Más de 6 meses"),IF(OR(_xlpm.trabaja,_xlpm.perfil="Estudio y quiero comenzar a trabajar"),IF(AND(_xlpm.trabaja,O377="No"),"Todavía no he iniciado una búsqueda activa",CHOOSE(MOD(_xlpm.turno*3,5)+1,"Menos de 1 mes","Entre 1 y 3 meses","Entre 4 y 6 meses","Más de 6 meses","Todavía no he iniciado una búsqueda activa")),""))) -> Todavía no he iniciado una búsqueda activa | Q377: =IF(I377="Tengo un emprendimiento o quiero iniciar uno","",CHOOSE(MOD(INT((COUNTIF($I$2:I377,I377)-1)/7),3)+1,"Sí","No","Tengo una pero necesito actualizarla")) -> Sí | R377: =IF(I377="Tengo un emprendimiento o quiero iniciar uno","",IF(I377="Busco mi primer empleo","No",IF(MOD(COUNTIF($I$2:I377,I377)-1,2)=0,"Sí","No"))) -> No | S377: =IF(I377="Tengo un emprendimiento o quiero iniciar uno","",CHOOSE(MOD(INT((COUNTIF($I$2:I377,I377)-1)/3),10)+1,"Portales de empleo","Redes sociales","Familiares o conocidos","Empresas directamente","Ferias de empleo","Instituciones públicas","Institución educativa","No sé dónde buscar","Portales de empleo;Redes sociales","Familiares o conocidos;Empresas directamente")) -> Redes sociales | T377: =IF(I377="Tengo un emprendimiento o quiero iniciar uno","",_xlfn.LET(_xlpm.opcion,MOD(INT((COUNTIF($I$2:I377,I377)-1)/4),6)+1,CHOOSE(IF(AND(_xlpm.opcion=3,Q377="Sí"),1,_xlpm.opcion),"Falta de experiencia","Falta de formación","Dificultades con la hoja de vida","Horarios disponibles","Transporte","Internet"))) -> Horarios disponibles | U377: =IF(I377="Tengo un emprendimiento o quiero iniciar uno","",IF(MOD(INT((COUNTIF($I$2:I377,I377)-1)/3),2)=0,"Sí","No")) -> No | V377: =IF(I377="Tengo un emprendimiento o quiero iniciar uno",CHOOSE(MOD(COUNTIF($I$2:I377,I377)-1,3)+1,"Tengo un emprendimiento","Estoy iniciando un emprendimiento","Me interesa emprender"),"") | W377: =IF(V377="Tengo un emprendimiento","Funcionamiento estable",IF(V377="Estoy iniciando un emprendimiento","Inicio","")) | X377: =IF(I377="Tengo un emprendimiento o quiero iniciar uno",CHOOSE(MOD(COUNTIF($I$2:I377,I377)-1,5)+1,"Falta de financiación","Falta de conocimientos administrativos","Falta de conocimientos financieros","Falta de tiempo","Falta de herramientas"),"") | Y377: =IF(I377="Tengo un emprendimiento o quiero iniciar uno",X377,"") | Z377: =IF(I377="Tengo un emprendimiento o quiero iniciar uno",CHOOSE(INT(MOD((COUNTIF($I$2:I377,I377)-1)*7,39)/13)+1,"Sí","No","No conozco programas de ese tipo"),"") | AA377: =CHOOSE(INT(MOD((ROW()-2)*191,479)/120)+1,"No puedo hacerlo","Puedo hacerlo con ayuda","Puedo hacerlo con dificultad","Puedo hacerlo sin ayuda") -> Puedo hacerlo con dificultad | AB377: =CHOOSE(INT(MOD((ROW()-2)*191,479)/120)+1,"No puedo hacerlo","Puedo hacerlo con ayuda","Puedo hacerlo con dificultad","Puedo hacerlo sin ayuda") -> Puedo hacerlo con dificultad | AC377: =CHOOSE(INT(MOD((ROW()-2)*157+83,479)/120)+1,"No puedo hacerlo","Puedo hacerlo con ayuda","Puedo hacerlo con dificultad","Puedo hacerlo sin ayuda") -> No puedo hacerlo | AD377: =CHOOSE(INT(MOD((ROW()-2)*89+131,479)/120)+1,"No puedo hacerlo","Puedo hacerlo con ayuda","Puedo hacerlo con dificultad","Puedo hacerlo sin ayuda") -> Puedo hacerlo sin ayuda | AE377: =CHOOSE(INT(MOD((ROW()-2)*73+179,479)/120)+1,"No puedo hacerlo","Puedo hacerlo con ayuda","Puedo hacerlo con dificultad","Puedo hacerlo sin ayuda") -> Puedo hacerlo con dificultad | AF377: =CHOOSE(MOD((ROW()-2)*61+23,10)+1,"Crear una hoja de vida","Preparación para entrevista","Comunicación","Liderazgo","Emprendimiento","Herramientas digitales","Educación financiera","Crear una hoja de vida;Preparación para entrevista","Comunicación;Liderazgo","Herramientas digitales;Educación financiera") -> Comunicación;Liderazgo | AG377: =CHOOSE(MOD(INT((ROW()-2)/3)*7,9)+1,"Costos de transporte","Distancia","Horarios","Falta de experiencia","Falta de información","Ninguna","Costos de transporte;Distancia","Horarios;Falta de información","Falta de experiencia;Falta de información") -> Horarios | AH377: =CHOOSE(INT(MOD((ROW()-2)*199+59,479)/120)+1,"Oficina de orientación laboral","Ferias de empleo","Programas de emprendimiento","No conozco ninguno") -> No conozco ninguno | AI377: =CHOOSE(INT(MOD((ROW()-2)*127+71,479)/120)+1,"Presencial","Virtual","Presencial y virtual","Me es indiferente") -> Presencial y virtual | AJ377: =CHOOSE(INT(MOD((ROW()-2)*163+97,479)/120)+1,"Diurno","Nocturno","Mañana entre semana","Fines de semana") -> Fines de semana | AK377: =CHOOSE(INT(MOD((ROW()-2)*181+109,479)/120)+1,"WhatsApp","Correo electrónico","Redes sociales","Celular") -> Celular
A378: ="SG"&TEXT(ROW()-1,"000") -> SG377 | B378: CENTROS POBLADOS Y RURAL | C378: SI, ACEPTO PARTICIPAR | D378: =IF(MOD((ROW()-2)*137,479)<230,"Masculino",IF(MOD((ROW()-2)*137,479)<460,"Femenino",IF(MOD((ROW()-2)*137,479)<470,"Otro","No quiero responder"))) -> Femenino | E378: =CHOOSE(MOD(ROW()-2,5)+1,"De 18 a 20 años","De 20 a 22 años","De 22 a 24 años","De 24 a 26 años","De 26 a 28 años") -> De 20 a 22 años | F378: =CHOOSE(MOD(ROW()-2,5)+1,18,20,22,24,26)+MOD(INT((ROW()-2)/5),IF(MOD(ROW()-2,5)=4,3,2)) -> 21 | G378: =IF(MOD(ROW()-371,2)=0,"Centro poblado","Rural") -> Rural | H378: =_xlfn.LET(_xlpm.grupo,MOD(ROW()-2,5),_xlpm.turno,INT((ROW()-2)/5),_xlpm.orden,MOD(_xlpm.turno*37,IF(_xlpm.grupo=4,95,96)),CHOOSE(_xlpm.grupo+1,IF(_xlpm.orden<60,"Bachiller",IF(_xlpm.orden<84,"Técnico","Tecnólogo")),IF(_xlpm.orden<36,"Bachiller",IF(_xlpm.orden<66,"Técnico","Tecnólogo")),IF(_xlpm.orden<24,"Bachiller",IF(_xlpm.orden<48,"Técnico",IF(_xlpm.orden<72,"Tecnólogo","Profesional"))),IF(_xlpm.orden<12,"Bachiller",IF(_xlpm.orden<30,"Técnico",IF(_xlpm.orden<54,"Tecnólogo",IF(_xlpm.orden<90,"Profesional","Posgrado")))),IF(_xlpm.orden<10,"Bachiller",IF(_xlpm.orden<25,"Técnico",IF(_xlpm.orden<45,"Tecnólogo",IF(_xlpm.orden<85,"Profesional","Posgrado")))))) -> Tecnólogo | I378: =_xlfn.LET(_xlpm.orden,MOD((ROW()-2)*173,479),IF(_xlpm.orden<150,"Trabajo actualmente como empleado",IF(_xlpm.orden<230,"Trabajo de manera independiente",IF(_xlpm.orden<320,"Actualmente no trabajo y estoy buscando empleo",IF(_xlpm.orden<380,"Busco mi primer empleo",IF(_xlpm.orden<440,"Estudio y quiero comenzar a trabajar","Tengo un emprendimiento o quiero iniciar uno")))))) -> Estudio y quiero comenzar a trabajar | J378: =IF(I378="Trabajo actualmente como empleado",IF(MOD((COUNTIF($I$2:I378,"Trabajo actualmente como empleado")-1)*37,150)<100,"Empleado con contrato","Empleado sin contrato formal"),IF(I378="Trabajo de manera independiente","Trabajo independiente","")) | K378: =IF(OR(I378="Trabajo actualmente como empleado",I378="Trabajo de manera independiente"),CHOOSE(MOD(COUNTIF($I$2:I378,I378)-1,4)+1,"Menos de 3 meses","De 3 a 6 meses","De 7 a 12 meses","Más de un año"),"") | L378: =IF(OR(I378="Trabajo actualmente como empleado",I378="Trabajo de manera independiente"),CHOOSE(MOD(COUNTIF($I$2:I378,I378)-1,3)+1,"Sí, completamente","Parcialmente","No"),"") | M378: =IF(OR(I378="Trabajo actualmente como empleado",I378="Trabajo de manera independiente"),CHOOSE(MOD(INT((COUNTIF($I$2:I378,I378)-1)/3),4)+1,"1- Muy satisfecho/a","2- Satisfecho/a","3- Insatisfecho/a","4- Muy insatisfecho/a"),"") | N378: =IF(OR(I378="Trabajo actualmente como empleado",I378="Trabajo de manera independiente"),_xlfn.LET(_xlpm.opcion,MOD(INT((COUNTIF($I$2:I378,I378)-1)/5),6)+1,CHOOSE(IF(AND(_xlpm.opcion=6,L378="Sí, completamente"),5,_xlpm.opcion),"Salario","Estabilidad laboral","Horario","Acceso a prestaciones","Oportunidades de crecimiento","Trabajar en un área relacionada con mi formación")),"") | O378: =IF(OR(I378="Trabajo actualmente como empleado",I378="Trabajo de manera independiente"),_xlfn.LET(_xlpm.turno,MOD(COUNTIF($I$2:I378,I378)-1,5),_xlpm.nivel,VALUE(LEFT(M378,1)),IF(_xlpm.turno=4,"No estoy seguro/a",IF(_xlpm.turno<IF(_xlpm.nivel<=2,1,3),"Sí","No"))),"") | P378: =_xlfn.LET(_xlpm.perfil,I378,_xlpm.turno,COUNTIF($I$2:I378,_xlpm.perfil)-1,_xlpm.busca,OR(_xlpm.perfil="Actualmente no trabajo y estoy buscando empleo",_xlpm.perfil="Busco mi primer empleo"),_xlpm.trabaja,OR(_xlpm.perfil="Trabajo actualmente como empleado",_xlpm.perfil="Trabajo de manera independiente"),IF(_xlpm.busca,CHOOSE(MOD(_xlpm.turno*3,4)+1,"Menos de 1 mes","Entre 1 y 3 meses","Entre 4 y 6 meses","Más de 6 meses"),IF(OR(_xlpm.trabaja,_xlpm.perfil="Estudio y quiero comenzar a trabajar"),IF(AND(_xlpm.trabaja,O378="No"),"Todavía no he iniciado una búsqueda activa",CHOOSE(MOD(_xlpm.turno*3,5)+1,"Menos de 1 mes","Entre 1 y 3 meses","Entre 4 y 6 meses","Más de 6 meses","Todavía no he iniciado una búsqueda activa")),""))) -> Menos de 1 mes | Q378: =IF(I378="Tengo un emprendimiento o quiero iniciar uno","",CHOOSE(MOD(INT((COUNTIF($I$2:I378,I378)-1)/7),3)+1,"Sí","No","Tengo una pero necesito actualizarla")) -> Sí | R378: =IF(I378="Tengo un emprendimiento o quiero iniciar uno","",IF(I378="Busco mi primer empleo","No",IF(MOD(COUNTIF($I$2:I378,I378)-1,2)=0,"Sí","No"))) -> No | S378: =IF(I378="Tengo un emprendimiento o quiero iniciar uno","",CHOOSE(MOD(INT((COUNTIF($I$2:I378,I378)-1)/3),10)+1,"Portales de empleo","Redes sociales","Familiares o conocidos","Empresas directamente","Ferias de empleo","Instituciones públicas","Institución educativa","No sé dónde buscar","Portales de empleo;Redes sociales","Familiares o conocidos;Empresas directamente")) -> Instituciones públicas | T378: =IF(I378="Tengo un emprendimiento o quiero iniciar uno","",_xlfn.LET(_xlpm.opcion,MOD(INT((COUNTIF($I$2:I378,I378)-1)/4),6)+1,CHOOSE(IF(AND(_xlpm.opcion=3,Q378="Sí"),1,_xlpm.opcion),"Falta de experiencia","Falta de formación","Dificultades con la hoja de vida","Horarios disponibles","Transporte","Internet"))) -> Internet | U378: =IF(I378="Tengo un emprendimiento o quiero iniciar uno","",IF(MOD(INT((COUNTIF($I$2:I378,I378)-1)/3),2)=0,"Sí","No")) -> No | V378: =IF(I378="Tengo un emprendimiento o quiero iniciar uno",CHOOSE(MOD(COUNTIF($I$2:I378,I378)-1,3)+1,"Tengo un emprendimiento","Estoy iniciando un emprendimiento","Me interesa emprender"),"") | W378: =IF(V378="Tengo un emprendimiento","Funcionamiento estable",IF(V378="Estoy iniciando un emprendimiento","Inicio","")) | X378: =IF(I378="Tengo un emprendimiento o quiero iniciar uno",CHOOSE(MOD(COUNTIF($I$2:I378,I378)-1,5)+1,"Falta de financiación","Falta de conocimientos administrativos","Falta de conocimientos financieros","Falta de tiempo","Falta de herramientas"),"") | Y378: =IF(I378="Tengo un emprendimiento o quiero iniciar uno",X378,"") | Z378: =IF(I378="Tengo un emprendimiento o quiero iniciar uno",CHOOSE(INT(MOD((COUNTIF($I$2:I378,I378)-1)*7,39)/13)+1,"Sí","No","No conozco programas de ese tipo"),"") | AA378: =CHOOSE(INT(MOD((ROW()-2)*191,479)/120)+1,"No puedo hacerlo","Puedo hacerlo con ayuda","Puedo hacerlo con dificultad","Puedo hacerlo sin ayuda") -> Puedo hacerlo sin ayuda | AB378: =CHOOSE(INT(MOD((ROW()-2)*191,479)/120)+1,"No puedo hacerlo","Puedo hacerlo con ayuda","Puedo hacerlo con dificultad","Puedo hacerlo sin ayuda") -> Puedo hacerlo sin ayuda | AC378: =CHOOSE(INT(MOD((ROW()-2)*157+83,479)/120)+1,"No puedo hacerlo","Puedo hacerlo con ayuda","Puedo hacerlo con dificultad","Puedo hacerlo sin ayuda") -> Puedo hacerlo con ayuda | AD378: =CHOOSE(INT(MOD((ROW()-2)*89+131,479)/120)+1,"No puedo hacerlo","Puedo hacerlo con ayuda","Puedo hacerlo con dificultad","Puedo hacerlo sin ayuda") -> No puedo hacerlo | AE378: =CHOOSE(INT(MOD((ROW()-2)*73+179,479)/120)+1,"No puedo hacerlo","Puedo hacerlo con ayuda","Puedo hacerlo con dificultad","Puedo hacerlo sin ayuda") -> Puedo hacerlo con dificultad | AF378: =CHOOSE(MOD((ROW()-2)*61+23,10)+1,"Crear una hoja de vida","Preparación para entrevista","Comunicación","Liderazgo","Emprendimiento","Herramientas digitales","Educación financiera","Crear una hoja de vida;Preparación para entrevista","Comunicación;Liderazgo","Herramientas digitales;Educación financiera") -> Herramientas digitales;Educación financiera | AG378: =CHOOSE(MOD(INT((ROW()-2)/3)*7,9)+1,"Costos de transporte","Distancia","Horarios","Falta de experiencia","Falta de información","Ninguna","Costos de transporte;Distancia","Horarios;Falta de información","Falta de experiencia;Falta de información") -> Horarios | AH378: =CHOOSE(INT(MOD((ROW()-2)*199+59,479)/120)+1,"Oficina de orientación laboral","Ferias de empleo","Programas de emprendimiento","No conozco ninguno") -> Ferias de empleo | AI378: =CHOOSE(INT(MOD((ROW()-2)*127+71,479)/120)+1,"Presencial","Virtual","Presencial y virtual","Me es indiferente") -> Me es indiferente | AJ378: =CHOOSE(INT(MOD((ROW()-2)*163+97,479)/120)+1,"Diurno","Nocturno","Mañana entre semana","Fines de semana") -> Diurno | AK378: =CHOOSE(INT(MOD((ROW()-2)*181+109,479)/120)+1,"WhatsApp","Correo electrónico","Redes sociales","Celular") -> Correo electrónico
A379: ="SG"&TEXT(ROW()-1,"000") -> SG378 | B379: CENTROS POBLADOS Y RURAL | C379: SI, ACEPTO PARTICIPAR | D379: =IF(MOD((ROW()-2)*137,479)<230,"Masculino",IF(MOD((ROW()-2)*137,479)<460,"Femenino",IF(MOD((ROW()-2)*137,479)<470,"Otro","No quiero responder"))) -> Femenino | E379: =CHOOSE(MOD(ROW()-2,5)+1,"De 18 a 20 años","De 20 a 22 años","De 22 a 24 años","De 24 a 26 años","De 26 a 28 años") -> De 22 a 24 años | F379: =CHOOSE(MOD(ROW()-2,5)+1,18,20,22,24,26)+MOD(INT((ROW()-2)/5),IF(MOD(ROW()-2,5)=4,3,2)) -> 23 | G379: =IF(MOD(ROW()-371,2)=0,"Centro poblado","Rural") -> Centro poblado | H379: =_xlfn.LET(_xlpm.grupo,MOD(ROW()-2,5),_xlpm.turno,INT((ROW()-2)/5),_xlpm.orden,MOD(_xlpm.turno*37,IF(_xlpm.grupo=4,95,96)),CHOOSE(_xlpm.grupo+1,IF(_xlpm.orden<60,"Bachiller",IF(_xlpm.orden<84,"Técnico","Tecnólogo")),IF(_xlpm.orden<36,"Bachiller",IF(_xlpm.orden<66,"Técnico","Tecnólogo")),IF(_xlpm.orden<24,"Bachiller",IF(_xlpm.orden<48,"Técnico",IF(_xlpm.orden<72,"Tecnólogo","Profesional"))),IF(_xlpm.orden<12,"Bachiller",IF(_xlpm.orden<30,"Técnico",IF(_xlpm.orden<54,"Tecnólogo",IF(_xlpm.orden<90,"Profesional","Posgrado")))),IF(_xlpm.orden<10,"Bachiller",IF(_xlpm.orden<25,"Técnico",IF(_xlpm.orden<45,"Tecnólogo",IF(_xlpm.orden<85,"Profesional","Posgrado")))))) -> Profesional | I379: =_xlfn.LET(_xlpm.orden,MOD((ROW()-2)*173,479),IF(_xlpm.orden<150,"Trabajo actualmente como empleado",IF(_xlpm.orden<230,"Trabajo de manera independiente",IF(_xlpm.orden<320,"Actualmente no trabajo y estoy buscando empleo",IF(_xlpm.orden<380,"Busco mi primer empleo",IF(_xlpm.orden<440,"Estudio y quiero comenzar a trabajar","Tengo un emprendimiento o quiero iniciar uno")))))) -> Trabajo actualmente como empleado | J379: =IF(I379="Trabajo actualmente como empleado",IF(MOD((COUNTIF($I$2:I379,"Trabajo actualmente como empleado")-1)*37,150)<100,"Empleado con contrato","Empleado sin contrato formal"),IF(I379="Trabajo de manera independiente","Trabajo independiente","")) -> Empleado con contrato | K379: =IF(OR(I379="Trabajo actualmente como empleado",I379="Trabajo de manera independiente"),CHOOSE(MOD(COUNTIF($I$2:I379,I379)-1,4)+1,"Menos de 3 meses","De 3 a 6 meses","De 7 a 12 meses","Más de un año"),"") -> De 7 a 12 meses | L379: =IF(OR(I379="Trabajo actualmente como empleado",I379="Trabajo de manera independiente"),CHOOSE(MOD(COUNTIF($I$2:I379,I379)-1,3)+1,"Sí, completamente","Parcialmente","No"),"") -> Parcialmente | M379: =IF(OR(I379="Trabajo actualmente como empleado",I379="Trabajo de manera independiente"),CHOOSE(MOD(INT((COUNTIF($I$2:I379,I379)-1)/3),4)+1,"1- Muy satisfecho/a","2- Satisfecho/a","3- Insatisfecho/a","4- Muy insatisfecho/a"),"") -> 4- Muy insatisfecho/a | N379: =IF(OR(I379="Trabajo actualmente como empleado",I379="Trabajo de manera independiente"),_xlfn.LET(_xlpm.opcion,MOD(INT((COUNTIF($I$2:I379,I379)-1)/5),6)+1,CHOOSE(IF(AND(_xlpm.opcion=6,L379="Sí, completamente"),5,_xlpm.opcion),"Salario","Estabilidad laboral","Horario","Acceso a prestaciones","Oportunidades de crecimiento","Trabajar en un área relacionada con mi formación")),"") -> Trabajar en un área relacionada con mi formación | O379: =IF(OR(I379="Trabajo actualmente como empleado",I379="Trabajo de manera independiente"),_xlfn.LET(_xlpm.turno,MOD(COUNTIF($I$2:I379,I379)-1,5),_xlpm.nivel,VALUE(LEFT(M379,1)),IF(_xlpm.turno=4,"No estoy seguro/a",IF(_xlpm.turno<IF(_xlpm.nivel<=2,1,3),"Sí","No"))),"") -> No | P379: =_xlfn.LET(_xlpm.perfil,I379,_xlpm.turno,COUNTIF($I$2:I379,_xlpm.perfil)-1,_xlpm.busca,OR(_xlpm.perfil="Actualmente no trabajo y estoy buscando empleo",_xlpm.perfil="Busco mi primer empleo"),_xlpm.trabaja,OR(_xlpm.perfil="Trabajo actualmente como empleado",_xlpm.perfil="Trabajo de manera independiente"),IF(_xlpm.busca,CHOOSE(MOD(_xlpm.turno*3,4)+1,"Menos de 1 mes","Entre 1 y 3 meses","Entre 4 y 6 meses","Más de 6 meses"),IF(OR(_xlpm.trabaja,_xlpm.perfil="Estudio y quiero comenzar a trabajar"),IF(AND(_xlpm.trabaja,O379="No"),"Todavía no he iniciado una búsqueda activa",CHOOSE(MOD(_xlpm.turno*3,5)+1,"Menos de 1 mes","Entre 1 y 3 meses","Entre 4 y 6 meses","Más de 6 meses","Todavía no he iniciado una búsqueda activa")),""))) -> Todavía no he iniciado una búsqueda activa | Q379: =IF(I379="Tengo un emprendimiento o quiero iniciar uno","",CHOOSE(MOD(INT((COUNTIF($I$2:I379,I379)-1)/7),3)+1,"Sí","No","Tengo una pero necesito actualizarla")) -> No | R379: =IF(I379="Tengo un emprendimiento o quiero iniciar uno","",IF(I379="Busco mi primer empleo","No",IF(MOD(COUNTIF($I$2:I379,I379)-1,2)=0,"Sí","No"))) -> Sí | S379: =IF(I379="Tengo un emprendimiento o quiero iniciar uno","",CHOOSE(MOD(INT((COUNTIF($I$2:I379,I379)-1)/3),10)+1,"Portales de empleo","Redes sociales","Familiares o conocidos","Empresas directamente","Ferias de empleo","Instituciones públicas","Institución educativa","No sé dónde buscar","Portales de empleo;Redes sociales","Familiares o conocidos;Empresas directamente")) -> Familiares o conocidos;Empresas directamente | T379: =IF(I379="Tengo un emprendimiento o quiero iniciar uno","",_xlfn.LET(_xlpm.opcion,MOD(INT((COUNTIF($I$2:I379,I379)-1)/4),6)+1,CHOOSE(IF(AND(_xlpm.opcion=3,Q379="Sí"),1,_xlpm.opcion),"Falta de experiencia","Falta de formación","Dificultades con la hoja de vida","Horarios disponibles","Transporte","Internet"))) -> Internet | U379: =IF(I379="Tengo un emprendimiento o quiero iniciar uno","",IF(MOD(INT((COUNTIF($I$2:I379,I379)-1)/3),2)=0,"Sí","No")) -> No | V379: =IF(I379="Tengo un emprendimiento o quiero iniciar uno",CHOOSE(MOD(COUNTIF($I$2:I379,I379)-1,3)+1,"Tengo un emprendimiento","Estoy iniciando un emprendimiento","Me interesa emprender"),"") | W379: =IF(V379="Tengo un emprendimiento","Funcionamiento estable",IF(V379="Estoy iniciando un emprendimiento","Inicio","")) | X379: =IF(I379="Tengo un emprendimiento o quiero iniciar uno",CHOOSE(MOD(COUNTIF($I$2:I379,I379)-1,5)+1,"Falta de financiación","Falta de conocimientos administrativos","Falta de conocimientos financieros","Falta de tiempo","Falta de herramientas"),"") | Y379: =IF(I379="Tengo un emprendimiento o quiero iniciar uno",X379,"") | Z379: =IF(I379="Tengo un emprendimiento o quiero iniciar uno",CHOOSE(INT(MOD((COUNTIF($I$2:I379,I379)-1)*7,39)/13)+1,"Sí","No","No conozco programas de ese tipo"),"") | AA379: =CHOOSE(INT(MOD((ROW()-2)*191,479)/120)+1,"No puedo hacerlo","Puedo hacerlo con ayuda","Puedo hacerlo con dificultad","Puedo hacerlo sin ayuda") -> Puedo hacerlo con ayuda | AB379: =CHOOSE(INT(MOD((ROW()-2)*191,479)/120)+1,"No puedo hacerlo","Puedo hacerlo con ayuda","Puedo hacerlo con dificultad","Puedo hacerlo sin ayuda") -> Puedo hacerlo con ayuda | AC379: =CHOOSE(INT(MOD((ROW()-2)*157+83,479)/120)+1,"No puedo hacerlo","Puedo hacerlo con ayuda","Puedo hacerlo con dificultad","Puedo hacerlo sin ayuda") -> Puedo hacerlo con dificultad | AD379: =CHOOSE(INT(MOD((ROW()-2)*89+131,479)/120)+1,"No puedo hacerlo","Puedo hacerlo con ayuda","Puedo hacerlo con dificultad","Puedo hacerlo sin ayuda") -> Puedo hacerlo con ayuda | AE379: =CHOOSE(INT(MOD((ROW()-2)*73+179,479)/120)+1,"No puedo hacerlo","Puedo hacerlo con ayuda","Puedo hacerlo con dificultad","Puedo hacerlo sin ayuda") -> Puedo hacerlo sin ayuda | AF379: =CHOOSE(MOD((ROW()-2)*61+23,10)+1,"Crear una hoja de vida","Preparación para entrevista","Comunicación","Liderazgo","Emprendimiento","Herramientas digitales","Educación financiera","Crear una hoja de vida;Preparación para entrevista","Comunicación;Liderazgo","Herramientas digitales;Educación financiera") -> Crear una hoja de vida | AG379: =CHOOSE(MOD(INT((ROW()-2)/3)*7,9)+1,"Costos de transporte","Distancia","Horarios","Falta de experiencia","Falta de información","Ninguna","Costos de transporte;Distancia","Horarios;Falta de información","Falta de experiencia;Falta de información") -> Horarios | AH379: =CHOOSE(INT(MOD((ROW()-2)*199+59,479)/120)+1,"Oficina de orientación laboral","Ferias de empleo","Programas de emprendimiento","No conozco ninguno") -> Programas de emprendimiento | AI379: =CHOOSE(INT(MOD((ROW()-2)*127+71,479)/120)+1,"Presencial","Virtual","Presencial y virtual","Me es indiferente") -> Presencial | AJ379: =CHOOSE(INT(MOD((ROW()-2)*163+97,479)/120)+1,"Diurno","Nocturno","Mañana entre semana","Fines de semana") -> Nocturno | AK379: =CHOOSE(INT(MOD((ROW()-2)*181+109,479)/120)+1,"WhatsApp","Correo electrónico","Redes sociales","Celular") -> Redes sociales
